Workbook
Name _______bot1: #REF!
Name _______bot3: #REF!
Name _______bot4: #REF!
Name _______bot5: #REF!
Name _______bot6: #REF!
Name _______top1: #REF!
Name _______top2: #REF!
Name _______top3: #REF!
Name _______top4: #REF!
Name _______top5: #REF!
Name _______top6: #REF!
Name ______bot2: #REF!
Name _____bot1: #REF!
Name _____bot3: #REF!
Name _____bot4: #REF!
Name _____bot5: #REF!
Name _____bot6: #REF!
Name _____top1: #REF!
Name _____top2: #REF!
Name _____top3: #REF!
Name _____top4: #REF!
Name _____top5: #REF!
Name _____top6: #REF!
Name ____bot1: #REF!
Name ____bot2: #REF!
Name ____bot3: #REF!
Name ____bot4: #REF!
Name ____bot5: #REF!
Name ____bot6: #REF!
Name ____top1: #REF!
Name ____top2: #REF!
Name ____top3: #REF!
Name ____top4: #REF!
Name ____top5: #REF!
Name ____top6: #REF!
Name ___bot1: #REF!
Name ___bot2: #REF!
Name ___bot3: #REF!
Name ___bot4: #REF!
Name ___bot5: #REF!
Name ___bot6: #REF!
Name ___top1: #REF!
Name ___top2: #REF!
Name ___top3: #REF!
Name ___top4: #REF!
Name ___top5: #REF!
Name ___top6: #REF!
Name __bot1: #REF!
Name __bot2: #REF!
Name __bot3: #REF!
Name __bot4: #REF!
Name __bot5: #REF!
Name __bot6: #REF!
Name __top1: #REF!
Name __top2: #REF!
Name __top3: #REF!
Name __top4: #REF!
Name __top5: #REF!
Name __top6: #REF!
Name _bot1: #REF!

Sheet How to update
B2: How to update
B3: 1. | C3: Navigate to the tabs included in the 'Data Links' tab at the bottom of this spreadsheet
B4: 2. | C4: Starting with the first link, download the data and open the downloaded spreadsheet
B5: 3. | C5: In the downloaded spreadsheet, find the tab that contains the same data as the tab in this spreadsheet that you are trying to update and copy all of the data and only the data
B6: 4. | C6: Line the first month of the copied data up with the first month in the tab you are hoping to update and paste the new data on top of it, overwriting the old data (i.e. July 2014 should be pasted on top of July 2014)
B7: 5. | C7: Repeat for all tabs until the spreadsheet is completely updated
B8: 6. | C8: Do a quick comparison with the ONS published stats to make sure all the formulas are pulling through correctly
B9: 7. | C9: To update the dashboard, ensure the yellow date box in the top left hand corner of the dashboard tab is set to the correct value

Sheet Data links
B2: Tab | C2: Data link (August - Make sure to download most recent month!!!)
B3: 1. Payrolled employees | C3: https://www.ons.gov.uk/employmentandlabourmarket/peopleinwork/earningsandworkinghours/datasets/realtimeinformationstatisticsreferencetableseasonallyadjusted
B4: 23. Employees Industry
B5: 2, 5, 10, 11, 13, 15, 18, 20, 21 | C5: A01: Summary of labour market statistics - Office for National Statistics
B6: 1 UK (Claimant count) | C6: CLA01: Claimant Count - Office for National Statistics
B7: Real Average Weekly Earnings (using CPI) | C7: X09: Real average weekly earnings using consumer price inflation (seasonally adjusted) - Office for National Statistics
B8: Redundancies | C8: HR1: Potential redundancies - Office for National Statistics
B9: Labour market flows | C9: X02: Labour Force Survey flows estimates

Sheet Dashboard
B1: Aug-Oct | L1: Dropdowns: | M1: Month | N1: Offset Count | O1: Year
A2: Year | B2: 2025 | M2: Nov-Jan | N2: 13 | O2: 2022
A3: Offset factor | B3: =((VLOOKUP(B1,$M$2:$N$13, 2, FALSE)-0)+((Dashboard!B2-2024)*12)) -> 34 | M3: Dec-Feb | N3: =N2+1 -> 14 | O3: 2023
M4: Jan-Mar | N4: =N3+1 -> 15 | O4: 2024
B5: ="Key Metrics, "&B1&" "&B2 -> Key Metrics, Aug-Oct 2025 | D5: Current | E5: Change on quarter | F5: Change on the year | G5: Change since Covid-20 | I5: Good or Bad' formatting? | K5: For data showing percentage point change | M5: Feb-Apr | N5: =N4+1 -> 16 | O5: 2025
B6: Employment (000s) 16+ | D6: =OFFSET('2'!$B$385,$B$3,0) -> 34226340 | E6: ='2'!J6 -> -60087.846 | F6: ='2'!J7 -> 255911.47 | G6: ='2'!J8 -> 672666.1 | I6: Minus = Bad | M6: Mar-May | N6: =N5+1 -> 17 | O6: 2026
B7: Employment rate (16-64) | D7: =OFFSET('2'!$K$385,$B$3,0)/100 -> 0.74915831 | E7: ='2'!K6 -> -0.25826284 | F7: ='2'!K7 -> 0.013358069 | G7: ='2'!K8 -> -1.5750361 | I7: Minus = Bad | K7: Add 'pp' in brief | M7: Apr-Jun | N7: =N6+1 -> 18 | O7: 2027
B8: Unemployment, 16+ (000s) | D8: =OFFSET('2'!$D$385,$B$3,0) -> 1831890.1 | E8: ='2'!D6 -> 157870.54 | F8: ='2'!D7 -> 326867.79 | G8: ='2'!D8 -> 468168.17 | I8: Minus = Good | M8: May-Jul | N8: =N7+1 -> 19 | O8: 2028
B9: Unemployment rate, 16+ | D9: =OFFSET('2'!$E$385,$B$3,0)/100 -> 0.050803661 | E9: ='2'!E6 -> 0.41951154 | F9: ='2'!E7 -> 0.81482364 | G9: ='2'!E8 -> 1.1327015 | I9: Minus = Good | K9: Add 'pp' in brief | M9: Jun-Aug | N9: =N8+1 -> 20 | O9: 2029
B10: Economic inactivity (000s) (16-64) | D10: =OFFSET('2'!$P$385,$B$3,0) -> 9098658.3 | E10: ='2'!P6 -> -25615.944 | F10: ='2'!P7 -> -234336.28 | G10: ='2'!P8 -> 652867.86 | I10: Minus = Good | M10: Jul-Sep | N10: =N9+1 -> 21 | O10: 2030
B11: Economic inactivity rate (16-64) | D11: =OFFSET('2'!$Q$385,$B$3,0)/100 -> 0.20981876 | E11: ='2'!Q6 -> -0.092627813 | F11: ='2'!Q7 -> -0.70740664 | G11: ='2'!Q8 -> 0.67560951 | I11: Minus = Good | K11: Add 'pp' in brief | M11: Aug-Oct | N11: =N10+1 -> 22
B12: 50-64s inactivity (000s) | D12: =OFFSET('2'!$BD$385,$B$3,0) -> 3457561.5 | E12: ='2'!BD6 -> -10258.327 | F12: ='2'!BD7 -> -90729.299 | G12: ='2'!BD8 -> 227915.35 | I12: Minus = Good | M12: Sep-Nov | N12: =N11+1 -> 23
B13: 50-64s inactivity rate | D13: =OFFSET('2'!$BE$385,$B$3,0)/100 -> 0.26131915 | E13: ='2'!BE6 -> -0.0437376 | F13: ='2'!BE7 -> -0.61936257 | G13: ='2'!BE8 -> 1.021681 | I13: Minus = Good | K13: Add 'pp' in brief | M13: Oct-Dec | N13: =N12+1 -> 24
B14: Provisional December 2024 HMRC Payroll employees (000s) | D14: =OFFSET('1. Payrolled employees (UK)'!B113,$B$3,0) -> 30256482 | E14: ='1. Payrolled employees (UK)'!D2 -> -49095.667 | F14: ='1. Payrolled employees (UK)'!E2 -> -142627 | G14: ='1. Payrolled employees (UK)'!F2 -> 1259184.3 | I14: Minus = Bad
A15: *note: covid period is different (Jan-Mar) due to reporting periods | B15: Provisional Nov 2024-Jan 2025 Vacancies (000s) | D15: =OFFSET('20'!C276,$B$3,0) -> 729 | E15: ='20'!B3 -> -2 | F15: ='20'!B4 -> -78 | G15: ='20'!B5 -> -66 | I15: Do not format
B16: Wage growth in cash terms (total pay, including bonuses, yearly % change) | C16: Change in annual earnings | D16: =OFFSET('13'!D293, $B$3,0)/100 -> 0.047190575 | E16: ='13'!B5 -> 523.61043 | F16: ='13'!B6 -> 1722.8963 | G16: ='13'!B7 -> 9895.5919 | I16: Minus = Bad
B17: Wage growth adjusted for inflation (total pay, including bonuses, yearly % change) | D17: =OFFSET('AWE Real_CPI'!E292,$B$3,0)/100 -> 0.0096785559 | E17: ='AWE Real_CPI'!B3 -> 142.57626 | F17: ='AWE Real_CPI'!B4 -> 263.19994 | G17: ='AWE Real_CPI'!B5 -> 1529.8116 | I17: Minus = Bad

Sheet 1. Payrolled employees (UK)
B1: Current | C1: Change on month (singular) | D1: Change on quarter | E1: Change year on year | F1: Change since Covid-19 | G1: Change since 2024 election | H1: Change since coming into office | I1: Change since start of the year | J1: Max
A2: Number | B2: =AVERAGE(OFFSET(INDEX($B$11:$B$1048576,COUNTA($B$11:$B$1048576)),-2,0,3,1)) -> 30289110 | C2: {=INDEX($B$11:$B$1048576,COUNTA($B$11:$B$1048576))-INDEX($B$11:$B$1048576,COUNTA($B$11:$B$1048576)-1)} -> -37996 | D2: =AVERAGE(OFFSET(INDEX($B$11:$B$1048576,COUNTA($B$11:$B$1048576)),-2,0,3,1))-AVERAGE(OFFSET(INDEX($B$11:$B$1048576,COUNTA($B$11:$B$1048576)),-5,0,3,1)) -> -49095.667 | E2: =AVERAGE(OFFSET(INDEX($B$11:$B$1048576,COUNTA($B$11:$B$1048576)),-2,0,3,1))-AVERAGE(OFFSET(INDEX($B$11:$B$1048576,COUNTA($B$11:$B$1048576)),-14,0,3,1)) -> -142627 | F2: =AVERAGE(OFFSET(INDEX($B$11:$B$1048576,COUNTA($B$11:$B$1048576)),-2,0,3,1))-AVERAGE($B$76:$B$78) -> 1259184.3 | G2: =AVERAGE(OFFSET(INDEX($B$11:$B$1048576,COUNTA($B$11:$B$1048576)),-2,0,3,1))-AVERAGE($B$128:$B$130) -> -139202.67 | H2: {=INDEX($B$11:$B$1048576,COUNTA($B$11:$B$1048576))-$B$130} -> -187431 | I2: {=INDEX(B$11:B$1048576,COUNTA(B$11:B$1048576))-_xlfn.XLOOKUP("January " & TEXT(TODAY(),"yyyy"),A$11:A$1048576,B$11:B$1048576)} -> -154900 | J2: =MAX($B$11:$B$1048576) -> 30450219
A3: % | C3: {=INDEX($B$11:$B$1048576,COUNTA($B$11:$B$1048576))/INDEX($B$11:$B$1048576,COUNTA($B$11:$B$1048576)-1)-1} -> -0.001254222 | D3: =AVERAGE(OFFSET(INDEX($B$11:$B$1048576,COUNTA($B$11:$B$1048576)),-2,0,3,1))/AVERAGE(OFFSET(INDEX($B$11:$B$1048576,COUNTA($B$11:$B$1048576)),-5,0,3,1))-1 -> -0.0016182785 | E3: =AVERAGE(OFFSET(INDEX($B$11:$B$1048576,COUNTA($B$11:$B$1048576)),-2,0,3,1))/AVERAGE(OFFSET(INDEX($B$11:$B$1048576,COUNTA($B$11:$B$1048576)),-14,0,3,1))-1 -> -0.0046867848 | F3: {=INDEX($B$11:$B$1048576,COUNTA($B$11:$B$1048576))/AVERAGE($B$76:$B$78)-1} -> 0.042251458 | G3: =AVERAGE(OFFSET(INDEX($B$11:$B$1048576,COUNTA($B$11:$B$1048576)),-2,0,3,1))/AVERAGE($B$128:$B$130)-1 -> -0.0045747745 | H3: {=INDEX($B$11:$B$1048576,COUNTA($B$11:$B$1048576))/$B$130-1} -> -0.0061566002 | I3: {=INDEX(B$11:B$1048576,COUNTA(B$11:B$1048576))/_xlfn.XLOOKUP("January " & TEXT(TODAY(),"yyyy"),A$11:A$1048576,B$11:B$1048576)-1} -> -0.0050934877
A5: 1. Payrolled employee counts from PAYE RTI
A6: UK, all industries, seasonally adjusted
A8: Units | B8: Payrolled employees
A10: Date | B10: Payrolled employees | C10: Change on previous month
A11: July 2014 | B11: 26762113
A12: August 2014 | B12: 26837223 | C12: 75110
A13: September 2014 | B13: 26892127 | C13: 54904
A14: October 2014 | B14: 26906169 | C14: 14042
A15: November 2014 | B15: 27000958 | C15: 94789
A16: December 2014 | B16: 26998286 | C16: -2672
A17: January 2015 | B17: 27157573 | C17: 159287
A18: February 2015 | B18: 27214499 | C18: 56926
A19: March 2015 | B19: 27294543 | C19: 80044
A20: April 2015 | B20: 27340654 | C20: 46111
A21: May 2015 | B21: 27398974 | C21: 58320
A22: June 2015 | B22: 27461315 | C22: 62341
A23: July 2015 | B23: 27519284 | C23: 57969
... A77: January 2020 | B77: 29054506 | C77: 59878
A78: February 2020 | B78: 29040642 | C78: -13864 | E78: =AVERAGE(B76:B78) -> 29029925
A79: March 2020 | B79: 29015447 | C79: -25195 | E79: =AVERAGE(B143:B145) -> 30331906
A80: April 2020 | B80: 28561484 | C80: -453963 | E80: =E79-E78 -> 1301980.3
A81: May 2020 | B81: 28406852 | C81: -154632
A82: June 2020 | B82: 28352191 | C82: -54661
A83: July 2020 | B83: 28321060 | C83: -31131
A84: August 2020 | B84: 28256016 | C84: -65044
A85: September 2020 | B85: 28193180 | C85: -62836
A86: October 2020 | B86: 28162587 | C86: -30593
A87: November 2020 | B87: 28086479 | C87: -76108
A88: December 2020 | B88: 28124206 | C88: 37727
A89: January 2021 | B89: 28164763 | C89: 40557
A90: February 2021 | B90: 28159854 | C90: -4909
A91: March 2021 | B91: 28207157 | C91: 47303
A92: April 2021 | B92: 28318611 | C92: 111454
... A144: August 2025 | B144: 30344181 | C144: 9014
A145: September 2025 | B145: 30316369 | C145: -27812 | H145: =F145/B145 -> 0
A146: October 2025 | B146: 30294478 | C146: -21891
A147: November 2025 | B147: 30256482 | C147: -37996

Sheet 23. Employees Industry
A1: Yearly change | B1: Agriculture, forestry and fishing | C1: Mining and quarrying | D1: Manufacturing | E1: Energy production and supply | F1: Water supply, sewerage and waste | G1: Construction | H1: Wholesale and retail; repair of motor vehicles | I1: Transportation and storage | J1: Accommodation and food service activities | K1: Information and communication | L1: Finance and insurance | M1: Real estate | N1: Professional, scientific and technical | O1: Administrative and support services | P1: Public administration and defence; social security | Q1: Education | R1: Health and social work | S1: Arts, entertainment and recreation | T1: Other service activities | U1: Households and Extraterritorial | V1: UK
A2: Number | B2: {=INDEX(B$12:B$1048576,COUNTA(B$12:B$1048576))-INDEX(B$12:B$1048576,COUNTA(B$12:B$1048576)-12)} -> -614 | C2: {=INDEX(C$12:C$1048576,COUNTA(C$12:C$1048576))-INDEX(C$12:C$1048576,COUNTA(C$12:C$1048576)-12)} -> -1901 | D2: {=INDEX(D$12:D$1048576,COUNTA(D$12:D$1048576))-INDEX(D$12:D$1048576,COUNTA(D$12:D$1048576)-12)} -> -30376 | E2: {=INDEX(E$12:E$1048576,COUNTA(E$12:E$1048576))-INDEX(E$12:E$1048576,COUNTA(E$12:E$1048576)-12)} -> 4496 | F2: {=INDEX(F$12:F$1048576,COUNTA(F$12:F$1048576))-INDEX(F$12:F$1048576,COUNTA(F$12:F$1048576)-12)} -> 6119 | G2: {=INDEX(G$12:G$1048576,COUNTA(G$12:G$1048576))-INDEX(G$12:G$1048576,COUNTA(G$12:G$1048576)-12)} -> -12288 | H2: {=INDEX(H$12:H$1048576,COUNTA(H$12:H$1048576))-INDEX(H$12:H$1048576,COUNTA(H$12:H$1048576)-12)} -> -70055 | I2: {=INDEX(I$12:I$1048576,COUNTA(I$12:I$1048576))-INDEX(I$12:I$1048576,COUNTA(I$12:I$1048576)-12)} -> 16154 | ... V2: {=INDEX(V$12:V$1048576,COUNTA(V$12:V$1048576))-INDEX(V$12:V$1048576,COUNTA(V$12:V$1048576)-12)} -> -170685
A3: % | B3: {=INDEX(B$12:B$1048576,COUNTA(B$12:B$1048576))/INDEX(B$12:B$1048576,COUNTA(B$12:B$1048576)-12)-1} -> -0.0031230449 | C3: {=INDEX(C$12:C$1048576,COUNTA(C$12:C$1048576))/INDEX(C$12:C$1048576,COUNTA(C$12:C$1048576)-12)-1} -> -0.041632903 | D3: {=INDEX(D$12:D$1048576,COUNTA(D$12:D$1048576))/INDEX(D$12:D$1048576,COUNTA(D$12:D$1048576)-12)-1} -> -0.012996732 | E3: {=INDEX(E$12:E$1048576,COUNTA(E$12:E$1048576))/INDEX(E$12:E$1048576,COUNTA(E$12:E$1048576)-12)-1} -> 0.038712233 | F3: {=INDEX(F$12:F$1048576,COUNTA(F$12:F$1048576))/INDEX(F$12:F$1048576,COUNTA(F$12:F$1048576)-12)-1} -> 0.029626223 | G3: {=INDEX(G$12:G$1048576,COUNTA(G$12:G$1048576))/INDEX(G$12:G$1048576,COUNTA(G$12:G$1048576)-12)-1} -> -0.0091847489 | H3: {=INDEX(H$12:H$1048576,COUNTA(H$12:H$1048576))/INDEX(H$12:H$1048576,COUNTA(H$12:H$1048576)-12)-1} -> -0.016213324 | I3: {=INDEX(I$12:I$1048576,COUNTA(I$12:I$1048576))/INDEX(I$12:I$1048576,COUNTA(I$12:I$1048576)-12)-1} -> 0.011613487 | ... V3: {=INDEX(V$12:V$1048576,COUNTA(V$12:V$1048576))/INDEX(V$12:V$1048576,COUNTA(V$12:V$1048576)-12)-1} -> -0.0056096251
A4: Rank | B4: =RANK(B2,$B$2:$U$2) -> 9 | C4: =RANK(C2,$B$2:$U$2) -> 10 | D4: =RANK(D2,$B$2:$U$2) -> 17 | E4: =RANK(E2,$B$2:$U$2) -> 8 | F4: =RANK(F2,$B$2:$U$2) -> 6 | G4: =RANK(G2,$B$2:$U$2) -> 14 | H4: =RANK(H2,$B$2:$U$2) -> 20 | I4: =RANK(I2,$B$2:$U$2) -> 2 | ... U4: =RANK(U2,$B$2:$U$2) -> 12
A5: 23. Payrolled employees from PAYE RTI
A6: UK, seasonally adjusted
A7: Earnings and employment from Pay As You Earn Real Time Information, seasonally adjusted - Office for National Statistics
A8: Units | B8: Payrolled employees
B10: A | C10: B | D10: C | E10: D | F10: E | G10: F | H10: G | I10: H | J10: I | K10: J | L10: K | M10: L | N10: M | O10: N | P10: O | Q10: P | R10: Q | S10: R | T10: S | U10: T-U
A11: Date | B11: Agriculture, forestry and fishing | C11: Mining and quarrying | D11: Manufacturing | E11: Energy production and supply | F11: Water supply, sewerage and waste | G11: Construction | H11: Wholesale and retail; repair of motor vehicles | I11: Transportation and storage | J11: Accommodation and food service activities | K11: Information and communication | L11: Finance and insurance | M11: Real estate | N11: Professional, scientific and technical | O11: Administrative and support services | P11: Public administration and defence; social security | Q11: Education | R11: Health and social work | S11: Arts, entertainment and recreation | T11: Other service activities | U11: Households and Extraterritorial | V11: UK
A12: July 2014 | B12: 177905 | C12: 58307 | D12: 2336087 | E12: 92943 | F12: 155653 | G12: 1081408 | H12: 4255533 | I12: 1164523 | J12: 1758770 | K12: 1060896 | L12: 1054685 | M12: 401247 | N12: 1934869 | O12: 2230040 | P12: 1588018 | Q12: 2879249 | R12: 3429105 | S12: 520128 | T12: 486204 | U12: 96542 | V12: 26762113
A13: August 2014 | B13: 178179 | C13: 58487 | D13: 2340535 | E13: 92980 | F13: 155943 | G13: 1087984 | H13: 4264797 | I13: 1165997 | J13: 1767010 | K13: 1066653 | L13: 1055820 | M13: 401904 | N13: 1943596 | O13: 2250253 | P13: 1584818 | Q13: 2881488 | R13: 3435643 | S13: 521066 | T13: 487131 | U13: 96940 | V13: 26837223
A14: September 2014 | B14: 177495 | C14: 58694 | D14: 2346087 | E14: 92853 | F14: 156177 | G14: 1093244 | H14: 4271407 | I14: 1169435 | J14: 1775315 | K14: 1069876 | L14: 1057134 | M14: 402426 | N14: 1950604 | O14: 2247490 | P14: 1583955 | Q14: 2894249 | R14: 3438641 | S14: 520971 | T14: 488583 | U14: 97491 | V14: 26892127
A15: October 2014 | B15: 176020 | C15: 58675 | D15: 2347383 | E15: 92877 | F15: 156256 | G15: 1097393 | H15: 4273008 | I15: 1168777 | J15: 1779273 | K15: 1071208 | L15: 1056146 | M15: 402339 | N15: 1957542 | O15: 2250103 | P15: 1578449 | Q15: 2891568 | R15: 3437878 | S15: 523690 | T15: 489885 | U15: 97699 | V15: 26906169
A16: November 2014 | B16: 177002 | C16: 58750 | D16: 2355064 | E16: 93182 | F16: 156820 | G16: 1104660 | H16: 4289831 | I16: 1173413 | J16: 1789505 | K16: 1075709 | L16: 1058097 | M16: 403228 | N16: 1968659 | O16: 2259100 | P16: 1578004 | Q16: 2895515 | R16: 3448268 | S16: 526409 | T16: 491726 | U16: 98015 | V16: 27000958
A17: December 2014 | B17: 178028 | C17: 58391 | D17: 2317834 | E17: 93448 | F17: 156531 | G17: 1084425 | H17: 4307019 | I17: 1176347 | J17: 1794077 | K17: 1079444 | L17: 1058427 | M17: 403689 | N17: 1973548 | O17: 2266343 | P17: 1575803 | Q17: 2898731 | R17: 3456646 | S17: 528625 | T17: 492350 | U17: 98580 | V17: 26998286
A18: January 2015 | B18: 178603 | C18: 58458 | D18: 2358927 | E18: 93625 | F18: 157927 | G18: 1117623 | H18: 4325847 | I18: 1183740 | J18: 1805912 | K18: 1083161 | L18: 1060588 | M18: 405182 | N18: 1980759 | O18: 2279879 | P18: 1573725 | Q18: 2901669 | R18: 3468093 | S18: 530428 | T18: 494311 | U18: 99116 | V18: 27157573
A19: February 2015 | B19: 178621 | C19: 57880 | D19: 2364907 | E19: 93778 | F19: 158501 | G19: 1119773 | H19: 4336022 | I19: 1187701 | J19: 1807320 | K19: 1089437 | L19: 1061180 | M19: 405416 | N19: 1992950 | O19: 2288539 | P19: 1569097 | Q19: 2901169 | R19: 3474682 | S19: 532809 | T19: 495242 | U19: 99475 | V19: 27214499
A20: March 2015 | B20: 178987 | C20: 57636 | D20: 2367842 | E20: 94093 | F20: 158988 | G20: 1126149 | H20: 4347421 | I20: 1191409 | J20: 1815637 | K20: 1095568 | L20: 1062977 | M20: 406721 | N20: 2008036 | O20: 2301315 | P20: 1565246 | Q20: 2903120 | R20: 3481996 | S20: 534688 | T20: 496790 | U20: 99923 | V20: 27294543
A21: April 2015 | B21: 179859 | C21: 55897 | D21: 2370463 | E21: 92731 | F21: 158857 | G21: 1132002 | H21: 4341372 | I21: 1189319 | J21: 1829538 | K21: 1095929 | L21: 1074624 | M21: 408254 | N21: 2020610 | O21: 2292050 | P21: 1563235 | Q21: 2904107 | R21: 3497763 | S21: 535741 | T21: 497816 | U21: 100486 | V21: 27340654
A22: May 2015 | B22: 180610 | C22: 55443 | D22: 2370582 | E22: 93205 | F22: 159168 | G22: 1136838 | H22: 4351394 | I22: 1192362 | J22: 1838931 | K22: 1099678 | L22: 1075060 | M22: 408890 | N22: 2027810 | O22: 2295487 | P22: 1569710 | Q22: 2900585 | R22: 3504968 | S22: 538501 | T22: 498657 | U22: 101096 | V22: 27398974
A23: June 2015 | B23: 181683 | C23: 54872 | D23: 2375700 | E23: 93850 | F23: 160027 | G23: 1143893 | H23: 4365722 | I23: 1198270 | J23: 1850234 | K23: 1105687 | L23: 1079142 | M23: 410606 | N23: 2037582 | O23: 2293723 | P23: 1548667 | Q23: 2903625 | R23: 3517935 | S23: 541917 | T23: 499535 | U23: 98645 | V23: 27461315
... A148: November 2025 | B148: 195989 | C148: 43760 | D148: 2306827 | E148: 120635 | F148: 212659 | G148: 1325582 | H148: 4250774 | I148: 1407123 | J148: 2129683 | K148: 1257532 | L148: 1104923 | M148: 471901 | N148: 2463249 | O148: 2393911 | P148: 1594167 | Q148: 3160819 | R148: 4506248 | S148: 649500 | T148: 543816 | U148: 117385 | V148: 30256482

Sheet 2
B2: Aged 16 and over | J2: Aged 16-64 | R2: Aged 16-17 | Z2: Aged 18-24 | AH2: Aged 25-34 | AP2: Aged 35-49 | AX2: Aged 50-64 | BF2: Age 65+
B3: Employment | D3: Unemployment | F3: Activity | H3: Inactivity | J3: Employment | L3: Unemployment | N3: Activity | P3: Inactivity | R3: Employment | T3: Unemployment | V3: Activity | X3: Inactivity | Z3: Employment | AB3: Unemployment | AD3: Activity | AF3: Inactivity | AH3: Employment | AJ3: Unemployment | AL3: Activity | AN3: Inactivity | AP3: Employment | AR3: Unemployment | AT3: Activity | AV3: Inactivity | AX3: Employment | AZ3: Unemployment | BB3: Activity | BD3: Inactivity | BF3: Employment | BH3: Unemployment | BJ3: Activity | BL3: Inactivity
B4: level | C4: rate (%) | D4: level | E4: rate (%) | F4: level | G4: rate (%) | H4: level | I4: rate (%) | J4: level | K4: rate (%) | L4: level | M4: rate (%) | N4: level | O4: rate (%) | P4: level | Q4: rate (%) | R4: level | S4: rate (%) | T4: level | U4: rate (%) | V4: level | W4: rate (%) | X4: level | Y4: rate (%) | Z4: level | AA4: rate (%) | AB4: level | AC4: rate (%) | AD4: level | AE4: rate (%) | AF4: level | AG4: rate (%) | AH4: level | AI4: rate (%) | AJ4: level | AK4: rate (%) | AL4: level | AM4: rate (%) | AN4: level | AO4: rate (%) | AP4: level | AQ4: rate (%) | AR4: level | AS4: rate (%) | AT4: level | AU4: rate (%) | AV4: level | AW4: rate (%) | AX4: level | AY4: rate (%) | AZ4: level | BA4: rate (%) | BB4: level | BC4: rate (%) | BD4: level | BE4: rate (%) | BF4: level | BG4: rate (%) | BH4: level | BI4: rate (%) | BJ4: level | BK4: rate (%) | BL4: level | BM4: rate (%)
A5: Current | B5: {=INDEX(B$18:B$1048576,COUNTA(B$18:B$1048576))} -> 34226340 | C5: {=INDEX(C$18:C$1048576,COUNTA(C$18:C$1048576))} -> 60.689871 | D5: {=INDEX(D$18:D$1048576,COUNTA(D$18:D$1048576))} -> 1831890.1 | E5: {=INDEX(E$18:E$1048576,COUNTA(E$18:E$1048576))} -> 5.0803661 | F5: {=INDEX(F$18:F$1048576,COUNTA(F$18:F$1048576))} -> 36058230 | G5: {=INDEX(G$18:G$1048576,COUNTA(G$18:G$1048576))} -> 63.938164 | H5: {=INDEX(H$18:H$1048576,COUNTA(H$18:H$1048576))} -> 20337243 | I5: {=INDEX(I$18:I$1048576,COUNTA(I$18:I$1048576))} -> 36.061836 | ... BM5: {=INDEX(BM$18:BM$1048576,COUNTA(BM$18:BM$1048576))} -> 86.244309
A6: Quarterly change | B6: {=INDEX(B$18:B$1048576,COUNTA(B$18:B$1048576))-INDEX(B$18:B$1048576,COUNTA(B$18:B$1048576)-3)} -> -16220.426 | C6: {=INDEX(C$18:C$1048576,COUNTA(C$18:C$1048576))-INDEX(C$18:C$1048576,COUNTA(C$18:C$1048576)-3)} -> -0.17271674 | D6: {=INDEX(D$18:D$1048576,COUNTA(D$18:D$1048576))-INDEX(D$18:D$1048576,COUNTA(D$18:D$1048576)-3)} -> 157870.54 | E6: {=INDEX(E$18:E$1048576,COUNTA(E$18:E$1048576))-INDEX(E$18:E$1048576,COUNTA(E$18:E$1048576)-3)} -> 0.41951154 | F6: {=INDEX(F$18:F$1048576,COUNTA(F$18:F$1048576))-INDEX(F$18:F$1048576,COUNTA(F$18:F$1048576)-3)} -> 141650.12 | G6: {=INDEX(G$18:G$1048576,COUNTA(G$18:G$1048576))-INDEX(G$18:G$1048576,COUNTA(G$18:G$1048576)-3)} -> 0.1001805 | H6: {=INDEX(H$18:H$1048576,COUNTA(H$18:H$1048576))-INDEX(H$18:H$1048576,COUNTA(H$18:H$1048576)-3)} -> -8261.1158 | I6: {=INDEX(I$18:I$1048576,COUNTA(I$18:I$1048576))-INDEX(I$18:I$1048576,COUNTA(I$18:I$1048576)-3)} -> -0.1001805 | ... BM6: {=INDEX(BM$18:BM$1048576,COUNTA(BM$18:BM$1048576))-INDEX(BM$18:BM$1048576,COUNTA(BM$18:BM$1048576)-3)} -> -0.29410289
A7: Change year on year | B7: {=INDEX(B$18:B$1048576,COUNTA(B$18:B$1048576))-INDEX(B$18:B$1048576,COUNTA(B$18:B$1048576)-12)} -> 448105.34 | C7: {=INDEX(C$18:C$1048576,COUNTA(C$18:C$1048576))-INDEX(C$18:C$1048576,COUNTA(C$18:C$1048576)-12)} -> 0.17645127 | D7: {=INDEX(D$18:D$1048576,COUNTA(D$18:D$1048576))-INDEX(D$18:D$1048576,COUNTA(D$18:D$1048576)-12)} -> 326867.79 | E7: {=INDEX(E$18:E$1048576,COUNTA(E$18:E$1048576))-INDEX(E$18:E$1048576,COUNTA(E$18:E$1048576)-12)} -> 0.81482364 | F7: {=INDEX(F$18:F$1048576,COUNTA(F$18:F$1048576))-INDEX(F$18:F$1048576,COUNTA(F$18:F$1048576)-12)} -> 774973.13 | G7: {=INDEX(G$18:G$1048576,COUNTA(G$18:G$1048576))-INDEX(G$18:G$1048576,COUNTA(G$18:G$1048576)-12)} -> 0.72850942 | H7: {=INDEX(H$18:H$1048576,COUNTA(H$18:H$1048576))-INDEX(H$18:H$1048576,COUNTA(H$18:H$1048576)-12)} -> -198911.13 | I7: {=INDEX(I$18:I$1048576,COUNTA(I$18:I$1048576))-INDEX(I$18:I$1048576,COUNTA(I$18:I$1048576)-12)} -> -0.72850942 | ... BM7: {=INDEX(BM$18:BM$1048576,COUNTA(BM$18:BM$1048576))-INDEX(BM$18:BM$1048576,COUNTA(BM$18:BM$1048576)-12)} -> -1.3558826
A8: Change since Covid (Dec 19-feb 20) | B8: {=INDEX(B$18:B$1048576,COUNTA(B$18:B$1048576))-B$351} -> 1045032 | C8: {=INDEX(C$18:C$1048576,COUNTA(C$18:C$1048576))-C$351} -> -1.3296027 | D8: {=INDEX(D$18:D$1048576,COUNTA(D$18:D$1048576))-D$351} -> 468168.17 | E8: {=INDEX(E$18:E$1048576,COUNTA(E$18:E$1048576))-E$351} -> 1.1327015 | F8: {=INDEX(F$18:F$1048576,COUNTA(F$18:F$1048576))-F$351} -> 1513200.2 | G8: {=INDEX(G$18:G$1048576,COUNTA(G$18:G$1048576))-G$351} -> -0.63025449 | H8: {=INDEX(H$18:H$1048576,COUNTA(H$18:H$1048576))-H$351} -> 1380838.8 | I8: {=INDEX(I$18:I$1048576,COUNTA(I$18:I$1048576))-I$351} -> 0.63025449 | ... BM8: {=INDEX(BM$18:BM$1048576,COUNTA(BM$18:BM$1048576))-BM$351} -> -2.0105074
A9: change since 2010 election | B9: {=INDEX(B$18:B$1048576,COUNTA(B$18:B$1048576))-B$233} -> 5178741.8 | C9: {=INDEX(C$18:C$1048576,COUNTA(C$18:C$1048576))-C$233} -> 2.6872425 | D9: {=INDEX(D$18:D$1048576,COUNTA(D$18:D$1048576))-D$233} -> -677652.17 | E9: {=INDEX(E$18:E$1048576,COUNTA(E$18:E$1048576))-E$233} -> -2.8720093 | F9: {=INDEX(F$18:F$1048576,COUNTA(F$18:F$1048576))-F$233} -> 4501089.6 | G9: {=INDEX(G$18:G$1048576,COUNTA(G$18:G$1048576))-G$233} -> 0.9244481 | H9: {=INDEX(H$18:H$1048576,COUNTA(H$18:H$1048576))-H$233} -> 1814587.4 | I9: {=INDEX(I$18:I$1048576,COUNTA(I$18:I$1048576))-I$233} -> -0.9244481 | ... BM9: {=INDEX(BM$18:BM$1048576,COUNTA(BM$18:BM$1048576))-BM$233} -> -5.4555123
A10: change since 2024 election | B10: {=INDEX(B$18:B$1048576,COUNTA(B$18:B$1048576))-B$403} -> 737154.92 | C10: {=INDEX(C$18:C$1048576,COUNTA(C$18:C$1048576))-C$403} -> 0.47639709 | D10: {=INDEX(D$18:D$1048576,COUNTA(D$18:D$1048576))-D$403} -> 365071.28 | E10: {=INDEX(E$18:E$1048576,COUNTA(E$18:E$1048576))-E$403} -> 0.88418044 | F10: {=INDEX(F$18:F$1048576,COUNTA(F$18:F$1048576))-F$403} -> 1102226.2 | G10: {=INDEX(G$18:G$1048576,COUNTA(G$18:G$1048576))-G$403} -> 1.0873532 | H10: {=INDEX(H$18:H$1048576,COUNTA(H$18:H$1048576))-H$403} -> -324180.19 | I10: {=INDEX(I$18:I$1048576,COUNTA(I$18:I$1048576))-I$403} -> -1.0873532 | ... BM10: {=INDEX(BM$18:BM$1048576,COUNTA(BM$18:BM$1048576))-BM$403} -> -1.746035
A11: Table 2: Labour market activity by age group (seasonally adjusted) | J11: =J418-J402 -> 624421.87
A12: Date of publication: | B12: 45335 | G12: Date of next publication: | J12: 45363 | M12: Source: Labour Force Survey
A13: Inquiries: Email: | B13: labour.market@ons.gov.uk | G13: Tel: 01633 455400 | J13: =K414-K417 -> 0.17762781
A14: United Kingdom (thousands) seasonally adjusted
B15: Aged 16 and over | J15: Aged 16-64 | R15: Aged 16-17 | Z15: Aged 18-24 | AH15: Aged 25-34 | AP15: Aged 35-49 | AX15: Aged 50-64 | BF15: Age 65+
B16: Employment | D16: Unemployment | F16: Activity | H16: Inactivity | J16: Employment | L16: Unemployment | N16: Activity | P16: Inactivity | R16: Employment | T16: Unemployment | V16: Activity | X16: Inactivity | Z16: Employment | AB16: Unemployment | AD16: Activity | AF16: Inactivity | AH16: Employment | AJ16: Unemployment | AL16: Activity | AN16: Inactivity | AP16: Employment | AR16: Unemployment | AT16: Activity | AV16: Inactivity | AX16: Employment | AZ16: Unemployment | BB16: Activity | BD16: Inactivity | BF16: Employment | BH16: Unemployment | BJ16: Activity | BL16: Inactivity
B17: level | C17: rate (%) | D17: level | E17: rate (%) | F17: level | G17: rate (%) | H17: level | I17: rate (%) | J17: level | K17: rate (%) | L17: level | M17: rate (%) | N17: level | O17: rate (%) | P17: level | Q17: rate (%) | R17: level | S17: rate (%) | T17: level | U17: rate (%) | V17: level | W17: rate (%) | X17: level | Y17: rate (%) | Z17: level | AA17: rate (%) | AB17: level | AC17: rate (%) | AD17: level | AE17: rate (%) | AF17: level | AG17: rate (%) | AH17: level | AI17: rate (%) | AJ17: level | AK17: rate (%) | AL17: level | AM17: rate (%) | AN17: level | AO17: rate (%) | AP17: level | AQ17: rate (%) | AR17: level | AS17: rate (%) | AT17: level | AU17: rate (%) | AV17: level | AW17: rate (%) | AX17: level | AY17: rate (%) | AZ17: level | BA17: rate (%) | BB17: level | BC17: rate (%) | BD17: level | BE17: rate (%) | BF17: level | BG17: rate (%) | BH17: level | BI17: rate (%) | BJ17: level | BK17: rate (%) | BL17: level | BM17: rate (%)
A18: Mar-May 1992 | B18: 25635937 | C18: 56.978873 | D18: 2795738.4 | E18: 9.8331819 | F18: 28431675 | G18: 63.19273 | H18: 16560329 | I18: 36.80727 | J18: 25157591 | K18: 69.194504 | L18: 2771842.3 | M18: 9.9244488 | N18: 27929433 | O18: 76.818297 | P18: 8428354.6 | Q18: 23.181703 | R18: 672842.98 | S18: 48.815635 | T18: 148298.6 | U18: 18.060053 | V18: 821141.59 | W18: 59.574892 | X18: 557193.41 | Y18: 40.425108 | Z18: 3807969.1 | AA18: 65.851182 | AB18: 711645.67 | AC18: 15.745715 | AD18: 4519614.8 | AE18: 78.157666 | AF18: 1263074.2 | AG18: 21.842334 | AH18: 6569245 | AI18: 73.761625 | AJ18: 766486.76 | AK18: 10.448675 | AL18: 7335731.8 | AM18: 82.367988 | AN18: 1570315.2 | AO18: 17.632012 | AP18: 9130969.3 | AQ18: 79.563995 | AR18: 715160.37 | AS18: 7.2633653 | AT18: 9846129.7 | AU18: 85.795646 | AV18: 1630128.3 | AW18: 14.204354 | AX18: 4976564.7 | AY18: 56.459105 | AZ18: 430250.91 | BA18: 7.9575657 | BB18: 5406815.6 | BC18: 61.3403 | BD18: 3407643.4 | BE18: 38.6597 | BF18: 478345.94 | BG18: 5.5401202 | BH18: 23896.055 | BI18: 4.7578768 | BJ18: 502242 | BK18: 5.8168802 | BL18: 8131974 | BM18: 94.18312
A19: Apr-Jun 1992 | B19: 25605421 | C19: 56.906189 | D19: 2777367.7 | E19: 9.785394 | F19: 28382788 | G19: 63.078687 | H19: 16613057 | I19: 36.921313 | J19: 25121755 | K19: 69.095274 | L19: 2755380.3 | M19: 9.8840153 | N19: 27877135 | O19: 76.673716 | P19: 8481002.7 | Q19: 23.326284 | R19: 664951.75 | S19: 48.404968 | T19: 154422.9 | U19: 18.846433 | V19: 819374.64 | W19: 59.646137 | X19: 554351.61 | Y19: 40.353863 | Z19: 3773820.3 | AA19: 65.44936 | AB19: 703256.67 | AC19: 15.707942 | AD19: 4477077 | AE19: 77.64594 | AF19: 1288938.6 | AG19: 22.35406 | AH19: 6562285.8 | AI19: 73.607934 | AJ19: 774481.14 | AK19: 10.556164 | AL19: 7336767 | AM19: 82.295144 | AN19: 1578421.2 | AO19: 17.704856 | AP19: 9154912.9 | AQ19: 79.688748 | AR19: 691103.96 | AS19: 7.0191223 | AT19: 9846016.8 | AU19: 85.704448 | AV19: 1642321.4 | AW19: 14.295552 | AX19: 4965784.3 | AY19: 56.334176 | AZ19: 432115.65 | BA19: 8.0052549 | BB19: 5397900 | BC19: 61.236297 | BD19: 3416970 | BE19: 38.763703 | BF19: 483665.56 | BG19: 5.5994671 | BH19: 21987.331 | BI19: 4.3483051 | BJ19: 505652.89 | BK19: 5.8540177 | BL19: 8132054 | BM19: 94.145982
A20: May-Jul 1992 | B20: 25541631 | C20: 56.759881 | D20: 2802624.9 | E20: 9.8878055 | F20: 28344256 | G20: 62.988013 | H20: 16655188 | I20: 37.011987 | J20: 25071012 | K20: 68.95567 | L20: 2780378.7 | M20: 9.9829079 | N20: 27851391 | O20: 76.602863 | P20: 8506768.3 | Q20: 23.397137 | R20: 657021.66 | S20: 47.988417 | T20: 160526.33 | U20: 19.635096 | V20: 817547.99 | W20: 59.713152 | X20: 551577.51 | Y20: 40.286848 | Z20: 3732657.6 | AA20: 64.922411 | AB20: 704380.25 | AC20: 15.875011 | AD20: 4437037.9 | AE20: 77.173753 | AF20: 1312375.3 | AG20: 22.826247 | AH20: 6563532.7 | AI20: 73.546748 | AJ20: 774921.42 | AK20: 10.559737 | AL20: 7338454.1 | AM20: 82.230022 | AN20: 1585846.2 | AO20: 17.769978 | AP20: 9147971.3 | AQ20: 79.549054 | AR20: 702795.56 | AS20: 7.1344248 | AT20: 9850766.9 | AU20: 85.660434 | AV20: 1649019.5 | AW20: 14.339566 | AX20: 4969829 | AY20: 56.375814 | AZ20: 437755.16 | BA20: 8.0952074 | BB20: 5407584.2 | BC20: 61.341539 | BD20: 3407949.8 | BE20: 38.658461 | BF20: 470618.68 | BG20: 5.4461656 | BH20: 22246.196 | BI20: 4.51365 | BJ20: 492864.88 | BK20: 5.7036065 | BL20: 8148420 | BM20: 94.296394
A21: Jun-Aug 1992 | B21: 25525070 | C21: 56.721622 | D21: 2816125.8 | E21: 9.9365103 | F21: 28341196 | G21: 62.979596 | H21: 16659404 | I21: 37.020404 | J21: 25060700 | K21: 68.931149 | L21: 2794467.3 | M21: 10.032132 | N21: 27855168 | O21: 76.61752 | P21: 8500965.7 | Q21: 23.38248 | R21: 655096.25 | S21: 48.013865 | T21: 155254.86 | U21: 19.158962 | V21: 810351.11 | W21: 59.392934 | X21: 554038.64 | Y21: 40.607066 | Z21: 3719998.3 | AA21: 64.885011 | AB21: 714329.99 | AC21: 16.109091 | AD21: 4434328.3 | AE21: 77.344508 | AF21: 1298888.4 | AG21: 22.655492 | AH21: 6566665.2 | AI21: 73.542227 | AJ21: 775662.24 | AK21: 10.564256 | AL21: 7342327.5 | AM21: 82.229121 | AN21: 1586781 | AO21: 17.770879 | AP21: 9143812.7 | AQ21: 79.452506 | AR21: 703958.08 | AS21: 7.1484003 | AT21: 9847770.8 | AU21: 85.569345 | AV21: 1660755.7 | AW21: 14.430655 | AX21: 4975128 | AY21: 56.401643 | AZ21: 445262.13 | BA21: 8.2145771 | BB21: 5420390.1 | BC21: 61.449456 | BD21: 3400501.9 | BE21: 38.550544 | BF21: 464369.35 | BG21: 5.3718688 | BH21: 21658.542 | BI21: 4.4562342 | BJ21: 486027.9 | BK21: 5.6224168 | BL21: 8158437.9 | BM21: 94.377583
A22: Jul-Sep 1992 | B22: 25509005 | C22: 56.682283 | D22: 2814524.8 | E22: 9.9370554 | F22: 28323530 | G22: 62.936297 | H22: 16679960 | I22: 37.063703 | J22: 25051022 | K22: 68.904267 | L22: 2793342.4 | M22: 10.031985 | N22: 27844364 | O22: 76.587515 | P22: 8511906.3 | Q22: 23.412485 | R22: 648817.45 | S22: 47.720183 | T22: 146301.37 | U22: 18.399938 | V22: 795118.82 | W22: 58.480572 | X22: 564510.18 | Y22: 41.519428 | Z22: 3700258.4 | AA22: 64.724227 | AB22: 723869.61 | AC22: 16.36186 | AD22: 4424128 | AE22: 77.386019 | AF22: 1292832.3 | AG22: 22.613981 | AH22: 6586437.2 | AI22: 73.720371 | AJ22: 762085.43 | AK22: 10.370594 | AL22: 7348522.7 | AM22: 82.250206 | AN22: 1585829 | AO22: 17.749794 | AP22: 9154876.5 | AQ22: 79.480524 | AR22: 712240.98 | AS22: 7.2183288 | AT22: 9867117.4 | AU22: 85.664036 | AV22: 1651272.2 | AW22: 14.335964 | AX22: 4960632.4 | AY22: 56.198778 | AZ22: 448845.05 | BA22: 8.2973827 | BB22: 5409477.5 | BC22: 61.283723 | BD22: 3417462.5 | BE22: 38.716277 | BF22: 457983.03 | BG22: 5.2963045 | BH22: 21182.41 | BI22: 4.4206882 | BJ22: 479165.44 | BK22: 5.5412666 | BL22: 8168053.2 | BM22: 94.458733
A23: Aug-Oct 1992 | B23: 25454432 | C23: 56.55781 | D23: 2849869.1 | E23: 10.068678 | F23: 28304301 | G23: 62.890002 | H23: 16701741 | I23: 37.109998 | J23: 24999843 | K23: 68.764542 | L23: 2829973 | M23: 10.168853 | N23: 27829816 | O23: 76.548662 | P23: 8525902.4 | Q23: 23.451338 | R23: 628524.21 | S23: 46.391089 | T23: 135175.21 | U23: 17.700054 | V23: 763699.42 | W23: 56.36831 | X23: 591138.83 | Y23: 43.63169 | Z23: 3693704.8 | AA23: 64.794223 | AB23: 740436.82 | AC23: 16.698538 | AD23: 4434141.6 | AE23: 77.782816 | AF23: 1266528.3 | AG23: 22.217184 | AH23: 6575853.7 | AI23: 73.560218 | AJ23: 775080.19 | AK23: 10.543969 | AL23: 7350933.9 | AM23: 82.230585 | AN23: 1588481.9 | AO23: 17.769415 | AP23: 9157510.7 | AQ23: 79.437958 | AR23: 727787.21 | AS23: 7.3623194 | AT23: 9885297.9 | AU23: 85.751238 | AV23: 1642579.9 | AW23: 14.248762 | AX23: 4944250 | AY23: 55.97528 | AZ23: 451493.6 | BA23: 8.3675882 | BB23: 5395743.6 | BC23: 61.086769 | BD23: 3437173.4 | BE23: 38.913231 | BF23: 454588.67 | BG23: 5.2551638 | BH23: 19896.06 | BI23: 4.1931929 | BJ23: 474484.73 | BK23: 5.4851674 | BL23: 8175838.9 | BM23: 94.514833
A24: Sep-Nov 1992 | B24: 25406419 | C24: 56.449606 | D24: 2898811.3 | E24: 10.241257 | F24: 28305230 | G24: 62.890371 | H24: 16702026 | I24: 37.109629 | J24: 24962923 | K24: 68.666128 | L24: 2880096.3 | M24: 10.344052 | N24: 27843020 | O24: 76.58848 | P24: 8511037.4 | Q24: 23.41152 | R24: 623263.78 | S24: 46.162438 | T24: 136924.83 | U24: 18.011955 | V24: 760188.61 | W24: 56.303865 | X24: 589964.89 | Y24: 43.696135 | Z24: 3682050 | AA24: 64.774538 | AB24: 750677.65 | AC24: 16.934892 | AD24: 4432727.6 | AE24: 77.980442 | AF24: 1251681.9 | AG24: 22.019558 | AH24: 6571774.9 | AI24: 73.47512 | AJ24: 787965.68 | AK24: 10.706433 | AL24: 7359740.6 | AM24: 82.284897 | AN24: 1584477.4 | AO24: 17.715103 | AP24: 9161864.5 | AQ24: 79.415391 | AR24: 730505.38 | AS24: 7.3845336 | AT24: 9892369.9 | AU24: 85.747439 | AV24: 1644266.1 | AW24: 14.252561 | AX24: 4923970.1 | AY24: 55.70959 | AZ24: 474022.79 | BA24: 8.7814639 | BB24: 5397992.9 | BC24: 61.072664 | BD24: 3440647.1 | BE24: 38.927336 | BF24: 443495.8 | BG24: 5.1252233 | BH24: 18714.996 | BI24: 4.0490174 | BJ24: 462210.8 | BK24: 5.3415017 | BL24: 8190988.7 | BM24: 94.658498
A25: Oct-Dec 1992 | B25: 25335708 | C25: 56.289377 | D25: 2931640.3 | E25: 10.371119 | F25: 28267348 | G25: 62.802722 | H25: 16742402 | I25: 37.197278 | J25: 24904858 | K25: 68.507651 | L25: 2912254.2 | M25: 10.46929 | N25: 27817112 | O25: 76.518606 | P25: 8536284.2 | Q25: 23.481394 | R25: 613179.3 | S25: 45.576197 | T25: 143304.85 | U25: 18.943537 | V25: 756484.15 | W25: 56.227714 | X25: 588909.6 | Y25: 43.772286 | Z25: 3657106.4 | AA25: 64.520168 | AB25: 749834.88 | AC25: 17.01486 | AD25: 4406941.3 | AE25: 77.749062 | AF25: 1261218.8 | AG25: 22.250938 | AH25: 6566330.4 | AI25: 73.371467 | AJ25: 796807.58 | AK25: 10.821576 | AL25: 7363138 | AM25: 82.274909 | AN25: 1586295.1 | AO25: 17.725091 | AP25: 9151189.4 | AQ25: 79.257564 | AR25: 741700.09 | AS25: 7.4973049 | AT25: 9892889.5 | AU25: 85.681356 | AV25: 1653250.7 | AW25: 14.318644 | AX25: 4917052.2 | AY25: 55.595914 | AZ25: 480606.78 | BA25: 8.9039856 | BB25: 5397659 | BC25: 61.030018 | BD25: 3446610 | BE25: 38.969982 | BF25: 430849.95 | BG25: 4.9772685 | BH25: 19386.125 | BI25: 4.3057689 | BJ25: 450236.08 | BK25: 5.2012211 | BL25: 8206117.3 | BM25: 94.798779
A26: Nov-Jan 1993 | B26: 25301164 | C26: 56.210098 | D26: 2982756.3 | E26: 10.545767 | F26: 28283920 | G26: 62.836711 | H26: 16727857 | I26: 37.163289 | J26: 24869383 | K26: 68.411497 | L26: 2964559.6 | M26: 10.650879 | N26: 27833942 | O26: 76.566503 | P26: 8518694 | Q26: 23.433497 | R26: 601737.22 | S26: 44.888946 | T26: 148625.82 | U26: 19.807188 | V26: 750363.04 | W26: 55.976271 | X26: 590138.96 | Y26: 44.023729 | Z26: 3642900.1 | AA26: 64.453285 | AB26: 758732.77 | AC26: 17.23753 | AD26: 4401632.8 | AE26: 77.87743 | AF26: 1250367.8 | AG26: 22.12257 | AH26: 6577421.7 | AI26: 73.455902 | AJ26: 802411.97 | AK26: 10.873036 | AL26: 7379833.7 | AM26: 82.417149 | AN26: 1574411.7 | AO26: 17.582851 | AP26: 9134290.6 | AQ26: 79.048594 | AR26: 755263.86 | AS26: 7.6369857 | AT26: 9889554.5 | AU26: 85.584684 | AV26: 1665730.9 | AW26: 14.415316 | AX26: 4913033.1 | AY26: 55.510717 | AZ26: 499525.19 | BA26: 9.2290034 | BB26: 5412558.3 | BC26: 61.154684 | BD26: 3438044.7 | BE26: 38.845316 | BF26: 431780.84 | BG26: 4.986417 | BH26: 18196.685 | BI26: 4.0439097 | BJ26: 449977.53 | BK26: 5.1965612 | BL26: 8209162.8 | BM26: 94.803439
A27: Dec-Feb 1993 | B27: 25274286 | C27: 56.147416 | D27: 3023283.2 | E27: 10.683897 | F27: 28297569 | G27: 62.86371 | H27: 16716588 | I27: 37.13629 | J27: 24839004 | K27: 68.329654 | L27: 3005600.8 | M27: 10.794194 | N27: 27844605 | O27: 76.597766 | P27: 8507114.4 | Q27: 23.402234 | R27: 589709.19 | S27: 44.1438 | T27: 147847.45 | U27: 20.045572 | V27: 737556.64 | W27: 55.211201 | X27: 598325.61 | Y27: 44.788799 | Z27: 3626688.4 | AA27: 64.350812 | AB27: 774878.08 | AC27: 17.604598 | AD27: 4401566.4 | AE27: 78.100004 | AF27: 1234241.8 | AG27: 21.899996 | AH27: 6573950.2 | AI27: 73.372982 | AJ27: 815460.81 | AK27: 11.035532 | AL27: 7389411.1 | AM27: 82.474479 | AN27: 1570222.4 | AO27: 17.525521 | AP27: 9123860.8 | AQ27: 78.895396 | AR27: 770251.41 | AS27: 7.7849472 | AT27: 9894112.2 | AU27: 85.555876 | AV27: 1670391.3 | AW27: 14.444124 | AX27: 4924795.6 | AY27: 55.610385 | AZ27: 497163.07 | BA27: 9.1694367 | BB27: 5421958.7 | BC27: 61.224309 | BD27: 3433933.3 | BE27: 38.775691 | BF27: 435281.59 | BG27: 5.0249321 | BH27: 17682.355 | BI27: 3.9037004 | BJ27: 452963.95 | BK27: 5.2290589 | BL27: 8209473.3 | BM27: 94.770941
A28: Jan-Mar 1993 | B28: 25282289 | C28: 56.163389 | D28: 3003526.8 | E28: 10.618491 | F28: 28285816 | G28: 62.835579 | H28: 16729789 | I28: 37.164421 | J28: 24847113 | K28: 68.354168 | L28: 2984739.8 | M28: 10.724187 | N28: 27831853 | O28: 76.565158 | P28: 8518692.9 | Q28: 23.434842 | R28: 587790.99 | S28: 44.156249 | T28: 143512.75 | U28: 19.624233 | V28: 731303.73 | W28: 54.937266 | X28: 599857.77 | Y28: 45.062734 | Z28: 3602671.5 | AA28: 64.109929 | AB28: 780912.52 | AC28: 17.814476 | AD28: 4383584 | AE28: 78.006352 | AF28: 1235937.9 | AG28: 21.993648 | AH28: 6591842.4 | AI28: 73.534333 | AJ28: 802247.85 | AK28: 10.849852 | AL28: 7394090.2 | AM28: 82.483692 | AN28: 1570215.4 | AO28: 17.516308 | AP28: 9128037.7 | AQ28: 78.867686 | AR28: 765601.85 | AS28: 7.7383237 | AT28: 9893639.6 | AU28: 85.482607 | AV28: 1680223.1 | AW28: 14.517393 | AX28: 4936770.4 | AY28: 55.709105 | AZ28: 492464.82 | BA28: 9.0706112 | BB28: 5429235.2 | BC28: 61.266336 | BD28: 3432458.8 | BE28: 38.733664 | BF28: 435176.21 | BG28: 5.0221955 | BH28: 18787.035 | BI28: 4.1384485 | BJ28: 453963.25 | BK28: 5.2390092 | BL28: 8211095.9 | BM28: 94.760991
A29: Feb-Apr 1993 | B29: 25258217 | C29: 56.10629 | D29: 2988474.6 | E29: 10.57991 | F29: 28246692 | G29: 62.744614 | H29: 16771821 | I29: 37.255386 | J29: 24824126 | K29: 68.291867 | L29: 2969360.9 | M29: 10.683657 | N29: 27793487 | O29: 76.460663 | P29: 8556560.4 | Q29: 23.539337 | R29: 576754.25 | S29: 43.483966 | T29: 140457.66 | U29: 19.583843 | V29: 717211.91 | W29: 54.073668 | X29: 609148.84 | Y29: 45.926332 | Z29: 3566918.9 | AA29: 63.657292 | AB29: 773854.39 | AC29: 17.82757 | AD29: 4340773.2 | AE29: 77.467944 | AF29: 1262542.2 | AG29: 22.532056 | AH29: 6606869.8 | AI29: 73.659732 | AJ29: 795947.06 | AK29: 10.751949 | AL29: 7402816.9 | AM29: 82.533715 | AN29: 1566629 | AO29: 17.466285 | AP29: 9125446.4 | AQ29: 78.780012 | AR29: 765785.88 | AS29: 7.7420675 | AT29: 9891232.3 | AU29: 85.391045 | AV29: 1692221.6 | AW29: 14.608955 | AX29: 4948137.2 | AY29: 55.80099 | AZ29: 493315.96 | BA29: 9.0658864 | BB29: 5441453.1 | BC29: 61.364199 | BD29: 3426018.9 | BE29: 38.635801 | BF29: 434090.92 | BG29: 5.0077023 | BH29: 19113.649 | BI29: 4.2174439 | BJ29: 453204.57 | BK29: 5.2281986 | BL29: 8215260.5 | BM29: 94.771801
... A419: Aug-Oct 2025 | B419: 34226340 | C419: 60.689871 | D419: 1831890.1 | E419: 5.0803661 | F419: 36058230 | G419: 63.938164 | H419: 20337243 | I419: 36.061836 | J419: 32486778 | K419: 74.915831 | L419: 1778933.7 | M419: 5.1915854 | N419: 34265712 | O419: 79.018124 | P419: 9098658.3 | Q419: 20.981876 | R419: 325541.93 | S419: 19.941936 | T419: 188250.06 | U419: 36.639353 | V419: 513792 | W419: 31.473694 | X419: 1118657 | Y419: 68.526306 | Z419: 3529344.5 | AA419: 60.507243 | AB419: 546361.34 | AC419: 13.405318 | AD419: 4075705.9 | AE419: 69.874087 | AF419: 1757223.1 | AG419: 30.125913 | AH419: 7675153.9 | AI419: 83.820727 | AJ419: 368725.43 | AK419: 4.5839255 | AL419: 8043879.3 | AM419: 87.847596 | AN419: 1112750.7 | AO419: 12.152404 | AP419: 11485218 | AQ419: 85.005301 | AR419: 373494.6 | AS419: 3.1495374 | AT419: 11858713 | AU419: 87.769639 | AV419: 1652466 | AW419: 12.230361 | AX419: 9471519.2 | AY419: 71.584825 | AZ419: 302102.23 | BA419: 3.0909958 | BB419: 9773621.5 | BC419: 73.868085 | BD419: 3457561.5 | BE419: 26.131915 | BF419: 1739561.9 | BG419: 13.349306 | BH419: 52956.431 | BI419: 2.9543035 | BJ419: 1792518.3 | BK419: 13.755691 | BL419: 11238585 | BM419: 86.244309
AC420: =AC418-AC406 -> -0.92378111
A421: Quality indicator | AC421: =AC418-AC415 -> 0.6717654
A422: Shaded estimates are based on a small sample size. This may result in less precise estimates, which should be used with caution.
A423: Unshaded estimates are based on a larger sample size. This is likely to result in estimates of higher precision, although they will still be subject to some sampling variability.
A424: * Estimate has been suppressed on disclosure grounds.

Sheet 5
B2: Workforce jobs | C2: Employee jobs | D2: Self-employment jobs | E2: HM Forces | F2: Government- supported trainees
A3: Current | B3: {=INDEX(B$16:B$1048576,COUNTA(B$16:B$1048576))} -> 36557 | C3: {=INDEX(C$16:C$1048576,COUNTA(C$16:C$1048576))} -> 32291 | D3: {=INDEX(D$16:D$1048576,COUNTA(D$16:D$1048576))} -> 4066 | E3: {=INDEX(E$16:E$1048576,COUNTA(E$16:E$1048576))} -> 148 | F3: {=INDEX(F$16:F$1048576,COUNTA(F$16:F$1048576))} -> 52
A4: Quarterly change | B4: {=INDEX(B$16:B$1048576,COUNTA(B$16:B$1048576))-INDEX(B$16:B$1048576,COUNTA(B$16:B$1048576)-1)} -> -116 | C4: {=INDEX(C$16:C$1048576,COUNTA(C$16:C$1048576))-INDEX(C$16:C$1048576,COUNTA(C$16:C$1048576)-1)} -> -15 | D4: {=INDEX(D$16:D$1048576,COUNTA(D$16:D$1048576))-INDEX(D$16:D$1048576,COUNTA(D$16:D$1048576)-1)} -> -120 | E4: {=INDEX(E$16:E$1048576,COUNTA(E$16:E$1048576))-INDEX(E$16:E$1048576,COUNTA(E$16:E$1048576)-1)} -> 1 | F4: {=INDEX(F$16:F$1048576,COUNTA(F$16:F$1048576))-INDEX(F$16:F$1048576,COUNTA(F$16:F$1048576)-1)} -> 18
A5: Max | B5: =MAX(B$16:B$1048576) -> 36931 | C5: =MAX(C$16:C$1048576) -> 32388 | D5: =MAX(D$16:D$1048576) -> 4693 | E5: =MAX(E$16:E$1048576) -> 595 | F5: =MAX(F$16:F$1048576) -> 467
A6: Jobs created since new gov | B6: {=INDEX(B$16:B$1048576,COUNTA(B$16:B$1048576))-B$276} -> -78 | C6: {=INDEX(C$16:C$1048576,COUNTA(C$16:C$1048576))-C$276} -> 75 | D6: {=INDEX(D$16:D$1048576,COUNTA(D$16:D$1048576))-D$276} -> -170 | E6: {=INDEX(E$16:E$1048576,COUNTA(E$16:E$1048576))-E$276} -> -1 | F6: {=INDEX(F$16:F$1048576,COUNTA(F$16:F$1048576))-F$276} -> 18
A8: Table 5: Workforce jobs (seasonally adjusted)1
A9: Date of publication: | C9: 45916 | E9: Date of next publication: | F9: 46007
A10: Inquiries: Email: | C10: workforce.jobs@ons.gov.uk | E10: Telephone: | F10: 01633 455400
F11: Sources: Employer surveys, Labour Force Survey and administrative sources
A12: United Kingdom (thousands) seasonally adjusted
B13: Workforce jobs1 | C13: Employee jobs1 | D13: Self-employment jobs2 | E13: HM Forces | F13: Government- supported trainees2 3
B14: 1 | C14: 2 | D14: 3 | E14: 4 | F14: 5
B15: DYDC | C15: BCAJ | D15: DYZN | E15: LOJX | F15: LOJU
A16: Jun 59 | B16: 25555 | C16: 23125 | D16: 1835 | E16: 595 | F16: 0
A17: Sep 59 | B17: 25660 | C17: 23248 | D17: 1834 | E17: 577 | F17: 0
A18: Dec 59 | B18: 25751 | C18: 23370 | D18: 1820 | E18: 560 | F18: 0
A19: Mar 60 | B19: 25905 | C19: 23531 | D19: 1824 | E19: 550 | F19: 0
A20: Jun 60 | B20: 26015 | C20: 23634 | D20: 1840 | E20: 541 | F20: 0
A21: Sep 60 | B21: 26060 | C21: 23685 | D21: 1839 | E21: 536 | F21: 0
A22: Dec 60 | B22: 26246 | C22: 23894 | D22: 1827 | E22: 526 | F22: 0
A23: Mar 61 | B23: 26345 | C23: 24011 | D23: 1827 | E23: 507 | F23: 0
A24: Jun 61 | B24: 26312 | C24: 23985 | D24: 1832 | E24: 495 | F24: 0
A25: Sep 61 | B25: 26374 | C25: 24065 | D25: 1824 | E25: 485 | F25: 0
A26: Dec 61 | B26: 26301 | C26: 24014 | D26: 1812 | E26: 475 | F26: 0
A27: Mar 62 | B27: 26450 | C27: 24175 | D27: 1809 | E27: 466 | F27: 0
... A274: Dec 23 (r) | B274: 36470 | C274: 32144 | D274: 4137 | E274: 151 | F274: 38
A275: Mar 24 (r) | B275: 36711 | C275: 32203 | D275: 4329 | E275: 148 | F275: 31 | G275: 1
A276: Jun 24 (r) | B276: 36635 | C276: 32216 | D276: 4236 | E276: 149 | F276: 34 | G276: 1
A277: Sep 24 (r) | B277: 36672 | C277: 32216 | D277: 4266 | E277: 148 | F277: 42
A278: Dec 24 (r) | B278: 36829 | C278: 32348 | D278: 4279 | E278: 147 | F278: 55
A279: Mar 25 (r) | B279: 36931 | C279: 32388 | D279: 4342 | E279: 148 | F279: 53
A280: Jun 25 (r) | B280: 36673 | C280: 32306 | D280: 4186 | E280: 147 | F280: 34 | H280: =B280-B276 -> 38
A281: Sep 25 (p) | B281: 36557 | C281: 32291 | D281: 4066 | E281: 148 | F281: 52
A282: 2. Workforce Jobs figures are a measure of jobs rather than people. For this reason estimates of self-employment jobs and government supported trainee jobs differ from estimates of people in self-employment and in government supported training and employment programmes. The estimates for government supported trainees shown in this table exclude trainees with contracts of employment as such people are included in the estimates of employee jobs. | G282: =B280-B276 -> 38
A283: 3. Due to a change in the method of compiling the data, there is currently a discontinuity between June and September 2002. These estimates do not include jobs with a contract of employment as such jobs are recorded in the employee jobs series.
A284: 4. The employee jobs data relate to the March 2020 period before reported cases of the coronavirus (COVID-19) in the UK. Self-employment jobs relate to the period February-April 2020 which includes self-employment jobs before and after COVID-19 measures were implemented .
A285: 5. Data for September 2022 onwards, for workforce jobs, self-employment jobs, government supported trainees and in SIC 2007 divisions 01 and 97-98 of employee jobs, has been affected by the reweighting of the LFS, causing a step change discontinuity.

Sheet 10
B1: People | D1: Men | F1: Women
B2: Level1 | C2: Rate per thousand2 | D2: Level1 | E2: Rate per thousand2 | F2: Level1 | G2: Rate per thousand2
A3: Current | B3: {=INDEX(B$18:B$1048576,COUNTA(B$18:B$1048576))} -> 156239 | C3: {=INDEX(C$18:C$1048576,COUNTA(C$18:C$1048576))} -> 5.2700935 | D3: {=INDEX(D$18:D$1048576,COUNTA(D$18:D$1048576))} -> 89850 | E3: {=INDEX(E$18:E$1048576,COUNTA(E$18:E$1048576))} -> 6.0970633 | F3: {=INDEX(F$18:F$1048576,COUNTA(F$18:F$1048576))} -> 66389 | G3: {=INDEX(G$18:G$1048576,COUNTA(G$18:G$1048576))} -> 4.4527267
A4: Quarterly change | B4: {=INDEX(B$18:B$1048576,COUNTA(B$18:B$1048576))-INDEX(B$18:B$1048576,COUNTA(B$18:B$1048576)-3)} -> 51943 | C4: {=INDEX(C$18:C$1048576,COUNTA(C$18:C$1048576))-INDEX(C$18:C$1048576,COUNTA(C$18:C$1048576)-3)} -> 1.7264944 | D4: {=INDEX(D$18:D$1048576,COUNTA(D$18:D$1048576))-INDEX(D$18:D$1048576,COUNTA(D$18:D$1048576)-3)} -> 33820 | E4: {=INDEX(E$18:E$1048576,COUNTA(E$18:E$1048576))-INDEX(E$18:E$1048576,COUNTA(E$18:E$1048576)-3)} -> 2.2583539 | F4: {=INDEX(F$18:F$1048576,COUNTA(F$18:F$1048576))-INDEX(F$18:F$1048576,COUNTA(F$18:F$1048576)-3)} -> 18123 | G4: {=INDEX(G$18:G$1048576,COUNTA(G$18:G$1048576))-INDEX(G$18:G$1048576,COUNTA(G$18:G$1048576)-3)} -> 1.1994616
A5: year on year change | B5: {=INDEX(B$18:B$1048576,COUNTA(B$18:B$1048576))-INDEX(B$18:B$1048576,COUNTA(B$18:B$1048576)-12)} -> 57485 | C5: {=INDEX(C$18:C$1048576,COUNTA(C$18:C$1048576))-INDEX(C$18:C$1048576,COUNTA(C$18:C$1048576)-12)} -> 1.8796563 | D5: {=INDEX(D$18:D$1048576,COUNTA(D$18:D$1048576))-INDEX(D$18:D$1048576,COUNTA(D$18:D$1048576)-12)} -> 29398 | E5: {=INDEX(E$18:E$1048576,COUNTA(E$18:E$1048576))-INDEX(E$18:E$1048576,COUNTA(E$18:E$1048576)-12)} -> 1.8999666 | F5: {=INDEX(F$18:F$1048576,COUNTA(F$18:F$1048576))-INDEX(F$18:F$1048576,COUNTA(F$18:F$1048576)-12)} -> 28087 | G5: {=INDEX(G$18:G$1048576,COUNTA(G$18:G$1048576))-INDEX(G$18:G$1048576,COUNTA(G$18:G$1048576)-12)} -> 1.8513827
A6: Since pandemic | B6: {=INDEX(B$18:B$1048576,COUNTA(B$18:B$1048576))-B$351} -> 49226 | C6: {=INDEX(C$18:C$1048576,COUNTA(C$18:C$1048576))-C$351} -> 1.4237069 | D6: {=INDEX(D$18:D$1048576,COUNTA(D$18:D$1048576))-D$351} -> 31966 | E6: {=INDEX(E$18:E$1048576,COUNTA(E$18:E$1048576))-E$351} -> 1.8926884 | F6: {=INDEX(F$18:F$1048576,COUNTA(F$18:F$1048576))-F$351} -> 17260 | G6: {=INDEX(G$18:G$1048576,COUNTA(G$18:G$1048576))-G$351} -> 0.95702903
A7: Since 2010 election | B7: {=INDEX(B$18:B$1048576,COUNTA(B$18:B$1048576))-B$233} -> -16419 | C7: {=INDEX(C$18:C$1048576,COUNTA(C$18:C$1048576))-C$233} -> -1.6509949 | D7: {=INDEX(D$18:D$1048576,COUNTA(D$18:D$1048576))-D$233} -> -28786 | E7: {=INDEX(E$18:E$1048576,COUNTA(E$18:E$1048576))-E$233} -> -3.3650026 | F7: {=INDEX(F$18:F$1048576,COUNTA(F$18:F$1048576))-F$233} -> 12367 | G7: {=INDEX(G$18:G$1048576,COUNTA(G$18:G$1048576))-G$233} -> 0.099129394
A9: Table 10: Redundancies levels1 and rates2 for those aged 16 and over
A10: Date of publication: | B10: 45643 | G10: Date of next publication: | I10: 45678
A11: Inquiries: Email: | B11: labour.market@ons.gov.uk | F11: Tel: 01633 455400 | H11: Source: Labour Force Survey
A12: United Kingdom (thousands)
B13: People | D13: Men | F13: Women
B15: Level1 | C15: Rate per thousand2 | D15: Level1 | E15: Rate per thousand2 | F15: Level1 | G15: Rate per thousand2
A16: Dataset identifier code | B16: BEAO | C16: BEIR | D16: BEIU | E16: BEIX | F16: BEJA | G16: BEJD
A18: Mar-May 1992 | B18: .. | C18: .. | D18: .. | E18: .. | F18: .. | G18: ..
A19: Apr-Jun 1992 | B19: .. | C19: .. | D19: .. | E19: .. | F19: .. | G19: ..
A20: May-Jul 1992 | B20: .. | C20: .. | D20: .. | E20: .. | F20: .. | G20: ..
A21: Jun-Aug 1992 | B21: .. | C21: .. | D21: .. | E21: .. | F21: .. | G21: ..
A22: Jul-Sep 1992 | B22: .. | C22: .. | D22: .. | E22: .. | F22: .. | G22: ..
A23: Aug-Oct 1992 | B23: .. | C23: .. | D23: .. | E23: .. | F23: .. | G23: ..
A24: Sep-Nov 1992 | B24: .. | C24: .. | D24: .. | E24: .. | F24: .. | G24: ..
A25: Oct-Dec 1992 | B25: .. | C25: .. | D25: .. | E25: .. | F25: .. | G25: ..
A26: Nov-Jan 1993 | B26: .. | C26: .. | D26: .. | E26: .. | F26: .. | G26: ..
A27: Dec-Feb 1993 | B27: .. | C27: .. | D27: .. | E27: .. | F27: .. | G27: ..
A28: Jan-Mar 1993 | B28: .. | C28: .. | D28: .. | E28: .. | F28: .. | G28: ..
... A53: Feb-Apr 1995 | B53: .. | C53: .. | D53: .. | E53: .. | F53: .. | G53: ..
A54: Mar-May 1995 | B54: 178580 | C54: 8.251544 | D54: 110631 | E54: 9.9189782 | F54: 67949 | G54: 6.4784023
A55: Apr-Jun 1995 | B55: 178249 | C55: 8.2250899 | D55: 109540 | E55: 9.8141913 | F55: 68709 | G55: 6.5374969
A56: May-Jul 1995 | B56: 168000 | C56: 7.7329073 | D56: 103867 | E56: 9.2790908 | F56: 64133 | G56: 6.0895355
A57: Jun-Aug 1995 | B57: 163905 | C57: 7.5347454 | D57: 104365 | E57: 9.2990437 | F57: 59540 | G57: 5.6543068
A58: Jul-Sep 1995 | B58: 164420 | C58: 7.5466264 | D58: 105296 | E58: 9.3726495 | F58: 59124 | G58: 5.6026685
A59: Aug-Oct 1995 | B59: 166301 | C59: 7.614352 | D59: 109483 | E59: 9.7290985 | F59: 56818 | G59: 5.3666099
A60: Sep-Nov 1995 | B60: 172777 | C60: 7.8856048 | D60: 110607 | E60: 9.7931999 | F60: 62170 | G60: 5.8561635
A61: Oct-Dec 1995 | B61: 162067 | C61: 7.3918845 | D61: 105156 | E61: 9.3096925 | F61: 56911 | G61: 5.353978
A62: Nov-Jan 1996 | B62: 179069 | C62: 8.1652749 | D62: 118724 | E62: 10.525961 | F62: 60345 | G62: 5.6654558
A63: Dec-Feb 1996 | B63: 181867 | C63: 8.2774116 | D63: 119522 | E63: 10.572536 | F63: 62345 | G63: 5.8449181
A64: Jan-Mar 1996 | B64: 195674 | C64: 8.866101 | D64: 130879 | E64: 11.520213 | F64: 64795 | G64: 6.0504675
A65: Feb-Apr 1996 | B65: 180895 | C65: 8.1844071 | D65: 118927 | E65: 10.471299 | F65: 61968 | G65: 5.7671641
... A407: Aug-Oct 2024 | B407: 98754 | C407: 3.3904372 | D407: 60452 | E407: 4.1970967 | F407: 38302 | G407: 2.601344
A408: Sep-Nov 2024 | B408: 111553 | C408: 3.8061282 | D408: 69339 | E408: 4.7764719 | F408: 42214 | G408: 2.8538389 | L408: =AVERAGE(C340:C350) -> 3.8945596
A409: Oct-Dec 2024 | B409: 113784 | C409: 3.8897008 | D409: 69852 | E409: 4.826236 | F409: 43932 | G409: 2.972547 | L409: =C419-L408 -> 1.3755338
A410: Nov-Jan 2025 | B410: 123983 | C410: 4.2450658 | D410: 78222 | E410: 5.3986596 | F410: 45761 | G410: 3.1093493
A411: Dec-Feb 2025 | B411: 117208 | C411: 4.0132156 | D411: 73992 | E411: 5.0958151 | F411: 43216 | G411: 2.9427952
A412: Jan-Mar 2025 | B412: 110084 | C412: 3.756666 | D412: 75913 | E412: 5.2175403 | F412: 34171 | G412: 2.3160394
A413: Feb-Apr 2025 | B413: 101937 | C413: 3.471822 | D413: 71849 | E413: 4.9326788 | F413: 30088 | G413: 2.0336158
A414: Mar-May 2025 | B414: 114155 | C414: 3.8853255 | D414: 72474 | E414: 4.9818354 | F414: 41681 | G414: 2.8099397
A415: Apr-Jun 2025 | B415: 106640 | C415: 3.6295019 | D415: 61830 | E415: 4.250868 | F415: 44810 | G415: 3.0203197
A416: May-Jul 2025 | B416: 104296 | C416: 3.5435991 | D416: 56030 | E416: 3.8387094 | F416: 48266 | G416: 3.2532651
A417: Jun-Aug 2025 | B417: 113041 | C417: 3.8286644 | D417: 66714 | E417: 4.5498035 | F417: 46327 | G417: 3.1171723
A418: Jul-Sep 2025 | B418: 133786 | C418: 4.5133321 | D418: 77994 | E418: 5.3016198 | F418: 55792 | G418: 3.7366432
A419: Aug-Oct 2025 | B419: 156239 | C419: 5.2700935 | D419: 89850 | E419: 6.0970633 | F419: 66389 | G419: 4.4527267
A420: 2. The redundancy rate is the ratio of the redundancy level for the given quarter to the seasonally adjusted number of employees in the previous quarter, multiplied by 1,000.
A421: 3. Data from July to September 2022 onward has been reweighted, causing a step change discontinuity.
A423: Quality indicator
A424: Shaded estimates are based on a small sample size. This may result in less precise estimates, which should be used with caution.
A425: Unshaded estimates are based on a larger sample size. This is likely to result in estimates of higher precision, although they will still be subject to some sampling variability.
A426: * Estimate has been suppressed on disclosure grounds.

Sheet 11
C1: Economic inactivity by reason (thousands) | M1: Percentage of economically inactive (%) | W1: Economic inactivity by wants a job (thousands) | AD1: Percentage of economically inactive by wants a job (%) | AK1: Economic inactivity by does not want a job (thousands) | AR1: Percentage of economically inactive by does not want a job (%)
B2: Total economically inactive aged 16-64 (thousands)4 | C2: Student | D2: Looking after family / home | E2: Temp sick | F2: Long-term sick | G2: Discouraged workers1 | H2: Retired | I2: Other2 | J2: Does not want job (thousands) | K2: Wants a job (thousands) | L2: Total economically inactive aged 16-64 | M2: Student | N2: Looking after family / home | O2: Temp sick | P2: Long-term sick | Q2: Discouraged workers1 | R2: Retired | S2: Other2 | T2: Does not want job (%age of economically inactive) | U2: Wants a job (%age of economically inactive) | V2: Total economically inactive wants a job aged 16-64 (thousands) | W2: Student | X2: Looking after family / home | Y2: Temp sick | Z2: Long-term sick | AA2: Discouraged workers1 | AB2: Other2 | AC2: Total wants a job aged 16-64 | AD2: Student | AE2: Looking after family / home | AF2: Temp sick | AG2: Long-term sick | AH2: Discouraged workers1 | AI2: Other2 | AJ2: Total economically inactive does not want a job aged 16-64 (thousands) | AK2: Student | AL2: Looking after family / home | AM2: Temp sick | AN2: Long-term sick | AO2: Retired | AP2: Other2 | AQ2: Total does not want a job aged 16-64 | AR2: Student | AS2: Looking after family / home | AT2: Temp sick | AU2: Long-term sick | AV2: Retired | AW2: Other2
A3: Current | B3: {=INDEX(B$18:B$1048576,COUNTA(B$18:B$1048576))} -> 9098658.3 | C3: {=INDEX(C$30:C$1048576,COUNTA(C$30:C$1048576))} -> 2349638 | D3: {=INDEX(D$30:D$1048576,COUNTA(D$30:D$1048576))} -> 1585084.5 | E3: {=INDEX(E$30:E$1048576,COUNTA(E$30:E$1048576))} -> 189524.3 | F3: {=INDEX(F$30:F$1048576,COUNTA(F$30:F$1048576))} -> 2810366.6 | G3: {=INDEX(G$30:G$1048576,COUNTA(G$30:G$1048576))} -> 40985.795 | H3: {=INDEX(H$30:H$1048576,COUNTA(H$30:H$1048576))} -> 1042702.3 | I3: {=INDEX(I$30:I$1048576,COUNTA(I$30:I$1048576))} -> 1080356.8 | J3: {=INDEX(J$30:J$1048576,COUNTA(J$30:J$1048576))} -> 6967924 | K3: {=INDEX(K$30:K$1048576,COUNTA(K$30:K$1048576))} -> 2130734.3 | L3: {=INDEX(L$18:L$1048576,COUNTA(L$18:L$1048576))} -> 100 | M3: {=INDEX(M$30:M$1048576,COUNTA(M$30:M$1048576))} -> 25.824005 | N3: {=INDEX(N$30:N$1048576,COUNTA(N$30:N$1048576))} -> 17.421079 | O3: {=INDEX(O$30:O$1048576,COUNTA(O$30:O$1048576))} -> 2.0829917 | P3: {=INDEX(P$30:P$1048576,COUNTA(P$30:P$1048576))} -> 30.887704 | Q3: {=INDEX(Q$30:Q$1048576,COUNTA(Q$30:Q$1048576))} -> 0.45045976 | R3: {=INDEX(R$30:R$1048576,COUNTA(R$30:R$1048576))} -> 11.459956 | S3: {=INDEX(S$30:S$1048576,COUNTA(S$30:S$1048576))} -> 11.873804 | T3: {=INDEX(T$30:T$1048576,COUNTA(T$30:T$1048576))} -> 76.581885 | U3: {=INDEX(U$30:U$1048576,COUNTA(U$30:U$1048576))} -> 23.418115 | V3: {=INDEX(V$18:V$1048576,COUNTA(V$18:V$1048576))} -> 2130734.3 | W3: {=INDEX(W$18:W$1048576,COUNTA(W$18:W$1048576))} -> 519773.77 | X3: {=INDEX(X$18:X$1048576,COUNTA(X$18:X$1048576))} -> 392475.66 | Y3: {=INDEX(Y$18:Y$1048576,COUNTA(Y$18:Y$1048576))} -> 93116.24 | Z3: {=INDEX(Z$18:Z$1048576,COUNTA(Z$18:Z$1048576))} -> 738422.59 | AA3: {=INDEX(AA$18:AA$1048576,COUNTA(AA$18:AA$1048576))} -> 27848.593 | AB3: {=INDEX(AB$18:AB$1048576,COUNTA(AB$18:AB$1048576))} -> 359183.3 | AC3: {=INDEX(AC$18:AC$1048576,COUNTA(AC$18:AC$1048576))} -> 100 | ... AW3: {=INDEX(AW$18:AW$1048576,COUNTA(AW$18:AW$1048576))} -> 10.430023
A4: Quarterly change | B4: {=INDEX(B$18:B$1048576,COUNTA(B$18:B$1048576))-INDEX(B$18:B$1048576,COUNTA(B$18:B$1048576)-3)} -> -25615.944 | C4: {=INDEX(C$18:C$1048576,COUNTA(C$18:C$1048576))-INDEX(C$18:C$1048576,COUNTA(C$18:C$1048576)-3)} -> -18212.587 | D4: {=INDEX(D$18:D$1048576,COUNTA(D$18:D$1048576))-INDEX(D$18:D$1048576,COUNTA(D$18:D$1048576)-3)} -> -29939.805 | E4: {=INDEX(E$18:E$1048576,COUNTA(E$18:E$1048576))-INDEX(E$18:E$1048576,COUNTA(E$18:E$1048576)-3)} -> -3000.4557 | F4: {=INDEX(F$18:F$1048576,COUNTA(F$18:F$1048576))-INDEX(F$18:F$1048576,COUNTA(F$18:F$1048576)-3)} -> 13296.123 | G4: {=INDEX(G$18:G$1048576,COUNTA(G$18:G$1048576))-INDEX(G$18:G$1048576,COUNTA(G$18:G$1048576)-3)} -> 13992.131 | H4: {=INDEX(H$18:H$1048576,COUNTA(H$18:H$1048576))-INDEX(H$18:H$1048576,COUNTA(H$18:H$1048576)-3)} -> 1653.9174 | I4: {=INDEX(I$18:I$1048576,COUNTA(I$18:I$1048576))-INDEX(I$18:I$1048576,COUNTA(I$18:I$1048576)-3)} -> -3405.2681 | ... AW4: {=INDEX(AW$18:AW$1048576,COUNTA(AW$18:AW$1048576))-INDEX(AW$18:AW$1048576,COUNTA(AW$18:AW$1048576)-3)} -> -0.1935363
A5: year on year change | B5: {=INDEX(B$18:B$1048576,COUNTA(B$18:B$1048576))-INDEX(B$18:B$1048576,COUNTA(B$18:B$1048576)-12)} -> -234336.28 | C5: {=INDEX(C$18:C$1048576,COUNTA(C$18:C$1048576))-INDEX(C$18:C$1048576,COUNTA(C$18:C$1048576)-12)} -> -116542.86 | D5: {=INDEX(D$18:D$1048576,COUNTA(D$18:D$1048576))-INDEX(D$18:D$1048576,COUNTA(D$18:D$1048576)-12)} -> -99983.743 | E5: {=INDEX(E$18:E$1048576,COUNTA(E$18:E$1048576))-INDEX(E$18:E$1048576,COUNTA(E$18:E$1048576)-12)} -> -8531.7342 | F5: {=INDEX(F$18:F$1048576,COUNTA(F$18:F$1048576))-INDEX(F$18:F$1048576,COUNTA(F$18:F$1048576)-12)} -> 15412.858 | G5: {=INDEX(G$18:G$1048576,COUNTA(G$18:G$1048576))-INDEX(G$18:G$1048576,COUNTA(G$18:G$1048576)-12)} -> 15502.771 | H5: {=INDEX(H$18:H$1048576,COUNTA(H$18:H$1048576))-INDEX(H$18:H$1048576,COUNTA(H$18:H$1048576)-12)} -> -52575.374 | I5: {=INDEX(I$18:I$1048576,COUNTA(I$18:I$1048576))-INDEX(I$18:I$1048576,COUNTA(I$18:I$1048576)-12)} -> 12381.803 | ... AW5: {=INDEX(AW$18:AW$1048576,COUNTA(AW$18:AW$1048576))-INDEX(AW$18:AW$1048576,COUNTA(AW$18:AW$1048576)-12)} -> 0.44781369
A6: Since pandemic | B6: {=INDEX(B$18:B$1048576,COUNTA(B$18:B$1048576))-B$351} -> 652867.86 | C6: {=INDEX(C$18:C$1048576,COUNTA(C$18:C$1048576))-C$351} -> 184416.4 | D6: {=INDEX(D$18:D$1048576,COUNTA(D$18:D$1048576))-D$351} -> -287119.77 | E6: {=INDEX(E$18:E$1048576,COUNTA(E$18:E$1048576))-E$351} -> 15540.059 | F6: {=INDEX(F$18:F$1048576,COUNTA(F$18:F$1048576))-F$351} -> 692335.83 | G6: {=INDEX(G$18:G$1048576,COUNTA(G$18:G$1048576))-G$351} -> 5981.2709 | H6: {=INDEX(H$18:H$1048576,COUNTA(H$18:H$1048576))-H$351} -> -75620.86 | I6: {=INDEX(I$18:I$1048576,COUNTA(I$18:I$1048576))-I$351} -> 117334.93 | ... AW6: {=INDEX(AW$18:AW$1048576,COUNTA(AW$18:AW$1048576))-AW$351} -> 0.62532245
A7: Since 2010 election | B7: {=INDEX(B$18:B$1048576,COUNTA(B$18:B$1048576))-B$233} -> -400441.51 | C7: {=INDEX(C$18:C$1048576,COUNTA(C$18:C$1048576))-C$233} -> 32951.873 | D7: {=INDEX(D$18:D$1048576,COUNTA(D$18:D$1048576))-D$233} -> -783736.6 | E7: {=INDEX(E$18:E$1048576,COUNTA(E$18:E$1048576))-E$233} -> 9724.8282 | F7: {=INDEX(F$18:F$1048576,COUNTA(F$18:F$1048576))-F$233} -> 582860.6 | G7: {=INDEX(G$18:G$1048576,COUNTA(G$18:G$1048576))-G$233} -> -39045.382 | H7: {=INDEX(H$18:H$1048576,COUNTA(H$18:H$1048576))-H$233} -> -485146.15 | I7: {=INDEX(I$18:I$1048576,COUNTA(I$18:I$1048576))-I$233} -> 281949.32 | ... AW7: {=INDEX(AW$18:AW$1048576,COUNTA(AW$18:AW$1048576))-AW$233} -> 3.81891
A9: Table 11: Economic inactivity for those aged from 16 to 64 (seasonally adjusted)
A10: Date of publication: | B10: 45643 | G10: Date of next publication: | I10: 45678 | L10: Source: Labour Force Survey
A11: Inquiries: Email: | B11: labour.market@ons.gov.uk | F11: Tel: 01633 455400
A12: United Kingdom (thousands) seasonally adjusted
C13: Economic inactivity by reason (thousands) | M13: Percentage of economically inactive (%) | W13: Economic inactivity by wants a job (thousands) | AD13: Percentage of economically inactive by wants a job (%) | AK13: Economic inactivity by does not want a job (thousands) | AR13: Percentage of economically inactive by does not want a job (%)
B14: Total economically inactive aged 16-64 (thousands)4 | C14: Student | D14: Looking after family / home | E14: Temp sick | F14: Long-term sick | G14: Discouraged workers1 | H14: Retired | I14: Other2 | J14: Does not want job (thousands) | K14: Wants a job (thousands) | L14: Total economically inactive aged 16-64 | M14: Student | N14: Looking after family / home | O14: Temp sick | P14: Long-term sick | Q14: Discouraged workers1 | R14: Retired | S14: Other2 | T14: Does not want job (%age of economically inactive) | U14: Wants a job (%age of economically inactive) | V14: Total economically inactive wants a job aged 16-64 (thousands) | W14: Student | X14: Looking after family / home | Y14: Temp sick | Z14: Long-term sick | AA14: Discouraged workers1 | AB14: Other2 | AC14: Total wants a job aged 16-64 | AD14: Student | AE14: Looking after family / home | AF14: Temp sick | AG14: Long-term sick | AH14: Discouraged workers1 | AI14: Other2 | AJ14: Total economically inactive does not want a job aged 16-64 (thousands) | AK14: Student | AL14: Looking after family / home | AM14: Temp sick | AN14: Long-term sick | AO14: Retired | AP14: Other2 | AQ14: Total does not want a job aged 16-64 | AR14: Student | AS14: Looking after family / home | AT14: Temp sick | AU14: Long-term sick | AV14: Retired | AW14: Other2
A16: Dataset identifier code | C16: LF63 | D16: LF65 | E16: LF67 | F16: LF69 | G16: LFL8 | H16: LF6B | I16: LF6D | J16: LFL9 | K16: LFM2 | L16: LF6V | M16: LF6X | N16: LF6Z | O16: LF73 | P16: LF75 | Q16: LF77 | R16: LF79 | S16: LF7B | T16: LF7D | U16: LF7F | V16: LFM2 | W16: LF6F | X16: LFP7 | Y16: LF6H | Z16: LFP8 | AA16: LF8B | AB16: LF6J | AC16: LF7H | AD16: LF7J | AE16: LF7L | AF16: LF7N | AG16: LF7P | AH16: LF7R | AI16: LF7T | AJ16: LFL9 | AK16: LF6L | AL16: LF6N | AM16: LF6P | AN16: LF6R | AO16: LF8E | AP16: LF6T | AQ16: LF7V | AR16: LF7X | AS16: LF7Z | AT16: LF83 | AU16: LF85 | AV16: LF87 | AW16: LF89
A18: Mar-May 1992 | B18: 8428354.6 | C18: .. | D18: .. | E18: .. | F18: .. | G18: .. | H18: .. | I18: .. | J18: .. | K18: .. | L18: 100 | M18: .. | N18: .. | O18: .. | P18: .. | Q18: .. | R18: .. | S18: .. | T18: .. | U18: .. | V18: 1989330.4 | W18: .. | X18: .. | Y18: .. | Z18: .. | AA18: .. | AB18: .. | AC18: 100 | AD18: .. | AE18: .. | AF18: .. | AG18: .. | AH18: .. | AI18: .. | AJ18: 6439024.2 | AK18: .. | AL18: .. | AM18: .. | AN18: .. | AO18: .. | AP18: .. | AQ18: 100 | AR18: .. | AS18: .. | AT18: .. | AU18: .. | AV18: .. | AW18: ..
A19: Apr-Jun 1992 | B19: 8481002.7 | C19: .. | D19: .. | E19: .. | F19: .. | G19: .. | H19: .. | I19: .. | J19: .. | K19: .. | L19: 100 | M19: .. | N19: .. | O19: .. | P19: .. | Q19: .. | R19: .. | S19: .. | T19: .. | U19: .. | V19: 1985287.1 | W19: .. | X19: .. | Y19: .. | Z19: .. | AA19: .. | AB19: .. | AC19: 100 | AD19: .. | AE19: .. | AF19: .. | AG19: .. | AH19: .. | AI19: .. | AJ19: 6495715.6 | AK19: .. | AL19: .. | AM19: .. | AN19: .. | AO19: .. | AP19: .. | AQ19: 100 | AR19: .. | AS19: .. | AT19: .. | AU19: .. | AV19: .. | AW19: ..
A20: May-Jul 1992 | B20: 8506768.3 | C20: .. | D20: .. | E20: .. | F20: .. | G20: .. | H20: .. | I20: .. | J20: .. | K20: .. | L20: 100 | M20: .. | N20: .. | O20: .. | P20: .. | Q20: .. | R20: .. | S20: .. | T20: .. | U20: .. | V20: 1991311.2 | W20: .. | X20: .. | Y20: .. | Z20: .. | AA20: .. | AB20: .. | AC20: 100 | AD20: .. | AE20: .. | AF20: .. | AG20: .. | AH20: .. | AI20: .. | AJ20: 6515457.1 | AK20: .. | AL20: .. | AM20: .. | AN20: .. | AO20: .. | AP20: .. | AQ20: 100 | AR20: .. | AS20: .. | AT20: .. | AU20: .. | AV20: .. | AW20: ..
A21: Jun-Aug 1992 | B21: 8500965.7 | C21: .. | D21: .. | E21: .. | F21: .. | G21: .. | H21: .. | I21: .. | J21: .. | K21: .. | L21: 100 | M21: .. | N21: .. | O21: .. | P21: .. | Q21: .. | R21: .. | S21: .. | T21: .. | U21: .. | V21: 2000140.9 | W21: .. | X21: .. | Y21: .. | Z21: .. | AA21: .. | AB21: .. | AC21: 100 | AD21: .. | AE21: .. | AF21: .. | AG21: .. | AH21: .. | AI21: .. | AJ21: 6500824.9 | AK21: .. | AL21: .. | AM21: .. | AN21: .. | AO21: .. | AP21: .. | AQ21: 100 | AR21: .. | AS21: .. | AT21: .. | AU21: .. | AV21: .. | AW21: ..
A22: Jul-Sep 1992 | B22: 8511906.3 | C22: .. | D22: .. | E22: .. | F22: .. | G22: .. | H22: .. | I22: .. | J22: .. | K22: .. | L22: 100 | M22: .. | N22: .. | O22: .. | P22: .. | Q22: .. | R22: .. | S22: .. | T22: .. | U22: .. | V22: 1995638.4 | W22: .. | X22: .. | Y22: .. | Z22: .. | AA22: .. | AB22: .. | AC22: 100 | AD22: .. | AE22: .. | AF22: .. | AG22: .. | AH22: .. | AI22: .. | AJ22: 6516267.9 | AK22: .. | AL22: .. | AM22: .. | AN22: .. | AO22: .. | AP22: .. | AQ22: 100 | AR22: .. | AS22: .. | AT22: .. | AU22: .. | AV22: .. | AW22: ..
A23: Aug-Oct 1992 | B23: 8525902.4 | C23: .. | D23: .. | E23: .. | F23: .. | G23: .. | H23: .. | I23: .. | J23: .. | K23: .. | L23: 100 | M23: .. | N23: .. | O23: .. | P23: .. | Q23: .. | R23: .. | S23: .. | T23: .. | U23: .. | V23: 1996011.9 | W23: .. | X23: .. | Y23: .. | Z23: .. | AA23: .. | AB23: .. | AC23: 100 | AD23: .. | AE23: .. | AF23: .. | AG23: .. | AH23: .. | AI23: .. | AJ23: 6529890.5 | AK23: .. | AL23: .. | AM23: .. | AN23: .. | AO23: .. | AP23: .. | AQ23: 100 | AR23: .. | AS23: .. | AT23: .. | AU23: .. | AV23: .. | AW23: ..
A24: Sep-Nov 1992 | B24: 8511037.4 | C24: .. | D24: .. | E24: .. | F24: .. | G24: .. | H24: .. | I24: .. | J24: .. | K24: .. | L24: 100 | M24: .. | N24: .. | O24: .. | P24: .. | Q24: .. | R24: .. | S24: .. | T24: .. | U24: .. | V24: 2003703.5 | W24: .. | X24: .. | Y24: .. | Z24: .. | AA24: .. | AB24: .. | AC24: 100 | AD24: .. | AE24: .. | AF24: .. | AG24: .. | AH24: .. | AI24: .. | AJ24: 6507333.9 | AK24: .. | AL24: .. | AM24: .. | AN24: .. | AO24: .. | AP24: .. | AQ24: 100 | AR24: .. | AS24: .. | AT24: .. | AU24: .. | AV24: .. | AW24: ..
A25: Oct-Dec 1992 | B25: 8536284.2 | C25: .. | D25: .. | E25: .. | F25: .. | G25: .. | H25: .. | I25: .. | J25: .. | K25: .. | L25: 100 | M25: .. | N25: .. | O25: .. | P25: .. | Q25: .. | R25: .. | S25: .. | T25: .. | U25: .. | V25: 2012595.8 | W25: .. | X25: .. | Y25: .. | Z25: .. | AA25: .. | AB25: .. | AC25: 100 | AD25: .. | AE25: .. | AF25: .. | AG25: .. | AH25: .. | AI25: .. | AJ25: 6523688.4 | AK25: .. | AL25: .. | AM25: .. | AN25: .. | AO25: .. | AP25: .. | AQ25: 100 | AR25: .. | AS25: .. | AT25: .. | AU25: .. | AV25: .. | AW25: ..
A26: Nov-Jan 1993 | B26: 8518694 | C26: .. | D26: .. | E26: .. | F26: .. | G26: .. | H26: .. | I26: .. | J26: .. | K26: .. | L26: 100 | M26: .. | N26: .. | O26: .. | P26: .. | Q26: .. | R26: .. | S26: .. | T26: .. | U26: .. | V26: 2008652 | W26: .. | X26: .. | Y26: .. | Z26: .. | AA26: .. | AB26: .. | AC26: 100 | AD26: .. | AE26: .. | AF26: .. | AG26: .. | AH26: .. | AI26: .. | AJ26: 6510041.9 | AK26: .. | AL26: .. | AM26: .. | AN26: .. | AO26: .. | AP26: .. | AQ26: 100 | AR26: .. | AS26: .. | AT26: .. | AU26: .. | AV26: .. | AW26: ..
A27: Dec-Feb 1993 | B27: 8507114.4 | C27: .. | D27: .. | E27: .. | F27: .. | G27: .. | H27: .. | I27: .. | J27: .. | K27: .. | L27: 100 | M27: .. | N27: .. | O27: .. | P27: .. | Q27: .. | R27: .. | S27: .. | T27: .. | U27: .. | V27: 1977317.8 | W27: .. | X27: .. | Y27: .. | Z27: .. | AA27: .. | AB27: .. | AC27: 100 | AD27: .. | AE27: .. | AF27: .. | AG27: .. | AH27: .. | AI27: .. | AJ27: 6529796.6 | AK27: .. | AL27: .. | AM27: .. | AN27: .. | AO27: .. | AP27: .. | AQ27: 100 | AR27: .. | AS27: .. | AT27: .. | AU27: .. | AV27: .. | AW27: ..
A28: Jan-Mar 1993 | B28: 8518692.9 | C28: .. | D28: .. | E28: .. | F28: .. | G28: .. | H28: .. | I28: .. | J28: .. | K28: .. | L28: 100 | M28: .. | N28: .. | O28: .. | P28: .. | Q28: .. | R28: .. | S28: .. | T28: .. | U28: .. | V28: 2049599.5 | W28: .. | X28: .. | Y28: .. | Z28: .. | AA28: .. | AB28: .. | AC28: 100 | AD28: .. | AE28: .. | AF28: .. | AG28: .. | AH28: .. | AI28: .. | AJ28: 6469093.4 | AK28: .. | AL28: .. | AM28: .. | AN28: .. | AO28: .. | AP28: .. | AQ28: 100 | AR28: .. | AS28: .. | AT28: .. | AU28: .. | AV28: .. | AW28: ..
A29: Feb-Apr 1993 | B29: 8556560.4 | C29: .. | D29: .. | E29: .. | F29: .. | G29: .. | H29: .. | I29: .. | J29: .. | K29: .. | L29: 100 | M29: .. | N29: .. | O29: .. | P29: .. | Q29: .. | R29: .. | S29: .. | T29: .. | U29: .. | V29: 2105097.8 | W29: .. | X29: .. | Y29: .. | Z29: .. | AA29: .. | AB29: .. | AC29: 100 | AD29: .. | AE29: .. | AF29: .. | AG29: .. | AH29: .. | AI29: .. | AJ29: 6451462.6 | AK29: .. | AL29: .. | AM29: .. | AN29: .. | AO29: .. | AP29: .. | AQ29: 100 | AR29: .. | AS29: .. | AT29: .. | AU29: .. | AV29: .. | AW29: ..
A30: Mar-May 1993 | B30: 8556939.1 | C30: 1450577.4 | D30: 3023835.8 | E30: 206486.54 | F30: 1812698.2 | G30: 166551.64 | H30: 1084924.9 | I30: 811864.66 | J30: 6371717.6 | K30: 2185221.5 | L30: 100 | M30: 16.952059 | N30: 35.33782 | O30: 2.4130888 | P30: 21.183956 | Q30: 1.9463927 | R30: 12.67889 | S30: 9.487793 | T30: 74.46258 | U30: 25.53742 | V30: 2185221.5 | W30: 321683.77 | X30: 822488.65 | Y30: 127594.68 | Z30: 425620.19 | AA30: 166551.64 | AB30: 321282.59 | AC30: 100 | AD30: 14.720877 | AE30: 37.638685 | AF30: 5.8389817 | AG30: 19.47721 | AH30: 7.6217278 | AI30: 14.702518 | AJ30: 6371717.6 | AK30: 1128893.6 | AL30: 2201347.1 | AM30: 78891.853 | AN30: 1387078 | AO30: 1084924.9 | AP30: 490582.08 | AQ30: 100 | AR30: 17.717257 | AS30: 34.548724 | AT30: 1.2381568 | AU30: 21.769295 | AV30: 17.027197 | AW30: 7.6993695
A31: Apr-Jun 1993 | B31: 8564917.3 | C31: 1441377.5 | D31: 3016165.5 | E31: 201122.34 | F31: 1833950.4 | G31: 165495.06 | H31: 1100387.8 | I31: 806418.73 | J31: 6388254.1 | K31: 2176663.3 | L31: 100 | M31: 16.828855 | N31: 35.215349 | O31: 2.3482111 | P31: 21.412354 | Q31: 1.9322436 | R31: 12.847618 | S31: 9.4153708 | T31: 74.58629 | U31: 25.41371 | V31: 2176663.3 | W31: 299875.66 | X31: 818461.01 | Y31: 117664.36 | Z31: 439066.01 | AA31: 165495.06 | AB31: 336101.15 | AC31: 100 | AD31: 13.776851 | AE31: 37.601636 | AF31: 5.4057219 | AG31: 20.171518 | AH31: 7.6031541 | AI31: 15.441119 | AJ31: 6388254.1 | AK31: 1141501.8 | AL31: 2197704.5 | AM31: 83457.978 | AN31: 1394884.4 | AO31: 1100387.8 | AP31: 470317.57 | AQ31: 100 | AR31: 17.868761 | AS31: 34.402271 | AT31: 1.3064286 | AU31: 21.835142 | AV31: 17.225173 | AW31: 7.3622239
A32: May-Jul 1993 | B32: 8565281.5 | C32: 1425547.6 | D32: 2995974.6 | E32: 204581.48 | F32: 1856899.1 | G32: 170664.99 | H32: 1102862.4 | I32: 808751.29 | J32: 6345371.4 | K32: 2219910.2 | L32: 100 | M32: 16.643325 | N32: 34.978121 | O32: 2.3884968 | P32: 21.679371 | Q32: 1.9925205 | R32: 12.875963 | S32: 9.4422033 | T32: 74.082461 | U32: 25.917539 | V32: 2219910.2 | W32: 295175 | X32: 825886.99 | Y32: 118226.73 | Z32: 458888.14 | AA32: 170664.99 | AB32: 351068.32 | AC32: 100 | AD32: 13.296709 | AE32: 37.203622 | AF32: 5.3257439 | AG32: 20.671473 | AH32: 7.6879232 | AI32: 15.814528 | AJ32: 6345371.4 | AK32: 1130372.6 | AL32: 2170087.6 | AM32: 86354.746 | AN32: 1398011 | AO32: 1102862.4 | AP32: 457682.97 | AQ32: 100 | AR32: 17.814129 | AS32: 34.199536 | AT32: 1.3609093 | AU32: 22.031981 | AV32: 17.380581 | AW32: 7.2128635
A33: Jun-Aug 1993 | B33: 8606126.6 | C33: 1455065.1 | D33: 2979010.8 | E33: 198057.87 | F33: 1889398.1 | G33: 168378.82 | H33: 1104304.8 | I33: 811911.06 | J33: 6345666.2 | K33: 2260460.3 | L33: 100 | M33: 16.907317 | N33: 34.615001 | O33: 2.301359 | P33: 21.954105 | Q33: 1.9564995 | R33: 12.831612 | S33: 9.4341055 | T33: 73.734289 | U33: 26.265711 | V33: 2260460.3 | W33: 306488.1 | X33: 836374.91 | Y33: 110154.12 | Z33: 477492.37 | AA33: 168378.82 | AB33: 361572 | AC33: 100 | AD33: 13.558659 | AE33: 37.000203 | AF33: 4.8730836 | AG33: 21.123678 | AH33: 7.4488731 | AI33: 15.995503 | AJ33: 6345666.2 | AK33: 1148577 | AL33: 2142635.9 | AM33: 87903.75 | AN33: 1411905.7 | AO33: 1104304.8 | AP33: 450339.06 | AQ33: 100 | AR33: 18.10018 | AS33: 33.765342 | AT33: 1.3852564 | AU33: 22.249921 | AV33: 17.402504 | AW33: 7.0967971
A34: Jul-Sep 1993 | B34: 8583321 | C34: 1454588.2 | D34: 2975484.2 | E34: 199681.78 | F34: 1884448.4 | G34: 166363.74 | H34: 1101187.3 | I34: 801567.32 | J34: 6301060.4 | K34: 2282260.6 | L34: 100 | M34: 16.946683 | N34: 34.665885 | O34: 2.326393 | P34: 21.95477 | Q34: 1.9382211 | R34: 12.829385 | S34: 9.3386618 | T34: 73.410518 | U34: 26.589482 | V34: 2282260.6 | W34: 321267.6 | X34: 843780.58 | Y34: 113443.11 | Z34: 480165.36 | AA34: 166363.74 | AB34: 357240.18 | AC34: 100 | AD34: 14.076727 | AE34: 36.971264 | AF34: 4.9706468 | AG34: 21.039024 | AH34: 7.2894278 | AI34: 15.65291 | AJ34: 6301060.4 | AK34: 1133320.6 | AL34: 2131703.6 | AM34: 86238.664 | AN34: 1404283 | AO34: 1101187.3 | AP34: 444327.14 | AQ34: 100 | AR34: 17.986189 | AS34: 33.830871 | AT34: 1.3686373 | AU34: 22.286456 | AV34: 17.476222 | AW34: 7.0516248
A35: Aug-Oct 1993 | B35: 8586338.7 | C35: 1453767.2 | D35: 2966535.2 | E35: 194253.75 | F35: 1905032.6 | G35: 166390.99 | H35: 1103458.3 | I35: 796900.61 | J35: 6289442.9 | K35: 2296895.8 | L35: 100 | M35: 16.931165 | N35: 34.549478 | O35: 2.2623583 | P35: 22.186787 | Q35: 1.9378573 | R35: 12.851325 | S35: 9.2810293 | T35: 73.249415 | U35: 26.750585 | V35: 2296895.8 | W35: 321495.86 | X35: 847824.17 | Y35: 112111.64 | Z35: 492821.82 | AA35: 166390.99 | AB35: 356251.32 | AC35: 100 | AD35: 13.996972 | AE35: 36.911738 | AF35: 4.8810067 | AG35: 21.455994 | AH35: 7.244168 | AI35: 15.510121 | AJ35: 6289442.9 | AK35: 1132271.3 | AL35: 2118711 | AM35: 82142.107 | AN35: 1412210.8 | AO35: 1103458.3 | AP35: 440649.28 | AQ35: 100 | AR35: 18.002729 | AS35: 33.686784 | AT35: 1.3060315 | AU35: 22.453671 | AV35: 17.544611 | AW35: 7.0061735
A36: Sep-Nov 1993 | B36: 8589339.6 | C36: 1442758 | D36: 2974061.1 | E36: 197455.91 | F36: 1938253.7 | G36: 163300.04 | H36: 1086966.1 | I36: 786544.69 | J36: 6298665.8 | K36: 2290673.8 | L36: 100 | M36: 16.797077 | N36: 34.625027 | O36: 2.2988486 | P36: 22.565806 | Q36: 1.9011943 | R36: 12.654828 | S36: 9.1572196 | T36: 73.3312 | U36: 26.6688 | V36: 2290673.8 | W36: 322701.07 | X36: 836079.93 | Y36: 124187.54 | Z36: 498599.43 | AA36: 163300.04 | AB36: 345805.75 | AC36: 100 | AD36: 14.087605 | AE36: 36.499302 | AF36: 5.4214416 | AG36: 21.766497 | AH36: 7.1289085 | AI36: 15.096246 | AJ36: 6298665.8 | AK36: 1120056.9 | AL36: 2137981.2 | AM36: 73268.374 | AN36: 1439654.3 | AO36: 1086966.1 | AP36: 440738.95 | AQ36: 100 | AR36: 17.782447 | AS36: 33.943398 | AT36: 1.1632364 | AU36: 22.856496 | AV36: 17.257085 | AW36: 6.9973381
A37: Oct-Dec 1993 | B37: 8585353.6 | C37: 1427616.3 | D37: 2990072.9 | E37: 207545.9 | F37: 1929738.3 | G37: 163644.32 | H37: 1086177.3 | I37: 780558.47 | J37: 6257681.3 | K37: 2327672.3 | L37: 100 | M37: 16.628509 | N37: 34.827604 | O37: 2.4174415 | P37: 22.477098 | Q37: 1.9060871 | R37: 12.651515 | S37: 9.0917452 | T37: 72.887869 | U37: 27.112131 | V37: 2327672.3 | W37: 329727.26 | X37: 851834.16 | Y37: 130188.95 | Z37: 512135.02 | AA37: 163644.32 | AB37: 340142.56 | AC37: 100 | AD37: 14.165536 | AE37: 36.595966 | AF37: 5.5930961 | AG37: 22.002024 | AH37: 7.0303848 | AI37: 14.612992 | AJ37: 6257681.3 | AK37: 1097889.1 | AL37: 2138238.8 | AM37: 77356.953 | AN37: 1417603.3 | AO37: 1086177.3 | AP37: 440415.91 | AQ37: 100 | AR37: 17.544663 | AS37: 34.169825 | AT37: 1.2361919 | AU37: 22.653811 | AV37: 17.357505 | AW37: 7.0380047
A38: Nov-Jan 1994 | B38: 8585252.1 | C38: 1421722.1 | D38: 2998779.5 | E38: 217125.12 | F38: 1925873.3 | G38: 161179.65 | H38: 1079535.1 | I38: 781037.34 | J38: 6258481.8 | K38: 2326770.4 | L38: 100 | M38: 16.560051 | N38: 34.929428 | O38: 2.5290477 | P38: 22.432344 | Q38: 1.8774014 | R38: 12.574297 | S38: 9.0974304 | T38: 72.898055 | U38: 27.101945 | V38: 2326770.4 | W38: 319191.92 | X38: 855899.91 | Y38: 138164.66 | Z38: 516528.38 | AA38: 161179.65 | AB38: 335805.84 | AC38: 100 | AD38: 13.718239 | AE38: 36.78489 | AF38: 5.9380444 | AG38: 22.199371 | AH38: 6.9271833 | AI38: 14.432273 | AJ38: 6258481.8 | AK38: 1102530.2 | AL38: 2142879.6 | AM38: 78960.468 | AN38: 1409344.9 | AO38: 1079535.1 | AP38: 445231.5 | AQ38: 100 | AR38: 17.616576 | AS38: 34.239607 | AT38: 1.2616553 | AU38: 22.518959 | AV38: 17.249154 | AW38: 7.1140496
A39: Dec-Feb 1994 | B39: 8586856.7 | C39: 1424344.4 | D39: 3003523.3 | E39: 220858 | F39: 1918251.3 | G39: 168968.6 | H39: 1089950.7 | I39: 760960.48 | J39: 6245867.9 | K39: 2340988.8 | L39: 100 | M39: 16.587494 | N39: 34.978146 | O39: 2.5720471 | P39: 22.339389 | Q39: 1.9677584 | R39: 12.693245 | S39: 8.8619213 | T39: 72.737535 | U39: 27.262465 | V39: 2340988.8 | W39: 327190.8 | X39: 853721.38 | Y39: 135831.22 | Z39: 534354.66 | AA39: 168968.6 | AB39: 320922.12 | AC39: 100 | AD39: 13.976607 | AE39: 36.46841 | AF39: 5.8023011 | AG39: 22.826024 | AH39: 7.2178303 | AI39: 13.708828 | AJ39: 6245867.9 | AK39: 1097153.6 | AL39: 2149801.9 | AM39: 85026.783 | AN39: 1383896.6 | AO39: 1089950.7 | AP39: 440038.36 | AQ39: 100 | AR39: 17.56607 | AS39: 34.419586 | AT39: 1.3613285 | AU39: 22.156995 | AV39: 17.450749 | AW39: 7.0452717
A40: Jan-Mar 1994 | B40: 8580490.6 | C40: 1435627.5 | D40: 2996842.8 | E40: 212466.49 | F40: 1911115.3 | G40: 169323.02 | H40: 1087224 | I40: 767891.47 | J40: 6272426.8 | K40: 2308063.8 | L40: 100 | M40: 16.731299 | N40: 34.92624 | O40: 2.4761578 | P40: 22.272798 | Q40: 1.973349 | R40: 12.670884 | S40: 8.9492723 | T40: 73.101027 | U40: 26.898973 | V40: 2308063.8 | W40: 313162.87 | X40: 850810.53 | Y40: 131975.31 | Z40: 520769.17 | AA40: 169323.02 | AB40: 322022.93 | AC40: 100 | AD40: 13.568206 | AE40: 36.862522 | AF40: 5.7180094 | AG40: 22.563032 | AH40: 7.33615 | AI40: 13.952081 | AJ40: 6272426.8 | AK40: 1122464.6 | AL40: 2146032.3 | AM40: 80491.178 | AN40: 1390346.2 | AO40: 1087224 | AP40: 445868.54 | AQ40: 100 | AR40: 17.895221 | AS40: 34.213747 | AT40: 1.2832542 | AU40: 22.166001 | AV40: 17.333387 | AW40: 7.1083897
A41: Feb-Apr 1994 | B41: 8586251.7 | C41: 1428352.2 | D41: 2995657.8 | E41: 207893.64 | F41: 1937922.3 | G41: 165422.91 | H41: 1083265.8 | I41: 767736.97 | J41: 6262400.7 | K41: 2323851 | L41: 100 | M41: 16.63534 | N41: 34.889005 | O41: 2.4212387 | P41: 22.570062 | Q41: 1.9266021 | R41: 12.616283 | S41: 8.9414684 | T41: 72.93521 | U41: 27.06479 | V41: 2323851 | W41: 322181.18 | X41: 839530.27 | Y41: 131772.23 | Z41: 541082.24 | AA41: 165422.91 | AB41: 323862.16 | AC41: 100 | AD41: 13.864107 | AE41: 36.126683 | AF41: 5.6704251 | AG41: 23.283861 | AH41: 7.1184817 | AI41: 13.936442 | AJ41: 6262400.7 | AK41: 1106171 | AL41: 2156127.5 | AM41: 76121.415 | AN41: 1396840.1 | AO41: 1083265.8 | AP41: 443874.82 | AQ41: 100 | AR41: 17.663689 | AS41: 34.429728 | AT41: 1.2155309 | AU41: 22.305186 | AV41: 17.297932 | AW41: 7.0879339
... A419: Aug-Oct 2025 | B419: 9098658.3 | C419: 2349638 | D419: 1585084.5 | E419: 189524.3 | F419: 2810366.6 | G419: 40985.795 | H419: 1042702.3 | I419: 1080356.8 | J419: 6967924 | K419: 2130734.3 | L419: 100 | M419: 25.824005 | N419: 17.421079 | O419: 2.0829917 | P419: 30.887704 | Q419: 0.45045976 | R419: 11.459956 | S419: 11.873804 | T419: 76.581885 | U419: 23.418115 | V419: 2130734.3 | W419: 519773.77 | X419: 392475.66 | Y419: 93116.24 | Z419: 738422.59 | AA419: 27848.593 | AB419: 359183.3 | AC419: 100 | AD419: 24.394115 | AE419: 18.419737 | AF419: 4.3701479 | AG419: 34.65578 | AH419: 1.3069951 | AI419: 16.857254 | AJ419: 6967924 | AK419: 1842757.6 | AL419: 1198766.4 | AM419: 97427.512 | AN419: 2087002.2 | AO419: 1013173.8 | AP419: 726756.11 | AQ419: 100 | AR419: 26.446293 | AS419: 17.204068 | AT419: 1.3982287 | AU419: 29.951564 | AV419: 14.54054 | AW419: 10.430023
A420: 3. Data from July to September 2022 onward has been reweighted, causing a step change discontinuity.
A421: 4. This series contains data that has not been modelled for periods from June to August 2011 to June to August 2022 to be consistent with other series within this table. It will therefore differ from figures published on tables A02SA and A05SA for those periods.
A423: Quality indicator
A424: Shaded estimates are based on a small sample size. This may result in less precise estimates, which should be used with caution.
A425: Unshaded estimates are based on a larger sample size. This is likely to result in estimates of higher precision, although they will still be subject to some sampling variability.
A426: * Estimate has been suppressed on disclosure grounds.

Sheet 13
B1: Whole Economy | E1: Private sector3 4 5 | H1: Public sector3 4 5 | K1: Services, SIC 2007 sections G-S | N1: Finance and business services, SIC 2007 sections K-N | Q1: Public sector excluding financial services 4 5 | T1: Manufacturing, SIC 2007 section C | W1: Construction, SIC 2007 section F | Z1: Wholesaling, retailing, hotels & restaurants, SIC 2007 sections G & I
B2: Weekly Earnings (£) | C2: % changes year on year | E2: Weekly Earnings (£) | F2: % changes year on year | H2: Weekly Earnings (£) | I2: % changes year on year | K2: Weekly Earnings (£) | L2: % changes year on year | N2: Weekly Earnings (£) | O2: % changes year on year | Q2: Weekly Earnings (£) | R2: % changes year on year | T2: Weekly Earnings (£) | U2: % changes year on year | W2: Weekly Earnings (£) | X2: % changes year on year | Z2: Weekly Earnings (£) | AA2: % changes year on year
C3: Single month | D3: 3 month average 2 | F3: Single month | G3: 3 month average 2 | I3: Single month | J3: 3 month average 2 | L3: Single month | M3: 3 month average 2 | O3: Single month | P3: 3 month average 2 | R3: Single month | S3: 3 month average 2 | U3: Single month | V3: 3 month average 2 | X3: Single month | Y3: 3 month average 2 | AA3: Single month | AB3: 3 month average 2
A4: Current (3mo avg) | B4: =(AVERAGE(OFFSET(INDEX(B$18:B$1048576,COUNTA(B$18:B$1048576)),-2,0,3,1))) -> 735.23513 | C4: {=INDEX(C$30:C$1048576,COUNTA(C$30:C$1048576))} -> 4.5603624 | D4: {=INDEX(D$32:D$1048576,COUNTA(D$32:D$1048576))} -> 4.7190575 | E4: =(AVERAGE(OFFSET(INDEX(E$18:E$1048576,COUNTA(E$18:E$1048576)),-2,0,3,1))) -> 737.79236 | F4: {=INDEX(F$30:F$1048576,COUNTA(F$30:F$1048576))} -> 3.7124992 | G4: {=INDEX(G$32:G$1048576,COUNTA(G$32:G$1048576))} -> 4.0045616 | H4: =(AVERAGE(OFFSET(INDEX(H$18:H$1048576,COUNTA(H$18:H$1048576)),-2,0,3,1))) -> 724.03101 | I4: {=INDEX(I$30:I$1048576,COUNTA(I$30:I$1048576))} -> 8.0156094 | J4: {=INDEX(J$32:J$1048576,COUNTA(J$32:J$1048576))} -> 7.7316879 | K4: =(AVERAGE(OFFSET(INDEX(K$18:K$1048576,COUNTA(K$18:K$1048576)),-2,0,3,1))) -> 723.20914 | L4: {=INDEX(L$30:L$1048576,COUNTA(L$30:L$1048576))} -> 4.5969049 | M4: {=INDEX(M$32:M$1048576,COUNTA(M$32:M$1048576))} -> 4.8320164 | N4: =(AVERAGE(OFFSET(INDEX(N$18:N$1048576,COUNTA(N$18:N$1048576)),-2,0,3,1))) -> 977.2453 | O4: {=INDEX(O$30:O$1048576,COUNTA(O$30:O$1048576))} -> 2.5574976 | P4: {=INDEX(P$32:P$1048576,COUNTA(P$32:P$1048576))} -> 2.7709084 | Q4: =(AVERAGE(OFFSET(INDEX(Q$18:Q$1048576,COUNTA(Q$18:Q$1048576)),-2,0,3,1))) -> 722.03231 | R4: {=INDEX(R$30:R$1048576,COUNTA(R$30:R$1048576))} -> 8.0606075 | S4: {=INDEX(S$32:S$1048576,COUNTA(S$32:S$1048576))} -> 8.1823042 | T4: =(AVERAGE(OFFSET(INDEX(T$18:T$1048576,COUNTA(T$18:T$1048576)),-2,0,3,1))) -> 802.86104 | U4: {=INDEX(U$30:U$1048576,COUNTA(U$30:U$1048576))} -> 4.1089957 | V4: {=INDEX(V$32:V$1048576,COUNTA(V$32:V$1048576))} -> 4.3707094 | W4: =(AVERAGE(OFFSET(INDEX(W$18:W$1048576,COUNTA(W$18:W$1048576)),-2,0,3,1))) -> 816.8283 | X4: {=INDEX(X$30:X$1048576,COUNTA(X$30:X$1048576))} -> 3.6111996 | Y4: {=INDEX(Y$32:Y$1048576,COUNTA(Y$32:Y$1048576))} -> 3.2041776 | Z4: =(AVERAGE(OFFSET(INDEX(Z$18:Z$1048576,COUNTA(Z$18:Z$1048576)),-2,0,3,1))) -> 494.14962 | AA4: {=INDEX(AA$30:AA$1048576,COUNTA(AA$30:AA$1048576))} -> 5.4289348 | AB4: {=INDEX(AB$32:AB$1048576,COUNTA(AB$32:AB$1048576))} -> 5.7680983
A5: Change on quarter | B5: =(AVERAGE(OFFSET(INDEX(B$18:B$1048576,COUNTA(B$18:B$1048576)),-2,0,3,1))-AVERAGE(OFFSET(INDEX(B$18:B$1048576,COUNTA(B$18:B$1048576)),-5,0,3,1)))*52 -> 523.61043 | C5: {=INDEX(C$30:C$1048576,COUNTA(C$30:C$1048576))-INDEX(C$30:C$1048576,COUNTA(C$30:C$1048576)-3)} -> -0.45788038 | D5: {=INDEX(D$32:D$1048576,COUNTA(D$32:D$1048576))-INDEX(D$32:D$1048576,COUNTA(D$32:D$1048576)-3)} -> -0.074487904 | E5: =(AVERAGE(OFFSET(INDEX(E$18:E$1048576,COUNTA(E$18:E$1048576)),-2,0,3,1))-AVERAGE(OFFSET(INDEX(E$18:E$1048576,COUNTA(E$18:E$1048576)),-5,0,3,1)))*52 -> 347.87552 | F5: {=INDEX(F$30:F$1048576,COUNTA(F$30:F$1048576))-INDEX(F$30:F$1048576,COUNTA(F$30:F$1048576)-3)} -> -1.2001635 | G5: {=INDEX(G$32:G$1048576,COUNTA(G$32:G$1048576))-INDEX(G$32:G$1048576,COUNTA(G$32:G$1048576)-3)} -> -0.69642495 | H5: =(AVERAGE(OFFSET(INDEX(H$18:H$1048576,COUNTA(H$18:H$1048576)),-2,0,3,1))-AVERAGE(OFFSET(INDEX(H$18:H$1048576,COUNTA(H$18:H$1048576)),-5,0,3,1)))*52 -> 1018.5119 | I5: {=INDEX(I$30:I$1048576,COUNTA(I$30:I$1048576))-INDEX(I$30:I$1048576,COUNTA(I$30:I$1048576)-3)} -> 2.7451135 | J5: {=INDEX(J$32:J$1048576,COUNTA(J$32:J$1048576))-INDEX(J$32:J$1048576,COUNTA(J$32:J$1048576)-3)} -> 2.590537 | K5: =(AVERAGE(OFFSET(INDEX(K$18:K$1048576,COUNTA(K$18:K$1048576)),-2,0,3,1))-AVERAGE(OFFSET(INDEX(K$18:K$1048576,COUNTA(K$18:K$1048576)),-5,0,3,1)))*52 -> 568.3851 | L5: {=INDEX(L$30:L$1048576,COUNTA(L$30:L$1048576))-INDEX(L$30:L$1048576,COUNTA(L$30:L$1048576)-3)} -> -0.51209553 | M5: {=INDEX(M$32:M$1048576,COUNTA(M$32:M$1048576))-INDEX(M$32:M$1048576,COUNTA(M$32:M$1048576)-3)} -> -0.020644788 | N5: =(AVERAGE(OFFSET(INDEX(N$18:N$1048576,COUNTA(N$18:N$1048576)),-2,0,3,1))-AVERAGE(OFFSET(INDEX(N$18:N$1048576,COUNTA(N$18:N$1048576)),-5,0,3,1)))*52 -> 500.85478 | O5: {=INDEX(O$30:O$1048576,COUNTA(O$30:O$1048576))-INDEX(O$30:O$1048576,COUNTA(O$30:O$1048576)-3)} -> -1.4900341 | P5: {=INDEX(P$32:P$1048576,COUNTA(P$32:P$1048576))-INDEX(P$32:P$1048576,COUNTA(P$32:P$1048576)-3)} -> 0.0015170546 | Q5: =(AVERAGE(OFFSET(INDEX(Q$18:Q$1048576,COUNTA(Q$18:Q$1048576)),-2,0,3,1))-AVERAGE(OFFSET(INDEX(Q$18:Q$1048576,COUNTA(Q$18:Q$1048576)),-5,0,3,1)))*52 -> 942.19565 | R5: {=INDEX(R$30:R$1048576,COUNTA(R$30:R$1048576))-INDEX(R$30:R$1048576,COUNTA(R$30:R$1048576)-3)} -> 2.3541607 | S5: {=INDEX(S$32:S$1048576,COUNTA(S$32:S$1048576))-INDEX(S$32:S$1048576,COUNTA(S$32:S$1048576)-3)} -> 2.1948313 | T5: =(AVERAGE(OFFSET(INDEX(T$18:T$1048576,COUNTA(T$18:T$1048576)),-2,0,3,1))-AVERAGE(OFFSET(INDEX(T$18:T$1048576,COUNTA(T$18:T$1048576)),-5,0,3,1)))*52 -> 268.41572 | U5: {=INDEX(U$30:U$1048576,COUNTA(U$30:U$1048576))-INDEX(U$30:U$1048576,COUNTA(U$30:U$1048576)-3)} -> -0.58782759 | V5: {=INDEX(V$32:V$1048576,COUNTA(V$32:V$1048576))-INDEX(V$32:V$1048576,COUNTA(V$32:V$1048576)-3)} -> -0.46041623 | W5: =(AVERAGE(OFFSET(INDEX(W$18:W$1048576,COUNTA(W$18:W$1048576)),-2,0,3,1))-AVERAGE(OFFSET(INDEX(W$18:W$1048576,COUNTA(W$18:W$1048576)),-5,0,3,1)))*52 -> 374.04525 | X5: {=INDEX(X$30:X$1048576,COUNTA(X$30:X$1048576))-INDEX(X$30:X$1048576,COUNTA(X$30:X$1048576)-3)} -> -0.94231783 | Y5: {=INDEX(Y$32:Y$1048576,COUNTA(Y$32:Y$1048576))-INDEX(Y$32:Y$1048576,COUNTA(Y$32:Y$1048576)-3)} -> -1.5090419 | Z5: =(AVERAGE(OFFSET(INDEX(Z$18:Z$1048576,COUNTA(Z$18:Z$1048576)),-2,0,3,1))-AVERAGE(OFFSET(INDEX(Z$18:Z$1048576,COUNTA(Z$18:Z$1048576)),-5,0,3,1)))*52 -> 447.92342 | AA5: {=INDEX(AA$30:AA$1048576,COUNTA(AA$30:AA$1048576))-INDEX(AA$30:AA$1048576,COUNTA(AA$30:AA$1048576)-3)} -> -0.28632331 | AB5: {=INDEX(AB$32:AB$1048576,COUNTA(AB$32:AB$1048576))-INDEX(AB$32:AB$1048576,COUNTA(AB$32:AB$1048576)-3)} -> -0.32879576
A6: Change year on year | B6: =(AVERAGE(OFFSET(INDEX(B$18:B$1048576,COUNTA(B$18:B$1048576)),-2,0,3,1))-AVERAGE(OFFSET(INDEX(B$18:B$1048576,COUNTA(B$18:B$1048576)),-14,0,3,1)))*52 -> 1722.8963 | C6: {=INDEX(C$30:C$1048576,COUNTA(C$30:C$1048576))-INDEX(C$30:C$1048576,COUNTA(C$30:C$1048576)-12)} -> -1.650328 | D6: {=INDEX(D$32:D$1048576,COUNTA(D$32:D$1048576))-INDEX(D$32:D$1048576,COUNTA(D$32:D$1048576)-12)} -> -0.64165637 | E6: =(AVERAGE(OFFSET(INDEX(E$18:E$1048576,COUNTA(E$18:E$1048576)),-2,0,3,1))-AVERAGE(OFFSET(INDEX(E$18:E$1048576,COUNTA(E$18:E$1048576)),-14,0,3,1)))*52 -> 1477.2027 | F6: {=INDEX(F$30:F$1048576,COUNTA(F$30:F$1048576))-INDEX(F$30:F$1048576,COUNTA(F$30:F$1048576)-12)} -> -3.2416074 | G6: {=INDEX(G$32:G$1048576,COUNTA(G$32:G$1048576))-INDEX(G$32:G$1048576,COUNTA(G$32:G$1048576)-12)} -> -1.6752254 | H6: =(AVERAGE(OFFSET(INDEX(H$18:H$1048576,COUNTA(H$18:H$1048576)),-2,0,3,1))-AVERAGE(OFFSET(INDEX(H$18:H$1048576,COUNTA(H$18:H$1048576)),-14,0,3,1)))*52 -> 2702.0374 | I6: {=INDEX(I$30:I$1048576,COUNTA(I$30:I$1048576))-INDEX(I$30:I$1048576,COUNTA(I$30:I$1048576)-12)} -> 3.6752614 | J6: {=INDEX(J$32:J$1048576,COUNTA(J$32:J$1048576))-INDEX(J$32:J$1048576,COUNTA(J$32:J$1048576)-12)} -> 3.72803 | K6: =(AVERAGE(OFFSET(INDEX(K$18:K$1048576,COUNTA(K$18:K$1048576)),-2,0,3,1))-AVERAGE(OFFSET(INDEX(K$18:K$1048576,COUNTA(K$18:K$1048576)),-14,0,3,1)))*52 -> 1733.4117 | L6: {=INDEX(L$30:L$1048576,COUNTA(L$30:L$1048576))-INDEX(L$30:L$1048576,COUNTA(L$30:L$1048576)-12)} -> -1.8200682 | M6: {=INDEX(M$32:M$1048576,COUNTA(M$32:M$1048576))-INDEX(M$32:M$1048576,COUNTA(M$32:M$1048576)-12)} -> -0.44321551 | N6: =(AVERAGE(OFFSET(INDEX(N$18:N$1048576,COUNTA(N$18:N$1048576)),-2,0,3,1))-AVERAGE(OFFSET(INDEX(N$18:N$1048576,COUNTA(N$18:N$1048576)),-14,0,3,1)))*52 -> 1370.1209 | O6: {=INDEX(O$30:O$1048576,COUNTA(O$30:O$1048576))-INDEX(O$30:O$1048576,COUNTA(O$30:O$1048576)-12)} -> -4.9806934 | P6: {=INDEX(P$32:P$1048576,COUNTA(P$32:P$1048576))-INDEX(P$32:P$1048576,COUNTA(P$32:P$1048576)-12)} -> -2.7025206 | Q6: =(AVERAGE(OFFSET(INDEX(Q$18:Q$1048576,COUNTA(Q$18:Q$1048576)),-2,0,3,1))-AVERAGE(OFFSET(INDEX(Q$18:Q$1048576,COUNTA(Q$18:Q$1048576)),-14,0,3,1)))*52 -> 2839.7452 | R6: {=INDEX(R$30:R$1048576,COUNTA(R$30:R$1048576))-INDEX(R$30:R$1048576,COUNTA(R$30:R$1048576)-12)} -> 3.3120819 | S6: {=INDEX(S$32:S$1048576,COUNTA(S$32:S$1048576))-INDEX(S$32:S$1048576,COUNTA(S$32:S$1048576)-12)} -> 4.0875618 | T6: =(AVERAGE(OFFSET(INDEX(T$18:T$1048576,COUNTA(T$18:T$1048576)),-2,0,3,1))-AVERAGE(OFFSET(INDEX(T$18:T$1048576,COUNTA(T$18:T$1048576)),-14,0,3,1)))*52 -> 1748.3043 | U6: {=INDEX(U$30:U$1048576,COUNTA(U$30:U$1048576))-INDEX(U$30:U$1048576,COUNTA(U$30:U$1048576)-12)} -> -2.1843353 | V6: {=INDEX(V$32:V$1048576,COUNTA(V$32:V$1048576))-INDEX(V$32:V$1048576,COUNTA(V$32:V$1048576)-12)} -> -1.7743534 | W6: =(AVERAGE(OFFSET(INDEX(W$18:W$1048576,COUNTA(W$18:W$1048576)),-2,0,3,1))-AVERAGE(OFFSET(INDEX(W$18:W$1048576,COUNTA(W$18:W$1048576)),-14,0,3,1)))*52 -> 1318.7225 | X6: {=INDEX(X$30:X$1048576,COUNTA(X$30:X$1048576))-INDEX(X$30:X$1048576,COUNTA(X$30:X$1048576)-12)} -> -4.0407877 | Y6: {=INDEX(Y$32:Y$1048576,COUNTA(Y$32:Y$1048576))-INDEX(Y$32:Y$1048576,COUNTA(Y$32:Y$1048576)-12)} -> -3.47834 | Z6: =(AVERAGE(OFFSET(INDEX(Z$18:Z$1048576,COUNTA(Z$18:Z$1048576)),-2,0,3,1))-AVERAGE(OFFSET(INDEX(Z$18:Z$1048576,COUNTA(Z$18:Z$1048576)),-14,0,3,1)))*52 -> 1401.3279 | AA6: {=INDEX(AA$30:AA$1048576,COUNTA(AA$30:AA$1048576))-INDEX(AA$30:AA$1048576,COUNTA(AA$30:AA$1048576)-12)} -> -0.19739904 | AB6: {=INDEX(AB$32:AB$1048576,COUNTA(AB$32:AB$1048576))-INDEX(AB$32:AB$1048576,COUNTA(AB$32:AB$1048576)-12)} -> -0.24612376
A7: Change since Covid-19 | B7: =(AVERAGE(OFFSET(INDEX(B$18:B$1048576,COUNTA(B$18:B$1048576)),-2,0,3,1))-AVERAGE($B$257:$B$259))*52 -> 9895.5919 | C7: {=INDEX(C$30:C$1048576,COUNTA(C$30:C$1048576))-AVERAGE($C$257:$C$259)} -> 1.7193657 | D7: {=INDEX(D$32:D$1048576,COUNTA(D$32:D$1048576))-AVERAGE($D$257:$D$259)} -> 1.8705081 | E7: =(AVERAGE(OFFSET(INDEX(E$18:E$1048576,COUNTA(E$18:E$1048576)),-2,0,3,1))-AVERAGE($B$257:$B$259))*52 -> 10028.568 | F7: {=INDEX(F$30:F$1048576,COUNTA(F$30:F$1048576))-AVERAGE($C$257:$C$259)} -> 0.87150246 | G7: {=INDEX(G$32:G$1048576,COUNTA(G$32:G$1048576))-AVERAGE($D$257:$D$259)} -> 1.1560121 | H7: =(AVERAGE(OFFSET(INDEX(H$18:H$1048576,COUNTA(H$18:H$1048576)),-2,0,3,1))-AVERAGE($B$257:$B$259))*52 -> 9312.9775 | I7: {=INDEX(I$30:I$1048576,COUNTA(I$30:I$1048576))-AVERAGE($C$257:$C$259)} -> 5.1746127 | J7: {=INDEX(J$32:J$1048576,COUNTA(J$32:J$1048576))-AVERAGE($D$257:$D$259)} -> 4.8831385 | K7: =(AVERAGE(OFFSET(INDEX(K$18:K$1048576,COUNTA(K$18:K$1048576)),-2,0,3,1))-AVERAGE($B$257:$B$259))*52 -> 9270.2404 | L7: {=INDEX(L$30:L$1048576,COUNTA(L$30:L$1048576))-AVERAGE($C$257:$C$259)} -> 1.7559082 | M7: {=INDEX(M$32:M$1048576,COUNTA(M$32:M$1048576))-AVERAGE($D$257:$D$259)} -> 1.983467 | N7: =(AVERAGE(OFFSET(INDEX(N$18:N$1048576,COUNTA(N$18:N$1048576)),-2,0,3,1))-AVERAGE($B$257:$B$259))*52 -> 22480.121 | O7: {=INDEX(O$30:O$1048576,COUNTA(O$30:O$1048576))-AVERAGE($C$257:$C$259)} -> -0.28349913 | P7: {=INDEX(P$32:P$1048576,COUNTA(P$32:P$1048576))-AVERAGE($D$257:$D$259)} -> -0.077641084 | Q7: =(AVERAGE(OFFSET(INDEX(Q$18:Q$1048576,COUNTA(Q$18:Q$1048576)),-2,0,3,1))-AVERAGE($B$257:$B$259))*52 -> 9209.0455 | R7: {=INDEX(R$30:R$1048576,COUNTA(R$30:R$1048576))-AVERAGE($C$257:$C$259)} -> 5.2196108 | S7: {=INDEX(S$32:S$1048576,COUNTA(S$32:S$1048576))-AVERAGE($D$257:$D$259)} -> 5.3337547 | T7: =(AVERAGE(OFFSET(INDEX(T$18:T$1048576,COUNTA(T$18:T$1048576)),-2,0,3,1))-AVERAGE($B$257:$B$259))*52 -> 13412.139 | U7: {=INDEX(U$30:U$1048576,COUNTA(U$30:U$1048576))-AVERAGE($C$257:$C$259)} -> 1.267999 | V7: {=INDEX(V$32:V$1048576,COUNTA(V$32:V$1048576))-AVERAGE($D$257:$D$259)} -> 1.5221599 | W7: =(AVERAGE(OFFSET(INDEX(W$18:W$1048576,COUNTA(W$18:W$1048576)),-2,0,3,1))-AVERAGE($B$257:$B$259))*52 -> 14138.437 | X7: {=INDEX(X$30:X$1048576,COUNTA(X$30:X$1048576))-AVERAGE($C$257:$C$259)} -> 0.77020293 | Y7: {=INDEX(Y$32:Y$1048576,COUNTA(Y$32:Y$1048576))-AVERAGE($D$257:$D$259)} -> 0.35562811 | Z7: =(AVERAGE(OFFSET(INDEX(Z$18:Z$1048576,COUNTA(Z$18:Z$1048576)),-2,0,3,1))-AVERAGE($B$257:$B$259))*52 -> -2640.8546 | AA7: {=INDEX(AA$30:AA$1048576,COUNTA(AA$30:AA$1048576))-AVERAGE($C$257:$C$259)} -> 2.5879381 | AB7: {=INDEX(AB$32:AB$1048576,COUNTA(AB$32:AB$1048576))-AVERAGE($D$257:$D$259)} -> 2.9195488
A9: Table 13: Average Weekly Earnings (nominal) - Total Pay (Great Britain, seasonally adjusted)1 | M9: Source: Monthly Wages & Salaries Survey
A10: Date of publication: | E10: 45643 | H10: Date of next publication: | L10: 45678
A11: Inquiries: Email: | C11: labour.market@ons.gov.uk | J11: Tel: 01633 455400
A12: Standard Industrial Classification (2007)
B13: Whole Economy | E13: Private sector3 4 5 | H13: Public sector3 4 5 | K13: Services, SIC 2007 sections G-S | N13: Finance and business services, SIC 2007 sections K-N | Q13: Public sector excluding financial services 4 5 | T13: Manufacturing, SIC 2007 section C | W13: Construction, SIC 2007 section F | Z13: Wholesaling, retailing, hotels & restaurants, SIC 2007 sections G & I
B14: Weekly Earnings (£) | C14: % changes year on year | E14: Weekly Earnings (£) | F14: % changes year on year | H14: Weekly Earnings (£) | I14: % changes year on year | K14: Weekly Earnings (£) | L14: % changes year on year | N14: Weekly Earnings (£) | O14: % changes year on year | Q14: Weekly Earnings (£) | R14: % changes year on year | T14: Weekly Earnings (£) | U14: % changes year on year | W14: Weekly Earnings (£) | X14: % changes year on year | Z14: Weekly Earnings (£) | AA14: % changes year on year
C15: Single month | D15: 3 month average 2 | F15: Single month | G15: 3 month average 2 | I15: Single month | J15: 3 month average 2 | L15: Single month | M15: 3 month average 2 | O15: Single month | P15: 3 month average 2 | R15: Single month | S15: 3 month average 2 | U15: Single month | V15: 3 month average 2 | X15: Single month | Y15: 3 month average 2 | AA15: Single month | AB15: 3 month average 2
B16: KAB9 | C16: KAC2 | D16: KAC3 | E16: KAC4 | F16: KAC5 | G16: KAC6 | H16: KAC7 | I16: KAC8 | J16: KAC9 | K16: K5BZ | L16: K5C2 | M16: K5C3 | N16: K5C4 | O16: K5C5 | P16: K5C6 | Q16: KAD8 | R16: KAD9 | S16: KAE2 | T16: K5CA | U16: K5CB | V16: K5CC | W16: K5CD | X16: K5CE | Y16: K5CF | Z16: K5CG | AA16: K5CH | AB16: K5CI
A18: 36526 | B18: 304.72293 | E18: 304.95015 | H18: 313.29054 | K18: 290.1503 | N18: 358.45319 | Q18: 312.8577 | T18: 362.9179 | W18: 356.44273 | Z18: 208.69443
A19: 36557 | B19: 299.81858 | E19: 296.22775 | H19: 314.92407 | K19: 283.09674 | N19: 339.63872 | Q19: 314.49888 | T19: 356.06462 | W19: 362.71112 | Z19: 209.18651
A20: 36586 | B20: 311.41872 | E20: 308.88204 | H20: 312.30939 | K20: 296.13452 | N20: 384.19807 | Q20: 311.57617 | T20: 357.5738 | W20: 358.22823 | Z20: 207.99583
A21: 36617 | B21: 308.74876 | E21: 308.67604 | H21: 309.39488 | K21: 291.03444 | N21: 373.26554 | Q21: 310.23049 | T21: 365.81605 | W21: 360.13142 | Z21: 209.35112
A22: 36647 | B22: 311.17877 | E22: 311.35841 | H22: 309.9174 | K22: 295.84062 | N22: 380.36826 | Q22: 310.61169 | T22: 362.06068 | W22: 363.8028 | Z22: 211.40595
A23: 36678 | B23: 310.50014 | E23: 309.11833 | H23: 312.12478 | K23: 295.04085 | N23: 378.67914 | Q23: 312.24515 | T23: 361.60258 | W23: 367.83133 | Z23: 210.72793
A24: 36708 | B24: 313.05003 | E24: 313.17445 | H24: 312.12664 | K24: 298.15893 | N24: 381.72333 | Q24: 312.94115 | T24: 362.66381 | W24: 368.57406 | Z24: 211.39313
A25: 36739 | B25: 314.65479 | E25: 314.80315 | H25: 311.83305 | K25: 300.14559 | N25: 384.80206 | Q25: 312.77928 | T25: 362.6818 | W25: 372.7553 | Z25: 213.18152
A26: 36770 | B26: 316.80591 | E26: 316.94686 | H26: 314.49744 | K26: 301.98707 | N26: 389.08515 | Q26: 314.25035 | T26: 364.99869 | W26: 373.97265 | Z26: 214.2324
A27: 36800 | B27: 317.60096 | E27: 317.58941 | H27: 315.75776 | K27: 302.26231 | N27: 388.74465 | Q27: 315.50773 | T27: 366.51557 | W27: 379.6952 | Z27: 215.66587
A28: 36831 | B28: 319.53141 | E28: 319.45682 | H28: 318.03708 | K28: 304.06317 | N28: 391.71038 | Q28: 317.73481 | T28: 369.11936 | W28: 381.7144 | Z28: 217.13349
A29: 36861 | B29: 323.33491 | E29: 325.6304 | H29: 314.97341 | K29: 309.70497 | N29: 414.64635 | Q29: 316.18937 | T29: 369.40701 | W29: 391.93979 | Z29: 217.05391
A30: 36892 | B30: 321.29767 | C30: 5.4392826 | E30: 323.52593 | F30: 6.091415 | H30: 321.94016 | I30: 2.7608929 | K30: 308.49545 | L30: 6.3226371 | N30: 406.89465 | O30: 13.514026 | Q30: 321.58271 | R30: 2.788811 | T30: 371.96331 | U30: 2.4924125 | W30: 386.99856 | X30: 8.5724379 | Z30: 215.30329 | AA30: 3.1667644
A31: 36923 | B31: 324.81959 | C31: 8.3387125 | E31: 324.60423 | F31: 9.5792766 | H31: 323.3905 | I31: 2.6884049 | K31: 310.05362 | L31: 9.5221437 | N31: 411.31514 | O31: 21.103726 | Q31: 323.07626 | R31: 2.7273157 | T31: 373.08328 | U31: 4.7796524 | W31: 381.90656 | X31: 5.2922117 | Z31: 217.31741 | AA31: 3.8869144
A32: 36951 | B32: 326.11025 | C32: 4.7176162 | D32: 6.142984 | E32: 323.74401 | F32: 4.811535 | G32: 6.7923243 | H32: 325.04556 | I32: 4.0780628 | J32: 3.1739991 | K32: 310.53777 | L32: 4.8637546 | M32: 6.8675583 | N32: 406.51465 | O32: 5.8086117 | P32: 13.160471 | Q32: 324.48045 | R32: 4.1416151 | S32: 3.2171285 | T32: 373.96437 | U32: 4.5838273 | V32: 3.9435585 | W32: 384.40801 | X32: 7.3081282 | Y32: 7.0477365 | Z32: 222.07081 | AA32: 6.766952 | AB32: 4.6038999
A33: 36982 | B33: 326.48489 | C33: 5.744519 | D33: 6.2423425 | E33: 326.44047 | F33: 5.7550392 | G33: 6.6758389 | H33: 327.43239 | I33: 5.8299304 | J33: 4.1895074 | K33: 311.6314 | L33: 7.0771579 | M33: 7.1193317 | N33: 404.624 | O33: 8.4011139 | P33: 11.425685 | Q33: 327.75371 | R33: 5.6484538 | S33: 4.1658291 | T33: 371.55363 | U33: 1.568433 | V33: 3.6265352 | W33: 390.59637 | X33: 8.4594001 | Y33: 7.0152832 | Z33: 219.37003 | AA33: 4.7856975 | AB33: 5.143347
A34: 37012 | B34: 326.62204 | C34: 4.9628276 | D34: 5.139972 | E34: 325.93097 | F34: 4.6803157 | G34: 5.0810758 | H34: 328.57247 | I34: 6.0193665 | J34: 5.305667 | K34: 311.55225 | L34: 5.3108425 | M34: 5.7430694 | N34: 398.74745 | O34: 4.8319453 | P34: 6.3325897 | Q34: 329.05052 | R34: 5.9362947 | S34: 5.2408167 | T34: 374.81319 | U34: 3.522201 | V34: 3.2134721 | W34: 395.89045 | X34: 8.820066 | Y34: 8.1995437 | Z34: 218.9694 | AA34: 3.5776909 | AB34: 5.0349415
A35: 37043 | B35: 328.43303 | C35: 5.7754855 | D35: 5.4934187 | E35: 327.41186 | F35: 5.9179688 | G35: 5.4491049 | H35: 329.45971 | I35: 5.5538459 | J35: 5.8004455 | K35: 313.60163 | L35: 6.2909163 | M35: 6.2216101 | N35: 411.73697 | O35: 8.7297739 | P35: 7.3120671 | Q35: 329.21897 | R35: 5.4360555 | S35: 5.6731957 | T35: 376.10049 | U35: 4.0093486 | V35: 3.0278678 | W35: 401.25649 | X35: 9.0870899 | Y35: 8.7910604 | Z35: 219.46192 | AA35: 4.1446757 | AB35: 4.1673756
A36: 37073 | B36: 328.38409 | C36: 4.8982792 | D36: 5.21116 | E36: 327.67349 | F36: 4.6297026 | G36: 5.0731075 | H36: 330.90903 | I36: 6.0175562 | J36: 5.8632217 | K36: 312.96918 | L36: 4.9672335 | M36: 5.5208574 | N36: 401.88654 | O36: 5.2821527 | P36: 6.2764784 | Q36: 331.33326 | R36: 5.8771791 | S36: 5.7496123 | T36: 376.33343 | U36: 3.7692272 | V36: 3.7668247 | W36: 404.10152 | X36: 9.6391669 | Y36: 9.1837418 | Z36: 221.00565 | AA36: 4.547226 | AB36: 4.0897963
A37: 37104 | B37: 330.71663 | C37: 5.104591 | D37: 5.2577845 | E37: 329.66133 | F37: 4.7198331 | G37: 5.0849389 | H37: 332.75894 | I37: 6.7106078 | J37: 6.093811 | K37: 315.09485 | L37: 4.9806711 | M37: 5.4089146 | N37: 406.50369 | O37: 5.6396858 | P37: 6.5422959 | Q37: 333.28099 | R37: 6.5546874 | S37: 5.9562565 | T37: 378.76049 | U37: 4.4332776 | V37: 4.0706836 | W37: 407.36834 | X37: 9.2857264 | Y37: 9.3373008 | Z37: 223.49686 | AA37: 4.8387578 | AB37: 4.5115274
A38: 37135 | B38: 331.09426 | C38: 4.5101294 | D38: 4.8368176 | E38: 330.00633 | F38: 4.120397 | G38: 4.4888983 | H38: 333.59618 | I38: 6.0727814 | J38: 6.2663524 | K38: 315.36763 | L38: 4.4308385 | M38: 4.7917891 | N38: 404.80806 | O38: 4.0409944 | P38: 4.9833178 | Q38: 333.15876 | R38: 6.0169873 | S38: 6.1493635 | T38: 379.80975 | U38: 4.0578385 | V38: 4.0867248 | W38: 405.76916 | X38: 8.5023642 | Y38: 9.1398583 | Z38: 222.19555 | AA38: 3.7170613 | AB38: 4.3661087
A39: 37165 | B39: 332.68494 | C39: 4.749351 | D39: 4.7872739 | E39: 331.62566 | F39: 4.4196228 | G39: 4.4192736 | H39: 334.82368 | I39: 6.0381465 | J39: 6.2722947 | K39: 316.8435 | L39: 4.8240193 | M39: 4.7447208 | N39: 404.52945 | O39: 4.0604542 | P39: 4.576628 | Q39: 334.3891 | R39: 5.9844395 | S39: 6.184527 | T39: 381.784 | U39: 4.1658319 | V39: 4.2184552 | W39: 408.89436 | X39: 7.6901565 | Y39: 8.4878146 | Z39: 221.41991 | AA39: 2.6680374 | AB39: 3.7370997
A40: 37196 | B40: 333.72305 | C40: 4.4413897 | D40: 4.5667499 | E40: 333.08021 | F40: 4.264548 | G40: 4.2682817 | H40: 334.24577 | I40: 5.096477 | J40: 5.7338171 | K40: 318.1902 | L40: 4.6460857 | M40: 4.633734 | N40: 409.35436 | O40: 4.5043444 | P40: 4.202651 | Q40: 333.85309 | R40: 5.072872 | S40: 5.689547 | T40: 382.75285 | U40: 3.6935167 | V40: 3.9716182 | W40: 408.18421 | X40: 6.9344534 | Y40: 7.7036151 | Z40: 223.88257 | AA40: 3.1082634 | AB40: 3.1631023
A41: 37226 | B41: 334.13697 | C41: 3.3408284 | D41: 4.1727277 | E41: 334.64916 | F41: 2.769628 | G41: 3.810043 | H41: 332.0935 | I41: 5.4354075 | J41: 5.5223908 | K41: 319.98793 | L41: 3.3202439 | M41: 4.2565384 | N41: 414.85805 | O41: 0.051056135 | P41: 2.8148646 | Q41: 333.06576 | R41: 5.3374299 | S41: 5.4639027 | T41: 382.74207 | U41: 3.609856 | V41: 3.822205 | W41: 406.99948 | X41: 3.842347 | Y41: 6.1324564 | Z41: 223.01081 | AA41: 2.7444318 | AB41: 2.8406449
A42: 37257 | B42: 332.54658 | C42: 3.501089 | D42: 3.7589681 | E42: 334.6472 | F42: 3.4375192 | G42: 3.4857472 | H42: 336.99262 | I42: 4.6755468 | J42: 5.06636 | K42: 320.98569 | L42: 4.0487617 | M42: 4.0010515 | N42: 412.98015 | O42: 1.4955964 | P42: 1.9733081 | Q42: 336.61885 | R42: 4.6756686 | S42: 5.0267359 | T42: 383.74298 | U42: 3.1668904 | V42: 3.489291 | W42: 396.76383 | X42: 2.5233352 | Y42: 4.4194756 | Z42: 223.31386 | AA42: 3.7205978 | AB42: 3.1896603
A43: 37288 | B43: 334.07361 | C43: 2.848973 | D43: 3.2291438 | E43: 333.07528 | F43: 2.6096566 | G43: 2.9382041 | H43: 337.77562 | I43: 4.4482199 | J43: 4.8482218 | K43: 319.03349 | L43: 2.896231 | M43: 3.4207312 | N43: 409.04639 | O43: -0.55158509 | P43: 0.32675759 | Q43: 337.06893 | R43: 4.3310716 | S43: 4.7775689 | T43: 384.84442 | U43: 3.1524179 | V43: 3.3088749 | W43: 408.81644 | X43: 7.0461947 | Y43: 4.4566537 | Z43: 223.89347 | AA43: 3.0260153 | AB43: 3.1621251
... A327: 45931 | B327: 738.54076 | C327: 4.5603624 | D327: 4.7190575 | E327: 740.31586 | F327: 3.7124992 | G327: 4.0045616 | H327: 729.85252 | I327: 8.0156094 | J327: 7.7316879 | K327: 726.93427 | L327: 4.5969049 | M327: 4.8320164 | N327: 981.67066 | O327: 2.5574976 | P327: 2.7709084 | Q327: 726.84531 | R327: 8.0606075 | S327: 8.1823042 | T327: 804.41453 | U327: 4.1089957 | V327: 4.3707094 | W327: 826.06383 | X327: 3.6111996 | Y327: 3.2041776 | Z327: 493.61992 | AA327: 5.4289348 | AB327: 5.7680983
A328: 3. From July 2009 Royal Bank of Scotland Group plc is classified to the public sector; for earlier time periods it is classified to the private sector. Between July 2009 and March 2014 Lloyds Banking Group plc is classified to the public sector; it is classified to the private sector for earlier and later time periods.
A329: 4. Between June 2010 and May 2012 English Further Education Corporations and Sixth Form College Corporations are classified to the public sector. Before June 2010 and after May 2012 they are classified to the private sector.
A330: 5. From October 2013 Royal Mail plc is classified to the private sector; previously it is in the public sector.

Sheet 15
B1: Whole Economy | E1: Private sector 3 4 5 | H1: Public sector 3 4 5 | K1: Services, SIC 2007 sections G-S | N1: Finance and business services, SIC 2007 sections K-N | Q1: Public sector excluding financial services 4 5 | T1: Manufacturing, SIC 2007 section C | W1: Construction, SIC 2007 section F | Z1: Wholesaling, retailing, hotels & restaurants, SIC 2007 sections G & I
B2: Weekly Earnings (£) | C2: % changes year on year | E2: Weekly Earnings (£) | F2: % changes year on year | H2: Weekly Earnings (£) | I2: % changes year on year | K2: Weekly Earnings (£) | L2: % changes year on year | N2: Weekly Earnings (£) | O2: % changes year on year | Q2: Weekly Earnings (£) | R2: % changes year on year | T2: Weekly Earnings (£) | U2: % changes year on year | W2: Weekly Earnings (£) | X2: % changes year on year | Z2: Weekly Earnings (£) | AA2: % changes year on year
C3: Single month | D3: 3 month average 2 | F3: Single month | G3: 3 month average 2 | I3: Single month | J3: 3 month average 2 | L3: Single month | M3: 3 month average 2 | O3: Single month | P3: 3 month average 2 | R3: Single month | S3: 3 month average 2 | U3: Single month | V3: 3 month average 2 | X3: Single month | Y3: 3 month average 2 | AA3: Single month | AB3: 3 month average 2
A4: Current | B4: {=INDEX(B$19:B$1048576,COUNTA(B$19:B$1048576))} -> 687.43684 | C4: {=INDEX(C$31:C$1048576,COUNTA(C$31:C$1048576))} -> 4.4424634 | D4: {=INDEX(D$33:D$1048576,COUNTA(D$33:D$1048576))} -> 4.600438 | E4: {=INDEX(E$19:E$1048576,COUNTA(E$19:E$1048576))} -> 678.97169 | F4: {=INDEX(F$31:F$1048576,COUNTA(F$31:F$1048576))} -> 3.4792427 | G4: {=INDEX(G$33:G$1048576,COUNTA(G$33:G$1048576))} -> 3.8650393 | H4: {=INDEX(H$19:H$1048576,COUNTA(H$19:H$1048576))} -> 726.0603 | I4: {=INDEX(I$31:I$1048576,COUNTA(I$31:I$1048576))} -> 8.4806104 | J4: {=INDEX(J$33:J$1048576,COUNTA(J$33:J$1048576))} -> 7.6338764 | K4: {=INDEX(K$19:K$1048576,COUNTA(K$19:K$1048576))} -> 674.38606 | L4: {=INDEX(L$31:L$1048576,COUNTA(L$31:L$1048576))} -> 4.5585559 | M4: {=INDEX(M$33:M$1048576,COUNTA(M$33:M$1048576))} -> 4.6927585 | N4: {=INDEX(N$19:N$1048576,COUNTA(N$19:N$1048576))} -> 859.74478 | O4: {=INDEX(O$31:O$1048576,COUNTA(O$31:O$1048576))} -> 1.6474172 | P4: {=INDEX(P$33:P$1048576,COUNTA(P$33:P$1048576))} -> 2.2981009 | Q4: {=INDEX(Q$19:Q$1048576,COUNTA(Q$19:Q$1048576))} -> 726.08473 | R4: {=INDEX(R$31:R$1048576,COUNTA(R$31:R$1048576))} -> 8.4866098 | S4: {=INDEX(S$33:S$1048576,COUNTA(S$33:S$1048576))} -> 8.0017971 | T4: {=INDEX(T$19:T$1048576,COUNTA(T$19:T$1048576))} -> 768.89081 | U4: {=INDEX(U$31:U$1048576,COUNTA(U$31:U$1048576))} -> 4.6189131 | V4: {=INDEX(V$33:V$1048576,COUNTA(V$33:V$1048576))} -> 4.4606137 | W4: {=INDEX(W$19:W$1048576,COUNTA(W$19:W$1048576))} -> 769.40742 | X4: {=INDEX(X$31:X$1048576,COUNTA(X$31:X$1048576))} -> 1.966623 | Y4: {=INDEX(Y$33:Y$1048576,COUNTA(Y$33:Y$1048576))} -> 2.9074512 | Z4: {=INDEX(Z$19:Z$1048576,COUNTA(Z$19:Z$1048576))} -> 465.39075 | AA4: {=INDEX(AA$31:AA$1048576,COUNTA(AA$31:AA$1048576))} -> 5.343712 | AB4: {=INDEX(AB$33:AB$1048576,COUNTA(AB$33:AB$1048576))} -> 5.5335217
A5: Quarterly change | B5: {=INDEX(B$19:B$1048576,COUNTA(B$19:B$1048576))-INDEX(B$19:B$1048576,COUNTA(B$19:B$1048576)-3)} -> 7.0513798 | C5: {=INDEX(C$31:C$1048576,COUNTA(C$31:C$1048576))-INDEX(C$31:C$1048576,COUNTA(C$31:C$1048576)-3)} -> -0.2418519 | D5: {=INDEX(D$33:D$1048576,COUNTA(D$33:D$1048576))-INDEX(D$33:D$1048576,COUNTA(D$33:D$1048576)-3)} -> -0.23518646 | E5: {=INDEX(E$19:E$1048576,COUNTA(E$19:E$1048576))-INDEX(E$19:E$1048576,COUNTA(E$19:E$1048576)-3)} -> 5.1044585 | F5: {=INDEX(F$31:F$1048576,COUNTA(F$31:F$1048576))-INDEX(F$31:F$1048576,COUNTA(F$31:F$1048576)-3)} -> -1.0266526 | G5: {=INDEX(G$33:G$1048576,COUNTA(G$33:G$1048576))-INDEX(G$33:G$1048576,COUNTA(G$33:G$1048576)-3)} -> -0.7906507 | H5: {=INDEX(H$19:H$1048576,COUNTA(H$19:H$1048576))-INDEX(H$19:H$1048576,COUNTA(H$19:H$1048576)-3)} -> 22.551721 | I5: {=INDEX(I$31:I$1048576,COUNTA(I$31:I$1048576))-INDEX(I$31:I$1048576,COUNTA(I$31:I$1048576)-3)} -> 3.0629663 | J5: {=INDEX(J$33:J$1048576,COUNTA(J$33:J$1048576))-INDEX(J$33:J$1048576,COUNTA(J$33:J$1048576)-3)} -> 2.0433046 | K5: {=INDEX(K$19:K$1048576,COUNTA(K$19:K$1048576))-INDEX(K$19:K$1048576,COUNTA(K$19:K$1048576)-3)} -> 7.6383889 | L5: {=INDEX(L$31:L$1048576,COUNTA(L$31:L$1048576))-INDEX(L$31:L$1048576,COUNTA(L$31:L$1048576)-3)} -> -0.17815924 | M5: {=INDEX(M$33:M$1048576,COUNTA(M$33:M$1048576))-INDEX(M$33:M$1048576,COUNTA(M$33:M$1048576)-3)} -> -0.22001039 | N5: {=INDEX(N$19:N$1048576,COUNTA(N$19:N$1048576))-INDEX(N$19:N$1048576,COUNTA(N$19:N$1048576)-3)} -> 4.651248 | O5: {=INDEX(O$31:O$1048576,COUNTA(O$31:O$1048576))-INDEX(O$31:O$1048576,COUNTA(O$31:O$1048576)-3)} -> -1.5940461 | P5: {=INDEX(P$33:P$1048576,COUNTA(P$33:P$1048576))-INDEX(P$33:P$1048576,COUNTA(P$33:P$1048576)-3)} -> -0.7008588 | Q5: {=INDEX(Q$19:Q$1048576,COUNTA(Q$19:Q$1048576))-INDEX(Q$19:Q$1048576,COUNTA(Q$19:Q$1048576)-3)} -> 23.761164 | R5: {=INDEX(R$31:R$1048576,COUNTA(R$31:R$1048576))-INDEX(R$31:R$1048576,COUNTA(R$31:R$1048576)-3)} -> 2.6052091 | S5: {=INDEX(S$33:S$1048576,COUNTA(S$33:S$1048576))-INDEX(S$33:S$1048576,COUNTA(S$33:S$1048576)-3)} -> 1.9845036 | T5: {=INDEX(T$19:T$1048576,COUNTA(T$19:T$1048576))-INDEX(T$19:T$1048576,COUNTA(T$19:T$1048576)-3)} -> 7.3921297 | U5: {=INDEX(U$31:U$1048576,COUNTA(U$31:U$1048576))-INDEX(U$31:U$1048576,COUNTA(U$31:U$1048576)-3)} -> 0.20269406 | V5: {=INDEX(V$33:V$1048576,COUNTA(V$33:V$1048576))-INDEX(V$33:V$1048576,COUNTA(V$33:V$1048576)-3)} -> -0.052818956 | W5: {=INDEX(W$19:W$1048576,COUNTA(W$19:W$1048576))-INDEX(W$19:W$1048576,COUNTA(W$19:W$1048576)-3)} -> 4.6402901 | X5: {=INDEX(X$31:X$1048576,COUNTA(X$31:X$1048576))-INDEX(X$31:X$1048576,COUNTA(X$31:X$1048576)-3)} -> -1.6926138 | Y5: {=INDEX(Y$33:Y$1048576,COUNTA(Y$33:Y$1048576))-INDEX(Y$33:Y$1048576,COUNTA(Y$33:Y$1048576)-3)} -> -0.93232907 | Z5: {=INDEX(Z$19:Z$1048576,COUNTA(Z$19:Z$1048576))-INDEX(Z$19:Z$1048576,COUNTA(Z$19:Z$1048576)-3)} -> 5.4246822 | AA5: {=INDEX(AA$31:AA$1048576,COUNTA(AA$31:AA$1048576))-INDEX(AA$31:AA$1048576,COUNTA(AA$31:AA$1048576)-3)} -> -0.50634901 | AB5: {=INDEX(AB$33:AB$1048576,COUNTA(AB$33:AB$1048576))-INDEX(AB$33:AB$1048576,COUNTA(AB$33:AB$1048576)-3)} -> -0.94810862
A6: year on year change | B6: {=INDEX(B$19:B$1048576,COUNTA(B$19:B$1048576))-INDEX(B$19:B$1048576,COUNTA(B$19:B$1048576)-12)} -> 29.240147 | C6: {=INDEX(C$31:C$1048576,COUNTA(C$31:C$1048576))-INDEX(C$31:C$1048576,COUNTA(C$31:C$1048576)-12)} -> -1.719612 | D6: {=INDEX(D$33:D$1048576,COUNTA(D$33:D$1048576))-INDEX(D$33:D$1048576,COUNTA(D$33:D$1048576)-12)} -> -0.82146274 | E6: {=INDEX(E$19:E$1048576,COUNTA(E$19:E$1048576))-INDEX(E$19:E$1048576,COUNTA(E$19:E$1048576)-12)} -> 22.828803 | F6: {=INDEX(F$31:F$1048576,COUNTA(F$31:F$1048576))-INDEX(F$31:F$1048576,COUNTA(F$31:F$1048576)-12)} -> -3.2006913 | G6: {=INDEX(G$33:G$1048576,COUNTA(G$33:G$1048576))-INDEX(G$33:G$1048576,COUNTA(G$33:G$1048576)-12)} -> -1.8071368 | H6: {=INDEX(H$19:H$1048576,COUNTA(H$19:H$1048576))-INDEX(H$19:H$1048576,COUNTA(H$19:H$1048576)-12)} -> 56.760692 | I6: {=INDEX(I$31:I$1048576,COUNTA(I$31:I$1048576))-INDEX(I$31:I$1048576,COUNTA(I$31:I$1048576)-12)} -> 4.5961867 | J6: {=INDEX(J$33:J$1048576,COUNTA(J$33:J$1048576))-INDEX(J$33:J$1048576,COUNTA(J$33:J$1048576)-12)} -> 3.3200019 | K6: {=INDEX(K$19:K$1048576,COUNTA(K$19:K$1048576))-INDEX(K$19:K$1048576,COUNTA(K$19:K$1048576)-12)} -> 29.401961 | L6: {=INDEX(L$31:L$1048576,COUNTA(L$31:L$1048576))-INDEX(L$31:L$1048576,COUNTA(L$31:L$1048576)-12)} -> -1.5906324 | M6: {=INDEX(M$33:M$1048576,COUNTA(M$33:M$1048576))-INDEX(M$33:M$1048576,COUNTA(M$33:M$1048576)-12)} -> -0.68773751 | N6: {=INDEX(N$19:N$1048576,COUNTA(N$19:N$1048576))-INDEX(N$19:N$1048576,COUNTA(N$19:N$1048576)-12)} -> 13.934032 | O6: {=INDEX(O$31:O$1048576,COUNTA(O$31:O$1048576))-INDEX(O$31:O$1048576,COUNTA(O$31:O$1048576)-12)} -> -5.4371835 | P6: {=INDEX(P$33:P$1048576,COUNTA(P$33:P$1048576))-INDEX(P$33:P$1048576,COUNTA(P$33:P$1048576)-12)} -> -2.8871545 | Q6: {=INDEX(Q$19:Q$1048576,COUNTA(Q$19:Q$1048576))-INDEX(Q$19:Q$1048576,COUNTA(Q$19:Q$1048576)-12)} -> 56.799616 | R6: {=INDEX(R$31:R$1048576,COUNTA(R$31:R$1048576))-INDEX(R$31:R$1048576,COUNTA(R$31:R$1048576)-12)} -> 4.1292809 | S6: {=INDEX(S$33:S$1048576,COUNTA(S$33:S$1048576))-INDEX(S$33:S$1048576,COUNTA(S$33:S$1048576)-12)} -> 3.6061328 | T6: {=INDEX(T$19:T$1048576,COUNTA(T$19:T$1048576))-INDEX(T$19:T$1048576,COUNTA(T$19:T$1048576)-12)} -> 33.946442 | U6: {=INDEX(U$31:U$1048576,COUNTA(U$31:U$1048576))-INDEX(U$31:U$1048576,COUNTA(U$31:U$1048576)-12)} -> -1.473204 | V6: {=INDEX(V$33:V$1048576,COUNTA(V$33:V$1048576))-INDEX(V$33:V$1048576,COUNTA(V$33:V$1048576)-12)} -> -1.5713565 | W6: {=INDEX(W$19:W$1048576,COUNTA(W$19:W$1048576))-INDEX(W$19:W$1048576,COUNTA(W$19:W$1048576)-12)} -> 14.839506 | X6: {=INDEX(X$31:X$1048576,COUNTA(X$31:X$1048576))-INDEX(X$31:X$1048576,COUNTA(X$31:X$1048576)-12)} -> -5.1113154 | Y6: {=INDEX(Y$33:Y$1048576,COUNTA(Y$33:Y$1048576))-INDEX(Y$33:Y$1048576,COUNTA(Y$33:Y$1048576)-12)} -> -2.3284809 | Z6: {=INDEX(Z$19:Z$1048576,COUNTA(Z$19:Z$1048576))-INDEX(Z$19:Z$1048576,COUNTA(Z$19:Z$1048576)-12)} -> 23.607618 | AA6: {=INDEX(AA$31:AA$1048576,COUNTA(AA$31:AA$1048576))-INDEX(AA$31:AA$1048576,COUNTA(AA$31:AA$1048576)-12)} -> -1.1393041 | AB6: {=INDEX(AB$33:AB$1048576,COUNTA(AB$33:AB$1048576))-INDEX(AB$33:AB$1048576,COUNTA(AB$33:AB$1048576)-12)} -> -0.87189414
A7: Since pandemic | B7: {=INDEX(B$19:B$1048576,COUNTA(B$19:B$1048576))-B$260} -> 175.53872 | C7: {=INDEX(C$31:C$1048576,COUNTA(C$31:C$1048576))-C$260} -> 1.5920218 | D7: {=INDEX(D$31:D$1048576,COUNTA(D$31:D$1048576))-D$260} -> 1.7953844 | E7: {=INDEX(E$19:E$1048576,COUNTA(E$19:E$1048576))-E$260} -> 174.46224 | F7: {=INDEX(F$31:F$1048576,COUNTA(F$31:F$1048576))-F$260} -> 0.76685572 | G7: {=INDEX(G$31:G$1048576,COUNTA(G$31:G$1048576))-G$260} -> 1.5583416 | H7: {=INDEX(H$19:H$1048576,COUNTA(H$19:H$1048576))-H$260} -> 179.24324 | I7: {=INDEX(I$31:I$1048576,COUNTA(I$31:I$1048576))-I$260} -> 5.0453289 | J7: {=INDEX(J$31:J$1048576,COUNTA(J$31:J$1048576))-J$260} -> 2.7677486 | K7: {=INDEX(K$19:K$1048576,COUNTA(K$19:K$1048576))-K$260} -> 178.98629 | L7: {=INDEX(L$31:L$1048576,COUNTA(L$31:L$1048576))-L$260} -> 1.5090972 | M7: {=INDEX(M$31:M$1048576,COUNTA(M$31:M$1048576))-M$260} -> 1.6552585 | N7: {=INDEX(N$19:N$1048576,COUNTA(N$19:N$1048576))-N$260} -> 240.30184 | O7: {=INDEX(O$31:O$1048576,COUNTA(O$31:O$1048576))-O$260} -> -1.5898071 | P7: {=INDEX(P$31:P$1048576,COUNTA(P$31:P$1048576))-P$260} -> -0.40137197 | Q7: {=INDEX(Q$19:Q$1048576,COUNTA(Q$19:Q$1048576))-Q$260} -> 182.86868 | R7: {=INDEX(R$31:R$1048576,COUNTA(R$31:R$1048576))-R$260} -> 5.0666861 | S7: {=INDEX(S$31:S$1048576,COUNTA(S$31:S$1048576))-S$260} -> 3.1469969 | T7: {=INDEX(T$19:T$1048576,COUNTA(T$19:T$1048576))-T$260} -> 171.61718 | U7: {=INDEX(U$31:U$1048576,COUNTA(U$31:U$1048576))-U$260} -> 2.6648845 | V7: {=INDEX(V$31:V$1048576,COUNTA(V$31:V$1048576))-V$260} -> 2.4496397 | W7: {=INDEX(W$19:W$1048576,COUNTA(W$19:W$1048576))-W$260} -> 149.67181 | X7: {=INDEX(X$31:X$1048576,COUNTA(X$31:X$1048576))-X$260} -> -0.23324064 | Y7: {=INDEX(Y$31:Y$1048576,COUNTA(Y$31:Y$1048576))-Y$260} -> 1.5810193 | Z7: {=INDEX(Z$19:Z$1048576,COUNTA(Z$19:Z$1048576))-Z$260} -> 122.86012 | AA7: {=INDEX(AA$31:AA$1048576,COUNTA(AA$31:AA$1048576))-AA$260} -> 3.0070842 | AB7: {=INDEX(AB$31:AB$1048576,COUNTA(AB$31:AB$1048576))-AB$260} -> 3.6759666
A8: Since 2010 election | B8: {=INDEX(B$19:B$1048576,COUNTA(B$19:B$1048576))-B$142} -> 270.4003 | C8: {=INDEX(C$31:C$1048576,COUNTA(C$31:C$1048576))-C$142} -> 3.0089659 | D8: {=INDEX(D$31:D$1048576,COUNTA(D$31:D$1048576))-D$142} -> 3.0687376 | E8: {=INDEX(E$19:E$1048576,COUNTA(E$19:E$1048576))-E$142} -> 274.36383 | F8: {=INDEX(F$31:F$1048576,COUNTA(F$31:F$1048576))-F$142} -> 2.824788 | G8: {=INDEX(G$31:G$1048576,COUNTA(G$31:G$1048576))-G$142} -> 3.5699942 | H8: {=INDEX(H$19:H$1048576,COUNTA(H$19:H$1048576))-H$142} -> 266.80277 | I8: {=INDEX(I$31:I$1048576,COUNTA(I$31:I$1048576))-I$142} -> 5.0786723 | J8: {=INDEX(J$31:J$1048576,COUNTA(J$31:J$1048576))-J$142} -> 2.2518819 | K8: {=INDEX(K$19:K$1048576,COUNTA(K$19:K$1048576))-K$142} -> 272.8156 | L8: {=INDEX(L$31:L$1048576,COUNTA(L$31:L$1048576))-L$142} -> 3.3663456 | M8: {=INDEX(M$31:M$1048576,COUNTA(M$31:M$1048576))-M$142} -> 3.3566648 | N8: {=INDEX(N$19:N$1048576,COUNTA(N$19:N$1048576))-N$142} -> 368.44991 | O8: {=INDEX(O$31:O$1048576,COUNTA(O$31:O$1048576))-O$142} -> -0.27139732 | P8: {=INDEX(P$31:P$1048576,COUNTA(P$31:P$1048576))-P$142} -> 0.83098799 | Q8: {=INDEX(Q$19:Q$1048576,COUNTA(Q$19:Q$1048576))-Q$142} -> 271.42333 | R8: {=INDEX(R$31:R$1048576,COUNTA(R$31:R$1048576))-R$142} -> 5.9803278 | S8: {=INDEX(S$31:S$1048576,COUNTA(S$31:S$1048576))-S$142} -> 3.664046 | T8: {=INDEX(T$19:T$1048576,COUNTA(T$19:T$1048576))-T$142} -> 275.60111 | U8: {=INDEX(U$31:U$1048576,COUNTA(U$31:U$1048576))-U$142} -> 0.13074301 | V8: {=INDEX(V$31:V$1048576,COUNTA(V$31:V$1048576))-V$142} -> -0.3086577 | W8: {=INDEX(W$19:W$1048576,COUNTA(W$19:W$1048576))-W$142} -> 258.12632 | X8: {=INDEX(X$31:X$1048576,COUNTA(X$31:X$1048576))-X$142} -> 0.77094528 | Y8: {=INDEX(Y$31:Y$1048576,COUNTA(Y$31:Y$1048576))-Y$142} -> 2.5391795 | Z8: {=INDEX(Z$19:Z$1048576,COUNTA(Z$19:Z$1048576))-Z$142} -> 191.97642 | AA8: {=INDEX(AA$31:AA$1048576,COUNTA(AA$31:AA$1048576))-AA$142} -> 3.2258843 | AB8: {=INDEX(AB$31:AB$1048576,COUNTA(AB$31:AB$1048576))-AB$142} -> 3.9920737
A10: Table 15: Average Weekly Earnings (nominal) - Regular Pay (Great Britain, seasonally adjusted)1 | M10: Source: Monthly Wages & Salaries Survey
A11: Date of publication: | E11: 45643 | H11: Date of next publication: | L11: 45678
A12: Inquiries: Email: | C12: labour.market@ons.gov.uk | J12: Tel: 01633 455400
A13: Standard Industrial Classification (2007)
B14: Whole Economy | E14: Private sector 3 4 5 | H14: Public sector 3 4 5 | K14: Services, SIC 2007 sections G-S | N14: Finance and business services, SIC 2007 sections K-N | Q14: Public sector excluding financial services 4 5 | T14: Manufacturing, SIC 2007 section C | W14: Construction, SIC 2007 section F | Z14: Wholesaling, retailing, hotels & restaurants, SIC 2007 sections G & I
B15: Weekly Earnings (£) | C15: % changes year on year | E15: Weekly Earnings (£) | F15: % changes year on year | H15: Weekly Earnings (£) | I15: % changes year on year | K15: Weekly Earnings (£) | L15: % changes year on year | N15: Weekly Earnings (£) | O15: % changes year on year | Q15: Weekly Earnings (£) | R15: % changes year on year | T15: Weekly Earnings (£) | U15: % changes year on year | W15: Weekly Earnings (£) | X15: % changes year on year | Z15: Weekly Earnings (£) | AA15: % changes year on year
C16: Single month | D16: 3 month average 2 | F16: Single month | G16: 3 month average 2 | I16: Single month | J16: 3 month average 2 | L16: Single month | M16: 3 month average 2 | O16: Single month | P16: 3 month average 2 | R16: Single month | S16: 3 month average 2 | U16: Single month | V16: 3 month average 2 | X16: Single month | Y16: 3 month average 2 | AA16: Single month | AB16: 3 month average 2
B17: KAI7 | C17: KAI8 | D17: KAI9 | E17: KAJ2 | F17: KAJ3 | G17: KAJ4 | H17: KAJ5 | I17: KAJ6 | J17: KAJ7 | K17: K5DL | L17: K5DM | M17: K5DN | N17: K5DO | O17: K5DP | P17: K5DQ | Q17: KAK6 | R17: KAK7 | S17: KAK8 | T17: K5DU | U17: K5DV | V17: K5DW | W17: K5DX | X17: K5DY | Y17: K5DZ | Z17: K5E2 | AA17: K5E3 | AB17: K5E4
A19: 36526 | B19: 293.41283 | E19: 289.02816 | H19: 310.37844 | K19: 278.50623 | N19: 335.66736 | Q19: 310.47127 | T19: 346.47058 | W19: 341.39654 | Z19: 197.69683
A20: 36557 | B20: 293.33006 | E20: 289.0332 | H20: 311.84042 | K20: 278.88776 | N20: 334.36444 | Q20: 311.54559 | T20: 345.86752 | W20: 343.15923 | Z20: 197.26653
A21: 36586 | B21: 292.73182 | E21: 288.45026 | H21: 308.94385 | K21: 277.38791 | N21: 334.09264 | Q21: 308.85264 | T21: 347.56597 | W21: 343.97908 | Z21: 195.81808
A22: 36617 | B22: 292.95622 | E22: 289.16074 | H22: 306.33844 | K22: 276.10631 | N22: 332.68352 | Q22: 306.7981 | T22: 349.61863 | W22: 344.93147 | Z22: 197.21612
A23: 36647 | B23: 294.44711 | E23: 290.71832 | H23: 307.78023 | K23: 279.18957 | N23: 339.34805 | Q23: 307.53209 | T23: 347.65633 | W23: 346.62002 | Z23: 199.87914
A24: 36678 | B24: 295.18579 | E24: 291.13929 | H24: 310.38378 | K24: 280.06247 | N24: 338.93362 | Q24: 310.20975 | T24: 347.7118 | W24: 352.52283 | Z24: 198.41488
A25: 36708 | B25: 295.65974 | E25: 291.7994 | H25: 310.19833 | K25: 280.89897 | N25: 341.93217 | Q25: 309.87232 | T25: 347.862 | W25: 351.98817 | Z25: 198.04434
A26: 36739 | B26: 296.9482 | E26: 292.97268 | H26: 311.89698 | K26: 282.21413 | N26: 339.79255 | Q26: 311.86976 | T26: 348.55497 | W26: 356.10299 | Z26: 199.18634
A27: 36770 | B27: 299.16012 | E27: 295.58629 | H27: 312.16957 | K27: 284.6412 | N27: 347.66319 | Q27: 311.94254 | T27: 351.03709 | W27: 355.07314 | Z27: 201.4805
A28: 36800 | B28: 300.22432 | E28: 296.65613 | H28: 313.45323 | K28: 285.4421 | N28: 348.83397 | Q28: 313.48111 | T28: 352.26966 | W28: 361.15658 | Z28: 202.06985
A29: 36831 | B29: 301.50505 | E29: 297.84886 | H29: 315.45455 | K29: 286.53217 | N29: 350.61544 | Q29: 315.57091 | T29: 354.40034 | W29: 362.49597 | Z29: 203.04545
A30: 36861 | B30: 302.66217 | E30: 299.23332 | H30: 315.14553 | K30: 287.68966 | N30: 354.41822 | Q30: 315.66468 | T30: 355.09177 | W30: 366.57049 | Z30: 202.70792
A31: 36892 | B31: 303.91052 | C31: 3.5777891 | E31: 299.77332 | F31: 3.7176874 | H31: 319.26944 | I31: 2.864568 | K31: 288.69288 | L31: 3.6576025 | N31: 352.42906 | O31: 4.9935449 | Q31: 319.07022 | R31: 2.7696418 | T31: 358.14504 | U31: 3.3695381 | W31: 368.45105 | X31: 7.9246612 | Z31: 202.53065 | AA31: 2.4450655
A32: 36923 | B32: 304.04604 | C32: 3.6532153 | E32: 300.17228 | F32: 3.8539086 | H32: 320.69645 | I32: 2.8399225 | K32: 288.95676 | L32: 3.6104124 | N32: 350.39006 | O32: 4.7928604 | Q32: 320.81896 | R32: 2.9765723 | T32: 358.86054 | U32: 3.7566469 | W32: 365.24133 | X32: 6.4349435 | Z32: 203.20841 | AA32: 3.0121067
A33: 36951 | B33: 305.981 | C33: 4.5260464 | D33: 3.9185719 | E33: 301.66468 | F33: 4.5811793 | G33: 4.0505703 | H33: 322.34169 | I33: 4.3366576 | J33: 3.3447285 | K33: 290.85336 | L33: 4.854378 | M33: 4.039511 | N33: 354.89274 | O33: 6.2258464 | P33: 5.3367306 | Q33: 322.38905 | R33: 4.3828041 | S33: 3.374128 | T33: 360.09419 | U33: 3.6045588 | V33: 3.5768395 | W33: 371.6378 | X33: 8.0408143 | Y33: 7.4664792 | Z33: 203.88006 | AA33: 4.1170724 | AB33: 3.1886018
A34: 36982 | B34: 308.58335 | C34: 5.3342877 | D34: 4.5041489 | E34: 304.05329 | F34: 5.1502699 | G34: 4.5285087 | H34: 325.37064 | I34: 6.212802 | J34: 4.4531391 | K34: 292.90478 | L34: 6.0840575 | M34: 4.8454824 | N34: 356.77246 | O34: 7.2407999 | P34: 6.0845263 | Q34: 325.44811 | R34: 6.0789192 | S34: 4.4715227 | T34: 362.4044 | U34: 3.6570616 | V34: 3.6725883 | W34: 373.75727 | X34: 8.3569656 | Y34: 7.6125304 | Z34: 204.14251 | AA34: 3.5120792 | AB34: 3.5456905
A35: 37012 | B35: 308.86331 | C35: 4.8960225 | D35: 4.9188471 | E35: 304.09898 | F35: 4.6026199 | G35: 4.7778695 | H35: 326.81461 | I35: 6.1844062 | J35: 5.5753988 | K35: 293.65906 | L35: 5.1826776 | M35: 5.3721977 | N35: 357.52989 | O35: 5.3578745 | P35: 6.2686977 | Q35: 326.72181 | R35: 6.2399095 | S35: 5.5651099 | T35: 361.95477 | U35: 4.112808 | V35: 3.7912399 | W35: 376.59659 | X35: 8.6482531 | Y35: 8.3494493 | Z35: 203.77389 | AA35: 1.9485497 | AB35: 3.1847998
A36: 37043 | B36: 309.70532 | C36: 4.9187739 | D36: 5.0491043 | E36: 304.89993 | F36: 4.7264821 | G36: 4.8258299 | H36: 328.31089 | I36: 5.7757881 | J36: 6.0566297 | K36: 294.80336 | L36: 5.2634266 | M36: 5.5076775 | N36: 359.61759 | O36: 6.1026627 | P36: 6.2271943 | Q36: 327.63547 | R36: 5.6173977 | S36: 5.9776161 | T36: 362.6402 | U36: 4.2933266 | V36: 4.0203963 | W36: 378.16068 | X36: 7.272678 | Y36: 8.087569 | Z36: 205.15901 | AA36: 3.3990054 | AB36: 2.9496161
A37: 37073 | B37: 311.45833 | C37: 5.3435021 | D37: 5.0530526 | E37: 306.6873 | F37: 5.1021001 | G37: 4.8107212 | H37: 329.84835 | I37: 6.3346636 | J37: 6.0979972 | K37: 296.2198 | L37: 5.4542162 | M37: 5.3003822 | N37: 361.36748 | O37: 5.6839651 | P37: 5.7145984 | Q37: 329.18476 | R37: 6.2323857 | S37: 6.0292177 | T37: 363.0606 | U37: 4.3691476 | V37: 4.2584511 | W37: 384.63643 | X37: 9.2753834 | Y37: 8.3969246 | Z37: 206.75812 | AA37: 4.3999113 | AB37: 3.2452469
A38: 37104 | B38: 313.5167 | C38: 5.579592 | D38: 5.2812497 | E38: 308.55706 | F38: 5.3193988 | G38: 5.049932 | H38: 332.63293 | I38: 6.648332 | J38: 6.2535533 | K38: 298.36057 | L38: 5.7213455 | M38: 5.4802543 | N38: 363.31671 | O38: 6.9230934 | P38: 6.235528 | Q38: 332.38887 | R38: 6.5793847 | S38: 6.1438009 | T38: 364.55553 | U38: 4.5905428 | V38: 4.417805 | W38: 386.94479 | X38: 8.660921 | Y38: 8.403425 | Z38: 207.72184 | AA38: 4.2851835 | AB38: 4.0281351
A39: 37135 | B39: 313.48173 | C39: 4.7872742 | D39: 5.2355203 | E39: 308.7356 | F39: 4.4485529 | G39: 4.9549816 | H39: 331.73048 | I39: 6.2661196 | J39: 6.4164765 | K39: 298.50095 | L39: 4.8691975 | M39: 5.3467172 | N39: 362.00942 | O39: 4.1264737 | P39: 5.5669676 | Q39: 331.5086 | R39: 6.2723297 | S39: 6.3616357 | T39: 366.07217 | U39: 4.2830457 | V39: 4.4139643 | W39: 385.41846 | X39: 8.5462193 | Y39: 8.8260469 | Z39: 207.6454 | AA39: 3.0598016 | AB39: 3.9107636
A40: 37165 | B40: 314.59792 | C40: 4.7876174 | D40: 5.049878 | E40: 309.82018 | F40: 4.4374759 | G40: 4.7330577 | H40: 332.62298 | I40: 6.1156654 | J40: 6.3429719 | K40: 299.49078 | L40: 4.9217238 | M40: 5.1689537 | N40: 362.67893 | O40: 3.9689279 | P40: 4.9904341 | Q40: 332.12325 | R40: 5.9468127 | S40: 6.2656272 | T40: 367.51676 | U40: 4.3282469 | V40: 4.4000788 | W40: 388.25037 | X40: 7.5019499 | Y40: 8.2326047 | Z40: 207.99678 | AA40: 2.9331113 | AB40: 3.42228
A41: 37196 | B41: 316.07764 | C41: 4.8332816 | D41: 4.8027861 | E41: 311.85998 | F41: 4.7041025 | G41: 4.5303749 | H41: 332.09319 | I41: 5.274496 | J41: 5.8836085 | K41: 301.19762 | L41: 5.1182567 | M41: 4.970009 | N41: 369.60992 | O41: 5.4174662 | P41: 4.5062653 | Q41: 331.99639 | R41: 5.2050064 | S41: 5.8059512 | T41: 369.12614 | U41: 4.1551332 | V41: 4.255241 | W41: 387.28899 | X41: 6.8395314 | Y41: 7.6230817 | Z41: 208.61667 | AA41: 2.7438258 | AB41: 2.911832
A42: 37226 | B42: 316.2507 | C42: 4.48967 | D42: 4.7031303 | E42: 311.8943 | F42: 4.231137 | G42: 4.4572478 | H42: 332.65949 | I42: 5.5574221 | J42: 5.6482357 | K42: 301.52909 | L42: 4.8105428 | M42: 4.9500225 | N42: 369.50753 | O42: 4.2574882 | P42: 4.5478914 | Q42: 332.9639 | R42: 5.4802513 | S42: 5.5431262 | T42: 369.66965 | U42: 4.1053853 | V42: 4.1959311 | W42: 387.7292 | X42: 5.7720704 | Y42: 6.7000527 | Z42: 207.90663 | AA42: 2.5646323 | AB42: 2.7469927
A43: 37257 | B43: 317.51812 | C43: 4.4775012 | D43: 4.5996852 | E43: 312.95509 | F43: 4.3972456 | G43: 4.4437322 | H43: 334.39218 | I43: 4.7366687 | J43: 5.1875905 | K43: 303.03651 | L43: 4.9684732 | M43: 4.9655562 | N43: 368.4231 | O43: 4.5382315 | P43: 4.7356595 | Q43: 334.38241 | R43: 4.7990052 | S43: 5.1601179 | T43: 371.25708 | U43: 3.6610985 | V43: 3.9728605 | W43: 382.04715 | X43: 3.6900696 | Y43: 5.425684 | Z43: 208.89891 | AA43: 3.1443448 | AB43: 2.8174648
A44: 37288 | B44: 319.82423 | C44: 5.1894071 | D44: 4.7192436 | E44: 316.19809 | F44: 5.3388696 | G44: 4.6563088 | H44: 335.00377 | I44: 4.4613289 | J44: 4.9150314 | K44: 305.36992 | L44: 5.6801445 | M44: 5.1536113 | N44: 372.78948 | O44: 6.3927092 | P44: 5.0587296 | Q44: 334.94639 | R44: 4.4035491 | S44: 4.8912821 | T44: 372.79173 | U44: 3.8820619 | V44: 3.8822143 | W44: 391.09561 | X44: 7.0786839 | Y44: 5.5086005 | Z44: 210.15265 | AA44: 3.4173017 | AB44: 3.0423718
... A328: 45931 | B328: 687.43684 | C328: 4.4424634 | D328: 4.600438 | E328: 678.97169 | F328: 3.4792427 | G328: 3.8650393 | H328: 726.0603 | I328: 8.4806104 | J328: 7.6338764 | K328: 674.38606 | L328: 4.5585559 | M328: 4.6927585 | N328: 859.74478 | O328: 1.6474172 | P328: 2.2981009 | Q328: 726.08473 | R328: 8.4866098 | S328: 8.0017971 | T328: 768.89081 | U328: 4.6189131 | V328: 4.4606137 | W328: 769.40742 | X328: 1.966623 | Y328: 2.9074512 | Z328: 465.39075 | AA328: 5.343712 | AB328: 5.5335217
A329: 3. From July 2009 Royal Bank of Scotland Group plc is classified to the public sector; for earlier time periods it is classified to the private sector. Between July 2009 and March 2014 Lloyds Banking Group plc is classified to the public sector; it is classified to the private sector for earlier and later time periods.
A330: 4. Between June 2010 and May 2012 English Further Education Corporations and Sixth Form College Corporations are classified to the public sector. Before June 2010 and after May 2012 they are classified to the private sector.
A331: 5. From October 2013 Royal Mail plc is classified to the private sector; previously it is in the public sector.

Sheet 18
B1: Working days lost (thousands) | C1: Number of stoppages 1,2 | D1: Workers involved (thousands) 3
A2: Current (singular month) | B2: {=INDEX(B$16:B$1048576,COUNTA(B$16:B$1048576))} -> 39 | C2: {=INDEX(C$16:C$1048576,COUNTA(C$16:C$1048576))} -> 37 | D2: {=INDEX(D$16:D$1048576,COUNTA(D$16:D$1048576))} -> 6
A3: Change on quarter (3mo avg) | B3: =(AVERAGE(OFFSET(INDEX(B$16:B$1048576,COUNTA(B$16:B$1048576)),-2,0,3,1))-AVERAGE(OFFSET(INDEX(B$16:B$1048576,COUNTA(B$16:B$1048576)),-5,0,3,1)))*52 -> -936 | C3: =AVERAGE(OFFSET(INDEX(C$16:C$1048576,COUNTA(C$16:C$1048576)),-2,0,3,1))-AVERAGE(OFFSET(INDEX(C$16:C$1048576,COUNTA(C$16:C$1048576)),-5,0,3,1)) -> -72.333333 | D3: =AVERAGE(OFFSET(INDEX(D$16:D$1048576,COUNTA(D$16:D$1048576)),-2,0,3,1))-AVERAGE(OFFSET(INDEX(D$16:D$1048576,COUNTA(D$16:D$1048576)),-5,0,3,1)) -> -5.3333333
A4: Change since Covid-19 (2019 average) | B4: =(AVERAGE(OFFSET(INDEX(B$16:B$1048576,COUNTA(B$16:B$1048576)),-2,0,3,1))-AVERAGE(B$1072:B$1083))*52 -> 702 | C4: =AVERAGE(OFFSET(INDEX(C$16:C$1048576,COUNTA(C$16:C$1048576)),-2,0,3,1))-AVERAGE(C$1072:C$1083) -> 20.416667 | D4: =AVERAGE(OFFSET(INDEX(D$16:D$1048576,COUNTA(D$16:D$1048576)),-2,0,3,1))-AVERAGE(D$1072:D$1083) -> 0.33333333
A5: Change since 2024 election (3mo avg) | B5: =(AVERAGE(OFFSET(INDEX(B$16:B$1048576,COUNTA(B$16:B$1048576)),-2,0,3,1))-AVERAGE(B$1135:B$1137))*52 -> -1196 | C5: =AVERAGE(OFFSET(INDEX(C$16:C$1048576,COUNTA(C$16:C$1048576)),-2,0,3,1))-AVERAGE(C$1135:C$1137) -> -102.33333 | D5: =AVERAGE(OFFSET(INDEX(D$16:D$1048576,COUNTA(D$16:D$1048576)),-2,0,3,1))-AVERAGE(D$1135:D$1137) -> -15
A6: 2019 average | B6: =AVERAGE(B$1072:B$1083) -> 19.5 | C6: =AVERAGE(C$1072:C$1083) -> 13.916667 | D6: =AVERAGE(D$1072:D$1083) -> 6.6666667
A7: 2023 average | B7: =AVERAGE(B$1120:B$1131) -> 221.66667 | C7: =AVERAGE(C$1120:C$1131) -> 456.66667 | D7: =AVERAGE(D$1120:D$1131) -> 117.83333
A9: Table 18: Labour Disputes summary, UK (not seasonally adjusted)
A10: Date of publication: | B10: 45307 | D10: Date of next publication:
A11: Inquiries: Email: | B11: labour.market@ons.gov.uk | D11: Tel: 01633 455400
C13: Source: Labour Disputes Inquiry, Office for National Statistics
A14: Time period and dataset code row | B14: Working days lost (thousands) | C14: Number of stoppages 1,2 | D14: Workers involved (thousands) 3
A15: Dataset identifier code | B15: BBFW | C15: BLUU | D15: BLUT
A16: January 1931 | B16: 3647 | C16: 50 | D16: [x]
A17: February 1931 | B17: 1794 | C17: 34 | D17: [x]
A18: March 1931 | B18: 177 | C18: 42 | D18: [x]
A19: April 1931 | B19: 123 | C19: 56 | D19: [x]
A20: May 1931 | B20: 192 | C20: 53 | D20: [x]
A21: June 1931 | B21: 116 | C21: 41 | D21: [x]
A22: July 1931 | B22: 358 | C22: 51 | D22: [x]
A23: August 1931 | B23: 347 | C23: 50 | D23: [x]
A24: September 1931 | B24: 79 | C24: 40 | D24: [x]
A25: October 1931 | B25: 57 | C25: 36 | D25: [x]
A26: November 1931 | B26: 42 | C26: 36 | D26: [x]
A27: December 1931 | B27: 51 | C27: 26 | D27: [x]
... A675: December 1985 | B675: 220 | C675: 72 | D675: [x]
A676: January 1986 | B676: 217 | C676: 96 | D676: 183
A677: February 1986 | B677: 248 | C677: 116 | D677: 188
A678: March 1986 | B678: 184 | C678: 91 | D678: 66
A679: April 1986 | B679: 145 | C679: 128 | D679: 62
A680: May 1986 | B680: 288 | C680: 99 | D680: 49
A681: June 1986 | B681: 170 | C681: 116 | D681: 64
A682: July 1986 | B682: 67 | C682: 100 | D682: 22
A683: August 1986 | B683: 67 | C683: 92 | D683: 28
A684: September 1986 | B684: 154 | C684: 102 | D684: 67
A685: October 1986 | B685: 167 | C685: 148 | D685: 48
A686: November 1986 | B686: 117 | C686: 107 | D686: 98
A687: December 1986 | B687: 97 | C687: 91 | D687: 50
... A1084: January 2020 | B1084: 18 | C1084: 7 | D1084: 7
A1085: February 2020 | B1085: [x] | C1085: [x] | D1085: [x]
A1086: March 2020 | B1086: [x] | C1086: [x] | D1086: [x]
A1087: April 2020 | B1087: [x] | C1087: [x] | D1087: [x]
A1088: May 2020 | B1088: [x] | C1088: [x] | D1088: [x]
A1089: June 2020 | B1089: [x] | C1089: [x] | D1089: [x]
A1090: July 2020 | B1090: [x] | C1090: [x] | D1090: [x]
A1091: August 2020 | B1091: [x] | C1091: [x] | D1091: [x]
A1092: September 2020 | B1092: [x] | C1092: [x] | D1092: [x]
A1093: October 2020 | B1093: [x] | C1093: [x] | D1093: [x]
A1094: November 2020 | B1094: [x] | C1094: [x] | D1094: [x]
A1095: December 2020 | B1095: [x] | C1095: [x] | D1095: [x]
A1096: January 2021 | B1096: [x] | C1096: [x] | D1096: [x]
... A1107: December 2021 | B1107: [x] | C1107: [x] | D1107: [x]
A1108: January 2022 | B1108: 22 | C1108: 12 | D1108: 1
A1109: February 2022 | B1109: 15 | C1109: 21 | D1109: 3
A1110: March 2022 | B1110: 36 | C1110: 55 | D1110: 12
A1111: April 2022 | B1111: 20 | C1111: 59 | D1111: 5
A1112: May 2022 | B1112: 32 | C1112: 76 | D1112: 9
A1113: June 2022 | B1113: 93 | C1113: 41 | D1113: 31
A1114: July 2022 | B1114: 86 | C1114: 52 | D1114: 53
A1115: August 2022 | B1115: 359 | C1115: 78 | D1115: 150
A1116: September 2022 | B1116: 208 | C1116: 79 | D1116: 98
A1117: October 2022 | B1117: 423 | C1117: 124 | D1117: 146
A1118: November 2022 | B1118: 390 | C1118: 316 | D1118: 165
A1119: December 2022 | B1119: 830 | C1119: 203 | D1119: 155
... A1153: October 2025 [p] | B1153: 39 | C1153: 37 | D1153: 6

Sheet 20
B1: All Vacancies1 (thousands) | C1: Unemployment2 (thousands) | D1: Number of unemployed people per vacancy | G1: All Vacancies1 (thousands) | H1: Unemployment2 (thousands) | I1: Number of unemployed people per vacancy
A2: Current | B2: {=INDEX(C$17:C$1048576,COUNTA(C$17:C$1048576))} -> 729 | C2: {=INDEX(D$17:D$1048576,COUNTA(D$17:D$1048576)-1)} -> 1832 | D2: {=INDEX(E$17:E$1048576,COUNTA(E$17:E$1048576)-1)} -> 2.5 | F2: Current | G2: =B2 -> 729 | H2: =C2 -> 1832 | I2: =D2 -> 2.5
A3: Quarterly change | B3: {=INDEX(C$17:C$1048576,COUNTA(C$17:C$1048576))-INDEX(C$17:C$1048576,COUNTA(C$17:C$1048576)-3)} -> -2 | C3: {=INDEX(D$17:D$1048576,COUNTA(D$17:D$1048576)-1)-INDEX(D$17:D$1048576,COUNTA(D$17:D$1048576)-4)} -> 158 | D3: {=INDEX(E$17:E$1048576,COUNTA(E$17:E$1048576)-1)-INDEX(E$17:E$1048576,COUNTA(E$17:E$1048576)-4)} -> 0.2 | F3: Quarterly change | G3: {=B3/INDEX(C$17:C$1048576,COUNTA(C$17:C$1048576)-1)} -> -0.0027586207 | H3: {=C3/INDEX(D$17:D$1048576,COUNTA(D$17:D$1048576)-2)} -> 0.088317496 | I3: {=D3/INDEX(E$17:E$1048576,COUNTA(E$17:E$1048576)-2)} -> 0.08
A4: Year on year change | B4: {=INDEX(C$17:C$1048576,COUNTA(C$17:C$1048576))-INDEX(C$17:C$1048576,COUNTA(C$17:C$1048576)-12)} -> -78 | C4: {=INDEX(D$17:D$1048576,COUNTA(D$17:D$1048576)-1)-INDEX(D$17:D$1048576,COUNTA(D$17:D$1048576)-13)} -> 327 | D4: {=INDEX(E$17:E$1048576,COUNTA(E$17:E$1048576)-1)-INDEX(E$17:E$1048576,COUNTA(E$17:E$1048576)-13)} -> 0.7 | F4: Year on year change | G4: {=B4/INDEX(C$17:C$1048576,COUNTA(C$17:C$1048576)-12)} -> -0.096654275 | H4: {=C4/INDEX(D$17:D$1048576,COUNTA(D$17:D$1048576)-13)} -> 0.21727575 | I4: {=D4/INDEX(E$17:E$1048576,COUNTA(E$17:E$1048576)-13)} -> 0.38888889
A5: Pre-pandemic trend (Jan-Mar) | B5: {=INDEX(C$17:C$1048576,COUNTA(C$17:C$1048576))-C$242} -> -66 | C5: {=INDEX(D$17:D$1048576,COUNTA(D$17:D$1048576)-1)-D$242} -> 421 | D5: {=INDEX(E$17:E$1048576,COUNTA(E$17:E$1048576)-1)-E$242} -> 0.7 | F5: Pre-pandemic trend (Jan-Mar) | G5: =B5/C242 -> -0.083018868 | H5: =C5/D242 -> 0.29836995 | I5: =D5/E242 -> 0.38888889
A6: Since 2024 election | B6: {=INDEX(C$17:C$1048576,COUNTA(C$17:C$1048576))-C$293} -> -141 | C6: {=INDEX(D$17:D$1048576,COUNTA(D$17:D$1048576)-1)-D$293} -> 365 | D6: {=INDEX(E$17:E$1048576,COUNTA(E$17:E$1048576)-1)-E$293} -> 0.8 | F6: Since 2010 election | G6: =B6/C123 -> -0.30192719 | H6: =C6/D123 -> 0.14541833 | I6: =D6/E123 -> 0.14814815
A7: *note: 1. Stats for unemployment are from the period before as data unavailable - check this is still the case.
A8: 2. Covid period is different (Jan-Mar) due to reporting periods
A9: Table 20: Vacancies1 and Unemployment (seasonally adjusted)
A10: Date of publication: | D10: 45307 | F10: Date of next publication:
A11: Inquiries: Email: | C11: labour.market@ons.gov.uk | H11: Tel: 01633 455400
A12: Source: ONS Vacancy Survey/ Labour Force Survey
F13: United Kingdom (thousands), seasonally adjusted
C15: All Vacancies1 (thousands) | D15: Unemployment2 (thousands) | E15: Number of unemployed people per vacancy
C16: AP2Y | D16: MGSC | E16: JPC5
A17: Apr-Jun 2001 | C17: 680 | D17: 1468 | E17: 2.2 | J17: =1/E17 -> 0.45454545
A18: May-Jul 2001 | C18: 674 | D18: 1472 | E18: 2.2 | J18: =1/E18 -> 0.45454545
A19: Jun-Aug 2001 | C19: 663 | D19: 1483 | E19: 2.2 | J19: =1/E19 -> 0.45454545
A20: Jul-Sep 2001 | C20: 663 | D20: 1487 | E20: 2.2 | J20: =1/E20 -> 0.45454545
A21: Aug-Oct 2001 | C21: 639 | D21: 1487 | E21: 2.3 | J21: =1/E21 -> 0.43478261
A22: Sep-Nov 2001 | C22: 626 | D22: 1495 | E22: 2.4 | J22: =1/E22 -> 0.41666667
A23: Oct-Dec 2001 | C23: 601 | D23: 1520 | E23: 2.5 | J23: =1/E23 -> 0.4
A24: Nov- Jan 2002 | C24: 606 | D24: 1518 | E24: 2.5 | J24: =1/E24 -> 0.4
A25: Dec-Feb 2002 | C25: 616 | D25: 1508 | E25: 2.4 | J25: =1/E25 -> 0.41666667
A26: Jan-Mar 2002 | C26: 619 | D26: 1515 | E26: 2.4 | J26: =1/E26 -> 0.41666667
A27: Feb-Apr 2002 | C27: 619 | D27: 1522 | E27: 2.5 | J27: =1/E27 -> 0.4
A28: Mar-May 2002 | C28: 613 | D28: 1542 | E28: 2.5 | J28: =1/E28 -> 0.4
... A290: Jan-Mar 2024 | C290: 905 | D290: 1513 | E290: 1.7 | J290: =1/E290 -> 0.58823529
A291: Feb-Apr 2024 | C291: 892 | D291: 1524 | E291: 1.7 | F291: =(C291/C290)-1 -> -0.014364641 | J291: =1/E291 -> 0.58823529
A292: Mar-May 2024 | C292: 886 | D292: 1549 | E292: 1.7 | F292: =(C292/C291)-1 -> -0.0067264574 | J292: =1/E292 -> 0.58823529
A293: Apr-Jun 2024 | C293: 870 | D293: 1467 | E293: 1.7 | F293: =(C293/C292)-1 -> -0.018058691 | J293: =1/E293 -> 0.58823529
A294: May-Jul 2024 | C294: 863 | D294: 1480 | E294: 1.7 | F294: =(C294/C293)-1 -> -0.008045977 | J294: =1/E294 -> 0.58823529
A295: Jun-Aug 2024 | C295: 847 | D295: 1440 | E295: 1.7 | F295: =(C295/C294)-1 -> -0.018539977 | J295: =1/E295 -> 0.58823529
A296: Jul-Sep 2024 | C296: 832 | D296: 1507 | E296: 1.8 | F296: =(C296/C295)-1 -> -0.017709563 | J296: =1/E296 -> 0.55555556
A297: Aug-Oct 2024 | C297: 822 | D297: 1505 | E297: 1.8 | F297: =(C297/C296)-1 -> -0.012019231 | J297: =1/E297 -> 0.55555556
A298: Sep-Nov 2024 | B298: (r) | C298: 807 | D298: 1560 | E298: 1.9 | F298: =(C298/C297)-1 -> -0.018248175 | J298: =1/E298 -> 0.52631579
A299: Oct-Dec 2024 | C299: 806 | D299: 1552 | E299: 1.9 | F299: =(C299/C298)-1 -> -0.0012391574 | J299: =1/E299 -> 0.52631579
A300: Nov-Jan 2025 | C300: 804 | D300: 1545 | E300: 1.9 | F300: =(C300/C299)-1 -> -0.0024813896 | J300: =1/E300 -> 0.52631579
A301: Dec-Feb 2025 | C301: 799 | D301: 1574 | E301: 2 | F301: =(C301/C300)-1 -> -0.0062189055 | J301: =1/E301 -> 0.5
A302: Jan-Mar 2025 | C302: 783 | D302: 1614 | E302: 2.1 | F302: =(C302/C301)-1 -> -0.020025031 | J302: =1/E302 -> 0.47619048
A303: Feb-Apr 2025 | C303: 762 | D303: 1640 | E303: 2.2 | F303: =(C303/C302)-1 -> -0.026819923 | J303: =1/E303 -> 0.45454545
A304: Mar-May 2025 | C304: 739 | D304: 1673 | E304: 2.3 | F304: =(C304/C303)-1 -> -0.030183727 | J304: =1/E304 -> 0.43478261
A305: Apr-Jun 2025 | C305: 726 | D305: 1672 | E305: 2.3 | F305: =(C305/C304)-1 -> -0.01759134 | J305: =1/E305 -> 0.43478261
A306: May-Jul 2025 | C306: 722 | D306: 1674 | E306: 2.3 | F306: =(C306/C305)-1 -> -0.0055096419 | J306: =1/E306 -> 0.43478261
A307: Jun-Aug 2025 | B307: (r) | C307: 731 | D307: 1737 | E307: 2.4 | F307: =(C307/C306)-1 -> 0.012465374 | J307: =1/E307 -> 0.41666667
A308: Jul-Sep 2025 | B308: (r) | C308: 725 | D308: 1789 | E308: 2.5 | F308: =(C308/C307)-1 -> -0.0082079343 | J308: =1/E308 -> 0.4
A309: Aug-Oct 2025 | B309: (r) | C309: 725 | D309: 1832 | E309: 2.5 | F309: =(C309/C308)-1 -> 0 | G309: =C309-C306 -> 3 | H309: =MAX(C17:C308) -> 1300
A310: Sep-Nov 2025 | B310: (p) | C310: 729 | D310: .. | E310: .. | F310: =(C310/C309)-1 -> 0.0055172414

Sheet 21
C1: All vacancies1 | D1: Mining & quarrying | E1: Manu- facturing | F1: Electricity, gas, steam & air conditioning supply2 | G1: Water supply, sewerage, waste & remediation activities | H1: Construc-tion | I1: Wholesale & retail trade; repair of motor vehicles and motor cycles | J1: Transport & storage | K1: Accomoda-tion & food service activities | L1: Information & communica-tion | M1: Financial & insurance activities | N1: Real estate activities2 | O1: Professional scientific & technical activities | P1: Administra-tive & support service activities | Q1: Public admin & defence; compulsory social security | R1: Education | S1: Human health & social work activities | T1: Arts, entertainment & recreation | U1: Other service activities | V1: Total services | W1: Motor Trades | X1: Wholesale | Y1: Retail
B2: Current | C2: {=INDEX(C$19:C$1048576,COUNTA(C$19:C$1048576))} -> 729 | D2: {=INDEX(D$19:D$1048576,COUNTA(D$19:D$1048576))} -> 1 | E2: {=INDEX(E$19:E$1048576,COUNTA(E$19:E$1048576))} -> 50 | F2: {=INDEX(F$19:F$1048576,COUNTA(F$19:F$1048576))} -> 3 | G2: {=INDEX(G$19:G$1048576,COUNTA(G$19:G$1048576))} -> 7 | H2: {=INDEX(H$19:H$1048576,COUNTA(H$19:H$1048576))} -> 28 | I2: {=INDEX(I$19:I$1048576,COUNTA(I$19:I$1048576))} -> 96 | J2: {=INDEX(J$19:J$1048576,COUNTA(J$19:J$1048576))} -> 32 | ... Y2: {=INDEX(Y$19:Y$1048576,COUNTA(Y$19:Y$1048576))} -> 53
B3: Quarterly change | C3: {=INDEX(C$19:C$1048576,COUNTA(C$19:C$1048576))-INDEX(C$19:C$1048576,COUNTA(C$19:C$1048576)-3)} -> -2 | D3: {=INDEX(D$19:D$1048576,COUNTA(D$19:D$1048576))/INDEX(D$19:D$1048576,COUNTA(D$19:D$1048576)-3)-1} -> 0 | E3: {=INDEX(E$19:E$1048576,COUNTA(E$19:E$1048576))/INDEX(E$19:E$1048576,COUNTA(E$19:E$1048576)-3)-1} -> 0.020408163 | F3: {=INDEX(F$19:F$1048576,COUNTA(F$19:F$1048576))/INDEX(F$19:F$1048576,COUNTA(F$19:F$1048576)-3)-1} -> -0.25 | G3: {=INDEX(G$19:G$1048576,COUNTA(G$19:G$1048576))/INDEX(G$19:G$1048576,COUNTA(G$19:G$1048576)-3)-1} -> -0.125 | H3: {=INDEX(H$19:H$1048576,COUNTA(H$19:H$1048576))/INDEX(H$19:H$1048576,COUNTA(H$19:H$1048576)-3)-1} -> -0.096774194 | I3: {=INDEX(I$19:I$1048576,COUNTA(I$19:I$1048576))/INDEX(I$19:I$1048576,COUNTA(I$19:I$1048576)-3)-1} -> 0.021276596 | J3: {=INDEX(J$19:J$1048576,COUNTA(J$19:J$1048576))/INDEX(J$19:J$1048576,COUNTA(J$19:J$1048576)-3)-1} -> 0.10344828 | K3: {=INDEX(K$19:K$1048576,COUNTA(K$19:K$1048576))/INDEX(K$19:K$1048576,COUNTA(K$19:K$1048576)-3)-1} -> -0.012820513 | ... Y3: {=INDEX(Y$19:Y$1048576,COUNTA(Y$19:Y$1048576))/INDEX(Y$19:Y$1048576,COUNTA(Y$19:Y$1048576)-3)-1} -> 0.081632653
B4: year on year change | C4: {=INDEX(C$19:C$1048576,COUNTA(C$19:C$1048576))-INDEX(C$19:C$1048576,COUNTA(C$19:C$1048576)-12)} -> -78 | D4: {=INDEX(D$19:D$1048576,COUNTA(D$19:D$1048576))/INDEX(D$19:D$1048576,COUNTA(D$19:D$1048576)-12)-1} -> -0.5 | E4: {=INDEX(E$19:E$1048576,COUNTA(E$19:E$1048576))/INDEX(E$19:E$1048576,COUNTA(E$19:E$1048576)-12)-1} -> -0.10714286 | F4: {=INDEX(F$19:F$1048576,COUNTA(F$19:F$1048576))/INDEX(F$19:F$1048576,COUNTA(F$19:F$1048576)-12)-1} -> -0.25 | G4: {=INDEX(G$19:G$1048576,COUNTA(G$19:G$1048576))/INDEX(G$19:G$1048576,COUNTA(G$19:G$1048576)-12)-1} -> 0 | H4: {=INDEX(H$19:H$1048576,COUNTA(H$19:H$1048576))/INDEX(H$19:H$1048576,COUNTA(H$19:H$1048576)-12)-1} -> -0.15151515 | I4: {=INDEX(I$19:I$1048576,COUNTA(I$19:I$1048576))/INDEX(I$19:I$1048576,COUNTA(I$19:I$1048576)-12)-1} -> -0.020408163 | J4: {=INDEX(J$19:J$1048576,COUNTA(J$19:J$1048576))/INDEX(J$19:J$1048576,COUNTA(J$19:J$1048576)-12)-1} -> -0.085714286 | K4: {=INDEX(K$19:K$1048576,COUNTA(K$19:K$1048576))/INDEX(K$19:K$1048576,COUNTA(K$19:K$1048576)-12)-1} -> -0.13483146 | ... Y4: {=INDEX(Y$19:Y$1048576,COUNTA(Y$19:Y$1048576))/INDEX(Y$19:Y$1048576,COUNTA(Y$19:Y$1048576)-12)-1} -> -0.086206897
B5: pre-pandemic trend (Dec-Feb) | C5: {=INDEX(C$19:C$1048576,COUNTA(C$19:C$1048576))-C$243} -> -90 | D5: {=INDEX(D$19:D$1048576,COUNTA(D$19:D$1048576))/D$243-1} -> -0.5 | E5: {=INDEX(E$19:E$1048576,COUNTA(E$19:E$1048576))/E$243-1} -> -0.10714286 | F5: {=INDEX(F$19:F$1048576,COUNTA(F$19:F$1048576))/F$243-1} -> 0 | G5: {=INDEX(G$19:G$1048576,COUNTA(G$19:G$1048576))/G$243-1} -> 1.3333333 | H5: {=INDEX(H$19:H$1048576,COUNTA(H$19:H$1048576))/H$243-1} -> 0 | I5: {=INDEX(I$19:I$1048576,COUNTA(I$19:I$1048576))/I$243-1} -> -0.27819549 | J5: {=INDEX(J$19:J$1048576,COUNTA(J$19:J$1048576))/J$243-1} -> -0.11111111 | K5: {=INDEX(K$19:K$1048576,COUNTA(K$19:K$1048576))/K$243-1} -> -0.16304348 | ... Y5: {=INDEX(Y$19:Y$1048576,COUNTA(Y$19:Y$1048576))/Y$243-1} -> -0.40449438
B6: Since 2010 election | C6: {=INDEX(C$19:C$1048576,COUNTA(C$19:C$1048576))-C$125} -> 262 | D6: {=INDEX(D$19:D$1048576,COUNTA(D$19:D$1048576))/D$125-1} -> 0 | E6: {=INDEX(E$19:E$1048576,COUNTA(E$19:E$1048576))/E$125-1} -> 0.92307692 | F6: {=INDEX(F$19:F$1048576,COUNTA(F$19:F$1048576))/F$125-1} -> 0 | G6: {=INDEX(G$19:G$1048576,COUNTA(G$19:G$1048576))/G$125-1} -> 6 | H6: {=INDEX(H$19:H$1048576,COUNTA(H$19:H$1048576))/H$125-1} -> 2.1111111 | I6: {=INDEX(I$19:I$1048576,COUNTA(I$19:I$1048576))/I$125-1} -> 0.078651685 | J6: {=INDEX(J$19:J$1048576,COUNTA(J$19:J$1048576))/J$125-1} -> 0.77777778 | K6: {=INDEX(K$19:K$1048576,COUNTA(K$19:K$1048576))/K$125-1} -> 0.67391304 | ... Y6: {=INDEX(Y$19:Y$1048576,COUNTA(Y$19:Y$1048576))/Y$125-1} -> -0.22058824
A8: Table 21: Vacancies 1 by industry (seasonally adjusted)
A9: Date of publication: | C9: 45881 | I9: Date of next publication: | J9: 45916
A10: Inquiries: Email: | C10: vacancy.survey@ons.gov.uk | I10: Telephone: | J10: 01633 455400
Y11: Source: ONS Vacancy Survey
A13: United Kingdom (thousands), seasonally adjusted
A14: SIC 2007 sections | C14: All vacancies1 | D14: Mining & quarrying | E14: Manu- facturing | F14: Electricity, gas, steam & air conditioning supply2 | G14: Water supply, sewerage, waste & remediation activities | H14: Construc-tion | I14: Wholesale & retail trade; repair of motor vehicles and motor cycles | J14: Transport & storage | K14: Accomoda-tion & food service activities | L14: Information & communica-tion | M14: Financial & insurance activities | N14: Real estate activities2 | O14: Professional scientific & technical activities | P14: Administra-tive & support service activities | Q14: Public admin & defence; compulsory social security | R14: Education | S14: Human health & social work activities | T14: Arts, entertainment & recreation | U14: Other service activities | V14: Total services | W14: Motor Trades | X14: Wholesale | Y14: Retail
C15: B-S | D15: B | E15: C | F15: D | G15: E | H15: F | I15: G | J15: H | K15: I | L15: J | M15: K | N15: L | O15: M | P15: N | Q15: O | R15: P | S15: Q | T15: R | U15: S | V15: G-S | W15: 45 | X15: 46 | Y15: 47
C16: AP2Y | D16: JP9H | E16: JP9I | F16: JP9J | G16: JP9K | H16: JP9L | I16: JP9M | J16: JP9N | K16: JP9O | L16: JP9P | M16: JP9Q | N16: JP9R | O16: JP9S | P16: JP9T | Q16: JP9U | R16: JP9V | S16: JP9W | T16: JP9X | U16: JP9Y | V16: JP9Z
A17: Levels (thousands)
A19: Apr-Jun 2001 | C19: 680 | D19: 2 | E19: 75 | F19: 2 | G19: 3 | H19: 31 | I19: 131 | J19: 29 | K19: 59 | L19: 50 | M19: 31 | N19: 8 | O19: 55 | P19: 41 | Q19: 17 | R19: 32 | S19: 79 | T19: 18 | U19: 19 | V19: 568 | W19: 11 | X19: 27 | Y19: 93
A20: May-Jul 2001 | C20: 674 | D20: 2 | E20: 75 | F20: 2 | G20: 3 | H20: 30 | I20: 130 | J20: 29 | K20: 60 | L20: 48 | M20: 30 | N20: 7 | O20: 53 | P20: 39 | Q20: 16 | R20: 32 | S20: 83 | T20: 17 | U20: 19 | V20: 563 | W20: 10 | X20: 27 | Y20: 93
A21: Jun-Aug 2001 | C21: 663 | D21: 2 | E21: 73 | F21: 3 | G21: 2 | H21: 29 | I21: 129 | J21: 30 | K21: 58 | L21: 47 | M21: 28 | N21: 6 | O21: 53 | P21: 39 | Q21: 16 | R21: 31 | S21: 84 | T21: 16 | U21: 18 | V21: 554 | W21: 9 | X21: 26 | Y21: 94
A22: Jul-Sep 2001 | C22: 663 | D22: 1 | E22: 72 | F22: 3 | G22: 3 | H22: 31 | I22: 122 | J22: 30 | K22: 63 | L22: 46 | M22: 29 | N22: 6 | O22: 53 | P22: 39 | Q22: 16 | R22: 32 | S22: 86 | T22: 16 | U22: 17 | V22: 554 | W22: 10 | X22: 26 | Y22: 86
A23: Aug-Oct 2001 | C23: 639 | D23: 1 | E23: 68 | F23: 3 | G23: 2 | H23: 29 | I23: 120 | J23: 29 | K23: 59 | L23: 44 | M23: 29 | N23: 6 | O23: 52 | P23: 38 | Q23: 15 | R23: 32 | S23: 83 | T23: 15 | U23: 16 | V23: 536 | W23: 10 | X23: 25 | Y23: 85
A24: Sep-Nov 2001 | C24: 626 | D24: 1 | E24: 66 | F24: 2 | G24: 2 | H24: 28 | I24: 121 | J24: 27 | K24: 59 | L24: 43 | M24: 30 | N24: 6 | O24: 49 | P24: 36 | Q24: 16 | R24: 32 | S24: 79 | T24: 14 | U24: 15 | V24: 526 | W24: 11 | X24: 24 | Y24: 86
A25: Oct-Dec 2001 | C25: 601 | D25: 1 | E25: 61 | F25: 2 | G25: 2 | H25: 25 | I25: 121 | J25: 25 | K25: 53 | L25: 40 | M25: 29 | N25: 5 | O25: 46 | P25: 34 | Q25: 16 | R25: 33 | S25: 81 | T25: 13 | U25: 15 | V25: 511 | W25: 10 | X25: 22 | Y25: 88
A26: Nov- Jan 2002 | C26: 606 | D26: 1 | E26: 66 | F26: 2 | G26: 2 | H26: 22 | I26: 126 | J26: 26 | K26: 54 | L26: 41 | M26: 28 | N26: 5 | O26: 44 | P26: 32 | Q26: 17 | R26: 33 | S26: 80 | T26: 13 | U26: 15 | V26: 513 | W26: 10 | X26: 26 | Y26: 91
A27: Dec-Feb 2002 | C27: 616 | D27: 1 | E27: 66 | F27: 2 | G27: 2 | H27: 25 | I27: 125 | J27: 27 | K27: 56 | L27: 42 | M27: 26 | N27: 5 | O27: 43 | P27: 32 | Q27: 16 | R27: 33 | S27: 86 | T27: 15 | U27: 16 | V27: 521 | W27: 10 | X27: 25 | Y27: 91
A28: Jan-Mar 2002 | C28: 619 | D28: 1 | E28: 65 | F28: 2 | G28: 2 | H28: 26 | I28: 127 | J28: 26 | K28: 56 | L28: 43 | M28: 26 | N28: 6 | O28: 43 | P28: 32 | Q28: 16 | R28: 35 | S28: 84 | T28: 14 | U28: 16 | V28: 523 | W28: 9 | X28: 24 | Y28: 93
A29: Feb-Apr 2002 | C29: 619 | D29: 1 | E29: 65 | F29: 2 | G29: 2 | H29: 26 | I29: 125 | J29: 29 | K29: 56 | L29: 44 | M29: 25 | N29: 6 | O29: 44 | P29: 32 | Q29: 15 | R29: 33 | S29: 82 | T29: 16 | U29: 17 | V29: 524 | W29: 9 | X29: 22 | Y29: 94
A30: Mar-May 2002 | C30: 613 | D30: 1 | E30: 64 | F30: 2 | G30: 2 | H30: 25 | I30: 120 | J30: 31 | K30: 55 | L30: 44 | M30: 25 | N30: 6 | O30: 44 | P30: 33 | Q30: 15 | R30: 33 | S30: 83 | T30: 14 | U30: 15 | V30: 519 | W30: 9 | X30: 22 | Y30: 88
... A299: Aug-Oct 2024 | C299: 822 | D299: 2 | E299: 57 | F299: 4 | G299: 6 | H299: 37 | I299: 104 | J299: 33 | K299: 91 | L299: 38 | M299: 35 | N299: 13 | O299: 85 | P299: 58 | Q299: 29 | R299: 53 | S299: 145 | T299: 18 | U299: 15 | V299: 716 | W299: 18 | X299: 27 | Y299: 59
A300: Sep-Nov 2024 | B300: (r) | C300: 807 | D300: 2 | E300: 56 | F300: 4 | G300: 7 | H300: 33 | I300: 98 | J300: 35 | K300: 89 | L300: 38 | M300: 34 | N300: 14 | O300: 81 | P300: 57 | Q300: 29 | R300: 53 | S300: 143 | T300: 17 | U300: 15 | V300: 704 | W300: 15 | X300: 26 | Y300: 58
A301: Oct-Dec 2024 | C301: 806 | D301: 2 | E301: 57 | F301: 4 | G301: 6 | H301: 35 | I301: 97 | J301: 37 | K301: 88 | L301: 38 | M301: 35 | N301: 14 | O301: 83 | P301: 58 | Q301: 30 | R301: 52 | S301: 139 | T301: 18 | U301: 15 | V301: 702 | W301: 15 | X301: 25 | Y301: 58
A302: Nov-Jan 2025 | C302: 804 | D302: 2 | E302: 58 | F302: 4 | G302: 6 | H302: 42 | I302: 94 | J302: 37 | K302: 85 | L302: 36 | M302: 35 | N302: 14 | O302: 83 | P302: 53 | Q302: 29 | R302: 52 | S302: 142 | T302: 19 | U302: 15 | V302: 692 | W302: 14 | X302: 23 | Y302: 58
A303: Dec-Feb 2025 | C303: 799 | D303: 2 | E303: 56 | F303: 4 | G303: 6 | H303: 43 | I303: 98 | J303: 35 | K303: 83 | L303: 36 | M303: 36 | N303: 13 | O303: 81 | P303: 53 | Q303: 28 | R303: 52 | S303: 138 | T303: 20 | U303: 16 | V303: 689 | W303: 15 | X303: 26 | Y303: 58
A304: Jan-Mar 2025 | C304: 783 | D304: 1 | E304: 53 | F304: 4 | G304: 7 | H304: 43 | I304: 102 | J304: 34 | K304: 82 | L304: 35 | M304: 34 | N304: 14 | O304: 79 | P304: 52 | Q304: 28 | R304: 48 | S304: 135 | T304: 18 | U304: 13 | V304: 676 | W304: 17 | X304: 27 | Y304: 59
A305: Feb-Apr 2025 | C305: 762 | D305: 1 | E305: 50 | F305: 4 | G305: 7 | H305: 33 | I305: 103 | J305: 33 | K305: 81 | L305: 36 | M305: 34 | N305: 13 | O305: 77 | P305: 52 | Q305: 29 | R305: 46 | S305: 134 | T305: 18 | U305: 12 | V305: 667 | W305: 18 | X305: 29 | Y305: 56
A306: Mar-May 2025 | C306: 739 | D306: 1 | E306: 49 | F306: 4 | G306: 7 | H306: 33 | I306: 99 | J306: 32 | K306: 78 | L306: 35 | M306: 33 | N306: 14 | O306: 74 | P306: 49 | Q306: 28 | R306: 44 | S306: 134 | T306: 16 | U306: 10 | V306: 645 | W306: 17 | X306: 28 | Y306: 54
A307: Apr-Jun 2025 | C307: 726 | D307: 1 | E307: 49 | F307: 4 | G307: 8 | H307: 30 | I307: 93 | J307: 32 | K307: 79 | L307: 35 | M307: 32 | N307: 13 | O307: 73 | P307: 49 | Q307: 28 | R307: 42 | S307: 136 | T307: 15 | U307: 11 | V307: 636 | W307: 14 | X307: 27 | Y307: 52
A308: May-Jul 2025 | C308: 722 | D308: 1 | E308: 47 | F308: 4 | G308: 8 | H308: 31 | I308: 93 | J308: 30 | K308: 75 | L308: 34 | M308: 33 | N308: 13 | O308: 74 | P308: 50 | Q308: 29 | R308: 45 | S308: 131 | T308: 15 | U308: 11 | V308: 632 | W308: 16 | X308: 27 | Y308: 50
A309: Jun-Aug 2025 | B309: (r) | C309: 731 | D309: 1 | E309: 49 | F309: 4 | G309: 8 | H309: 31 | I309: 94 | J309: 29 | K309: 78 | L309: 36 | M309: 33 | N309: 12 | O309: 77 | P309: 50 | Q309: 29 | R309: 47 | S309: 129 | T309: 14 | U309: 13 | V309: 639 | W309: 17 | X309: 28 | Y309: 49
A310: Jul-Sep 2025 | B310: (r) | C310: 725 | D310: 1 | E310: 47 | F310: 3 | G310: 7 | H310: 30 | I310: 96 | J310: 30 | K310: 75 | L310: 36 | M310: 33 | N310: 10 | O310: 76 | P310: 50 | Q310: 30 | R310: 49 | S310: 126 | T310: 14 | U310: 13 | V310: 636 | W310: 20 | X310: 26 | Y310: 50
A311: Aug-Oct 2025 | B311: (r) | C311: 725 | D311: 1 | E311: 48 | F311: 3 | G311: 8 | H311: 29 | I311: 92 | J311: 30 | K311: 77 | L311: 35 | M311: 33 | N311: 10 | O311: 79 | P311: 49 | Q311: 30 | R311: 49 | S311: 125 | T311: 15 | U311: 14 | V311: 636 | W311: 17 | X311: 23 | Y311: 51
A312: Sep-Nov 2025 | B312: (p) | C312: 729 | D312: 1 | E312: 50 | F312: 3 | G312: 7 | H312: 28 | I312: 96 | J312: 32 | K312: 77 | L312: 35 | M312: 34 | N312: 11 | O312: 78 | P312: 47 | Q312: 30 | R312: 50 | S312: 121 | T312: 16 | U312: 14 | V312: 639 | W312: 17 | X312: 25 | Y312: 53

Sheet 1 UK
A1: Worksheet 1: CLA01: Claimant Count, United Kingdom (not designated as an Accredited Official Statistic) [note 1, 2, 5]
A2: This worksheet contains one table. Some cells may refer to notes which can be found on the notes worksheet tab.
A3: Some shorthand may have been used in the spreadsheet, [w] - none recorded in survey, [c] - confidential, [z] - not applicable, [p] - provisional, [r] - revised
A4: Source: Claimant Count, Office for National Statistics
A5: Time period and dataset code row | B5: People: level seasonally adjusted (thousands) | C5: People: rate seasonally adjusted (%) [note 2] | D5: People: level not seasonally adjusted (thousands) | E5: People: rate not seasonally adjusted (%) [note 2] | F5: Men: level seasonally adjusted (thousands) | G5: Men: rate seasonally adjusted (%) [note 2] | H5: Men: level not seasonally adjusted (thousands) | I5: Men: rate not seasonally adjusted (%) [note 2] | J5: Women: level seasonally adjusted (thousands) | K5: Women: rate seasonally adjusted (%) [note 2] | L5: Women: level not seasonally adjusted (thousands) | M5: Women: rate not seasonally adjusted (%) [note 2] | N5: Notes
A6: Dataset identifier code | B6: BCJD | C6: BCJE | D6: BCJA | E6: BCJB | F6: DPAE | G6: DPAH | H6: DPAA | I6: DPAC | J6: DPAF | K6: DPAI | L6: DPAB | M6: DPAD
A7: January 1971 | B7: 533.6 | C7: 2 | D7: 682.8 | E7: 2.6 | F7: 462.2 | G7: 2.7 | H7: 591.5 | I7: 3.4 | J7: 71.4 | K7: 0.8 | L7: 91.3 | M7: 1 | N7: 5 week month
A8: February 1971 | B8: 552.3 | C8: 2.1 | D8: 690.9 | E8: 2.6 | F8: 477.1 | G8: 2.8 | H8: 596.5 | I8: 3.5 | J8: 75.2 | K8: 0.8 | L8: 94.4 | M8: 1
A9: March 1971 | B9: 573.5 | C9: 2.2 | D9: 705.3 | E9: 2.6 | F9: 494.2 | G9: 2.9 | H9: 607.4 | I9: 3.5 | J9: 79.3 | K9: 0.8 | L9: 97.9 | M9: 1
A10: April 1971 | B10: 599.1 | C10: 2.2 | D10: 714.7 | E10: 2.7 | F10: 519.3 | G10: 3 | H10: 618.9 | I10: 3.6 | J10: 79.8 | K10: 0.8 | L10: 95.8 | M10: 1
A11: May 1971 | B11: 641.7 | C11: 2.4 | D11: 720 | E11: 2.7 | F11: 554.9 | G11: 3.2 | H11: 623.8 | I11: 3.6 | J11: 86.8 | K11: 0.9 | L11: 96.2 | M11: 1 | N11: 5 week month
A12: June 1971 | B12: 655.2 | C12: 2.5 | D12: 696 | E12: 2.6 | F12: 567.1 | G12: 3.3 | H12: 606.4 | I12: 3.5 | J12: 88.1 | K12: 0.9 | L12: 89.6 | M12: 0.9
A13: July 1971 | B13: 662.9 | C13: 2.5 | D13: 711.7 | E13: 2.7 | F13: 574.8 | G13: 3.3 | H13: 618.9 | I13: 3.6 | J13: 88.1 | K13: 0.9 | L13: 92.7 | M13: 1
A14: August 1971 | B14: 664.1 | C14: 2.5 | D14: 759 | E14: 2.8 | F14: 578.3 | G14: 3.4 | H14: 653.8 | I14: 3.8 | J14: 85.8 | K14: 0.9 | L14: 105.2 | M14: 1.1 | N14: 5 week month
A15: September 1971 | B15: 684 | C15: 2.6 | D15: 783.6 | E15: 2.9 | F15: 591.6 | G15: 3.4 | H15: 670.7 | I15: 3.9 | J15: 92.4 | K15: 1 | L15: 112.9 | M15: 1.2
A16: October 1971 | B16: 715.8 | C16: 2.7 | D16: 815.6 | E16: 3.1 | F16: 616.9 | G16: 3.6 | H16: 694.9 | I16: 4 | J16: 98.9 | K16: 1 | L16: 120.7 | M16: 1.3 | N16: 5 week month
A17: November 1971 | B17: 747.6 | C17: 2.8 | D17: 857.4 | E17: 3.2 | F17: 644.3 | G17: 3.7 | H17: 730.7 | I17: 4.2 | J17: 103.3 | K17: 1.1 | L17: 126.7 | M17: 1.3
A18: December 1971 | B18: 757.7 | C18: 2.8 | D18: 878.5 | E18: 3.3 | F18: 652.2 | G18: 3.8 | H18: 752.8 | I18: 4.4 | J18: 105.5 | K18: 1.1 | L18: 125.8 | M18: 1.3
A19: January 1972 | B19: 754.1 | C19: 2.8 | D19: 936.1 | E19: 3.5 | F19: 651 | G19: 3.8 | H19: 802.5 | I19: 4.7 | J19: 103.1 | K19: 1.1 | L19: 133.6 | M19: 1.4 | N19: 5 week month
A20: February 1972 | B20: 768.5 | C20: 2.9 | D20: 936.6 | E20: 3.5 | F20: 663.3 | G20: 3.9 | H20: 802.8 | I20: 4.7 | J20: 105.2 | K20: 1.1 | L20: 133.8 | M20: 1.4
A21: March 1972 | B21: 779.6 | C21: 2.9 | D21: 938 | E21: 3.5 | F21: 671.3 | G21: 3.9 | H21: 802.5 | I21: 4.7 | J21: 108.3 | K21: 1.1 | L21: 135.5 | M21: 1.4
A22: April 1972 | B22: 775.9 | C22: 2.9 | D22: 918.4 | E22: 3.4 | F22: 666.2 | G22: 3.9 | H22: 784.1 | I22: 4.6 | J22: 109.7 | K22: 1.1 | L22: 134.3 | M22: 1.4 | N22: 5 week month
A23: May 1972 | B23: 745.8 | C23: 2.8 | D23: 840.9 | E23: 3.1 | F23: 637.8 | G23: 3.7 | H23: 718.3 | I23: 4.2 | J23: 108 | K23: 1.1 | L23: 122.6 | M23: 1.3
A24: June 1972 | B24: 722.4 | C24: 2.7 | D24: 777.6 | E24: 2.9 | F24: 617 | G24: 3.6 | H24: 666.3 | I24: 3.9 | J24: 105.4 | K24: 1.1 | L24: 111.4 | M24: 1.2
A25: July 1972 | B25: 709.8 | C25: 2.7 | D25: 776.2 | E25: 2.9 | F25: 607 | G25: 3.5 | H25: 662.3 | I25: 3.9 | J25: 102.8 | K25: 1.1 | L25: 113.9 | M25: 1.2 | N25: 5 week month
A26: August 1972 | B26: 692.7 | C26: 2.6 | D26: 808.5 | E26: 3 | F26: 593.6 | G26: 3.5 | H26: 681.8 | I26: 4 | J26: 99.1 | K26: 1 | L26: 126.7 | M26: 1.3
A27: September 1972 | B27: 696.7 | C27: 2.6 | D27: 809.5 | E27: 3 | F27: 596.8 | G27: 3.5 | H27: 683.9 | I27: 4 | J27: 99.9 | K27: 1 | L27: 125.6 | M27: 1.3 | N27: 5 week month
A28: October 1972 | B28: 680.7 | C28: 2.5 | D28: 783.5 | E28: 2.9 | F28: 580.2 | G28: 3.4 | H28: 659.7 | I28: 3.9 | J28: 100.5 | K28: 1 | L28: 123.7 | M28: 1.3
A29: November 1972 | B29: 666.2 | C29: 2.5 | D29: 771.4 | E29: 2.9 | F29: 565.6 | G29: 3.3 | H29: 648.1 | I29: 3.8 | J29: 100.6 | K29: 1 | L29: 123.3 | M29: 1.3
A30: December 1972 | B30: 639.4 | C30: 2.4 | D30: 751.6 | E30: 2.8 | F30: 540.6 | G30: 3.2 | H30: 634.4 | I30: 3.7 | J30: 98.8 | K30: 1 | L30: 117.2 | M30: 1.2 | N30: 5 week month
A31: January 1973 | B31: 603.7 | C31: 2.2 | D31: 776.6 | E31: 2.9 | F31: 510.7 | G31: 3 | H31: 654.9 | I31: 3.8 | J31: 93 | K31: 0.9 | L31: 121.7 | M31: 1.2
A32: February 1973 | B32: 574.3 | C32: 2.1 | D32: 725.4 | E32: 2.7 | F32: 484.7 | G32: 2.8 | H32: 611.9 | I32: 3.6 | J32: 89.6 | K32: 0.9 | L32: 113.5 | M32: 1.1
A33: March 1973 | B33: 560.3 | C33: 2.1 | D33: 693 | E33: 2.6 | F33: 471.7 | G33: 2.8 | H33: 585.2 | I33: 3.4 | J33: 88.6 | K33: 0.9 | L33: 107.8 | M33: 1.1
A34: April 1973 | B34: 547.2 | C34: 2 | D34: 656.8 | E34: 2.4 | F34: 459.1 | G34: 2.7 | H34: 554.5 | I34: 3.2 | J34: 88.1 | K34: 0.9 | L34: 102.3 | M34: 1 | N34: 5 week month
A35: May 1973 | B35: 537.6 | C35: 2 | D35: 601.8 | E35: 2.2 | F35: 452.3 | G35: 2.6 | H35: 512.2 | I35: 3 | J35: 85.3 | K35: 0.9 | L35: 89.7 | M35: 0.9
A36: June 1973 | B36: 530.2 | C36: 2 | D36: 556.8 | E36: 2.1 | F36: 445.5 | G36: 2.6 | H36: 476.1 | I36: 2.8 | J36: 84.7 | K36: 0.9 | L36: 80.7 | M36: 0.8 | N36: 5 week month
A37: July 1973 | B37: 506.3 | C37: 1.9 | D37: 541.5 | E37: 2 | F37: 426.5 | G37: 2.5 | H37: 461.1 | I37: 2.7 | J37: 79.8 | K37: 0.8 | L37: 80.5 | M37: 0.8
A38: August 1973 | B38: 486.8 | C38: 1.8 | D38: 552.9 | E38: 2 | F38: 412 | G38: 2.4 | H38: 467.5 | I38: 2.7 | J38: 74.8 | K38: 0.8 | L38: 85.4 | M38: 0.9
A39: September 1973 | B39: 469.4 | C39: 1.7 | D39: 530.9 | E39: 2 | F39: 397.4 | G39: 2.3 | H39: 449.7 | I39: 2.6 | J39: 72 | K39: 0.7 | L39: 81.2 | M39: 0.8 | N39: 5 week month
A40: October 1973 | B40: 456.5 | C40: 1.7 | D40: 513.1 | E40: 1.9 | F40: 387.2 | G40: 2.3 | H40: 435.6 | I40: 2.5 | J40: 69.3 | K40: 0.7 | L40: 77.5 | M40: 0.8
A41: November 1973 | B41: 441.2 | C41: 1.6 | D41: 503 | E41: 1.9 | F41: 375.3 | G41: 2.2 | H41: 428.4 | I41: 2.5 | J41: 65.9 | K41: 0.7 | L41: 74.6 | M41: 0.7
A42: December 1973 | B42: 422.6 | C42: 1.6 | D42: 495.5 | E42: 1.8 | F42: 358.4 | G42: 2.1 | H42: 425 | I42: 2.5 | J42: 64.2 | K42: 0.6 | L42: 70.5 | M42: 0.7 | N42: 5 week month
A43: January 1974 | B43: 468.7 | C43: 1.7 | D43: 611.5 | E43: 2.3 | F43: 399 | G43: 2.4 | H43: 521.7 | I43: 3.1 | J43: 69.7 | K43: 0.7 | L43: 89.9 | M43: 0.9
A44: February 1974 | B44: 486.6 | C44: 1.8 | D44: 612.5 | E44: 2.3 | F44: 414.6 | G44: 2.4 | H44: 523.6 | I44: 3.1 | J44: 72 | K44: 0.7 | L44: 88.9 | M44: 0.9 | N44: 5 week month
A45: March 1974 | B45: 494.8 | C45: 1.8 | D45: 601.5 | E45: 2.2 | F45: 422.1 | G45: 2.5 | H45: 517.1 | I45: 3 | J45: 72.7 | K45: 0.7 | L45: 84.4 | M45: 0.8
A46: April 1974 | B46: 497.4 | C46: 1.8 | D46: 588 | E46: 2.2 | F46: 420.8 | G46: 2.5 | H46: 502.6 | I46: 3 | J46: 76.6 | K46: 0.8 | L46: 85.4 | M46: 0.8
A47: May 1974 | B47: 494.3 | C47: 1.8 | D47: 545.8 | E47: 2 | F47: 418.7 | G47: 2.5 | H47: 469.9 | I47: 2.8 | J47: 75.6 | K47: 0.7 | L47: 75.9 | M47: 0.7
A48: June 1974 | B48: 508.9 | C48: 1.9 | D48: 527.5 | E48: 1.9 | F48: 429.5 | G48: 2.5 | H48: 455.6 | I48: 2.7 | J48: 79.4 | K48: 0.8 | L48: 71.9 | M48: 0.7 | N48: 5 week month
A49: July 1974 | B49: 510.8 | C49: 1.9 | D49: 552.1 | E49: 2 | F49: 434.5 | G49: 2.6 | H49: 472.3 | I49: 2.8 | J49: 76.3 | K49: 0.7 | L49: 79.8 | M49: 0.8
A50: August 1974 | B50: 530.2 | C50: 2 | D50: 626.8 | E50: 2.3 | F50: 451.1 | G50: 2.7 | H50: 524.7 | I50: 3.1 | J50: 79.1 | K50: 0.8 | L50: 102.1 | M50: 1
A51: September 1974 | B51: 534.3 | C51: 2 | D51: 621.7 | E51: 2.3 | F51: 453.9 | G51: 2.7 | H51: 520 | I51: 3.1 | J51: 80.4 | K51: 0.8 | L51: 101.6 | M51: 1 | N51: 5 week month
A52: October 1974 | B52: 539.7 | C52: 2 | D52: 615.4 | E52: 2.3 | F52: 461.7 | G52: 2.7 | H52: 520.2 | I52: 3.1 | J52: 78 | K52: 0.8 | L52: 95.3 | M52: 0.9
A53: November 1974 | B53: 544.9 | C53: 2 | D53: 629.8 | E53: 2.3 | F53: 465.7 | G53: 2.7 | H53: 531.3 | I53: 3.1 | J53: 79.2 | K53: 0.8 | L53: 98.4 | M53: 1 | N53: 5 week month
A54: December 1974 | B54: 558.5 | C54: 2.1 | D54: 661.1 | E54: 2.4 | F54: 476.3 | G54: 2.8 | H54: 559.1 | I54: 3.3 | J54: 82.2 | K54: 0.8 | L54: 101.9 | M54: 1
A55: January 1975 | B55: 587.8 | C55: 2.1 | D55: 771.8 | E55: 2.8 | F55: 499.8 | G55: 2.9 | H55: 635.1 | I55: 3.7 | J55: 88 | K55: 0.9 | L55: 136.7 | M55: 1.3
A56: February 1975 | B56: 609.1 | C56: 2.2 | D56: 791.8 | E56: 2.9 | F56: 515.1 | G56: 3 | H56: 650.2 | I56: 3.8 | J56: 94 | K56: 0.9 | L56: 141.6 | M56: 1.4 | N56: 5 week month
A57: March 1975 | B57: 641.7 | C57: 2.3 | D57: 802.6 | E57: 2.9 | F57: 539 | G57: 3.2 | H57: 657.7 | I57: 3.9 | J57: 102.7 | K57: 1 | L57: 144.9 | M57: 1.4
A58: April 1975 | B58: 683.4 | C58: 2.5 | D58: 845 | E58: 3.1 | F58: 573.5 | G58: 3.4 | H58: 690.2 | I58: 4 | J58: 109.9 | K58: 1.1 | L58: 154.9 | M58: 1.5
A59: May 1975 | B59: 734.4 | C59: 2.7 | D59: 850.3 | E59: 3.1 | F59: 612.2 | G59: 3.6 | H59: 693.9 | I59: 4.1 | J59: 122.2 | K59: 1.2 | L59: 156.4 | M59: 1.5
A60: June 1975 | B60: 774.2 | C60: 2.8 | D60: 866.1 | E60: 3.2 | F60: 644.5 | G60: 3.8 | H60: 706.6 | I60: 4.1 | J60: 129.7 | K60: 1.3 | L60: 159.4 | M60: 1.5 | N60: 5 week month
A61: July 1975 | B61: 818.7 | C61: 3 | D61: 990.1 | E61: 3.6 | F61: 681.3 | G61: 4 | H61: 784.5 | I61: 4.6 | J61: 137.4 | K61: 1.3 | L61: 205.6 | M61: 2
A62: August 1975 | B62: 845.8 | C62: 3.1 | D62: 1151 | E62: 4.2 | F62: 703.6 | G62: 4.1 | H62: 885.2 | I62: 5.2 | J62: 142.2 | K62: 1.4 | L62: 265.8 | M62: 2.6 | N62: 5 week month
A63: September 1975 | B63: 877 | C63: 3.2 | D63: 1145.5 | E63: 4.2 | F63: 727.2 | G63: 4.3 | H63: 883.3 | I63: 5.2 | J63: 149.8 | K63: 1.5 | L63: 262.2 | M63: 2.5
A64: October 1975 | B64: 934.4 | C64: 3.4 | D64: 1147.3 | E64: 4.2 | F64: 767.3 | G64: 4.5 | H64: 888.8 | I64: 5.2 | J64: 167.1 | K64: 1.6 | L64: 258.5 | M64: 2.5
A65: November 1975 | B65: 970.1 | C65: 3.5 | D65: 1168.9 | E65: 4.3 | F65: 794.7 | G65: 4.7 | H65: 909 | I65: 5.3 | J65: 175.4 | K65: 1.7 | L65: 259.9 | M65: 2.5 | N65: 5 week month
A66: December 1975 | B66: 997.1 | C66: 3.6 | D66: 1200.8 | E66: 4.4 | F66: 814.4 | G66: 4.8 | H66: 940.5 | I66: 5.5 | J66: 182.7 | K66: 1.8 | L66: 260.3 | M66: 2.5
A67: January 1976 | B67: 1022 | C67: 3.7 | D67: 1303.2 | E67: 4.7 | F67: 831.4 | G67: 4.9 | H67: 1017.4 | I67: 5.9 | J67: 190.6 | K67: 1.8 | L67: 285.8 | M67: 2.7
A68: February 1976 | B68: 1042.3 | C68: 3.8 | D68: 1304.4 | E68: 4.7 | F68: 843.3 | G68: 4.9 | H68: 1014.6 | I68: 5.9 | J68: 199 | K68: 1.9 | L68: 289.8 | M68: 2.8 | N68: 5 week month
A69: March 1976 | B69: 1055.6 | C69: 3.8 | D69: 1284.9 | E69: 4.7 | F69: 849.9 | G69: 5 | H69: 997.7 | I69: 5.8 | J69: 205.7 | K69: 2 | L69: 287.2 | M69: 2.8
A70: April 1976 | B70: 1070.1 | C70: 3.9 | D70: 1281.1 | E70: 4.6 | F70: 860.3 | G70: 5 | H70: 994.2 | I70: 5.8 | J70: 209.8 | K70: 2 | L70: 287 | M70: 2.8
A71: May 1976 | B71: 1088.2 | C71: 3.9 | D71: 1271.8 | E71: 4.6 | F71: 872.4 | G71: 5.1 | H71: 982.9 | I71: 5.7 | J71: 215.8 | K71: 2.1 | L71: 288.9 | M71: 2.8 | N71: 5 week month
A72: June 1976 | B72: 1085.5 | C72: 3.9 | D72: 1331.8 | E72: 4.8 | F72: 868.1 | G72: 5.1 | H72: 1009.4 | I72: 5.9 | J72: 217.4 | K72: 2.1 | L72: 322.4 | M72: 3.1
A73: July 1976 | B73: 1093 | C73: 4 | D73: 1463.5 | E73: 5.3 | F73: 869.6 | G73: 5.1 | H73: 1071.2 | I73: 6.3 | J73: 223.4 | K73: 2.1 | L73: 392.2 | M73: 3.8
A74: August 1976 | B74: 1107.6 | C74: 4 | D74: 1502 | E74: 5.5 | F74: 874.2 | G74: 5.1 | H74: 1092.2 | I74: 6.4 | J74: 233.4 | K74: 2.2 | L74: 408.8 | M74: 3.9 | N74: 5 week month
A75: September 1976 | B75: 1107 | C75: 4 | D75: 1455.7 | E75: 5.3 | F75: 871.5 | G75: 5.1 | H75: 1059.8 | I75: 6.2 | J75: 235.5 | K75: 2.3 | L75: 395.9 | M75: 3.8
A76: October 1976 | B76: 1097.8 | C76: 4 | D76: 1377.1 | E76: 5 | F76: 862.2 | G76: 5 | H76: 1010 | I76: 5.9 | J76: 235.6 | K76: 2.3 | L76: 367.1 | M76: 3.5 | N76: 5 week month
A77: November 1976 | B77: 1105.1 | C77: 4 | D77: 1366.5 | E77: 5 | F77: 864.7 | G77: 5 | H77: 1011.6 | I77: 5.9 | J77: 240.4 | K77: 2.3 | L77: 354.9 | M77: 3.4
A78: December 1976 | B78: 1108.8 | C78: 4 | D78: 1371 | E78: 5 | F78: 865.4 | G78: 5.1 | H78: 1019.5 | I78: 5.9 | J78: 243.4 | K78: 2.3 | L78: 351.5 | M78: 3.4
A79: January 1977 | B79: 1111.1 | C79: 4 | D79: 1448.2 | E79: 5.2 | F79: 863.6 | G79: 5.1 | H79: 1074.1 | I79: 6.3 | J79: 247.5 | K79: 2.3 | L79: 374.1 | M79: 3.5 | N79: 5 week month
A80: February 1977 | B80: 1107.4 | C80: 4 | D80: 1421.8 | E80: 5.1 | F80: 859.7 | G80: 5 | H80: 1055.5 | I80: 6.2 | J80: 247.7 | K80: 2.3 | L80: 366.3 | M80: 3.5
A81: March 1977 | B81: 1107.9 | C81: 4 | D81: 1383.5 | E81: 5 | F81: 858.9 | G81: 5 | H81: 1028.5 | I81: 6 | J81: 249 | K81: 2.4 | L81: 355 | M81: 3.4
A82: April 1977 | B82: 1117.6 | C82: 4 | D82: 1392.3 | E82: 5 | F82: 865.7 | G82: 5.1 | H82: 1032.4 | I82: 6 | J82: 251.9 | K82: 2.4 | L82: 359.9 | M82: 3.4 | N82: 5 week month
A83: May 1977 | B83: 1119.7 | C83: 4 | D83: 1341.7 | E83: 4.8 | F83: 866 | G83: 5.1 | H83: 994.3 | I83: 5.8 | J83: 253.7 | K83: 2.4 | L83: 347.4 | M83: 3.3
A84: June 1977 | B84: 1149.3 | C84: 4.2 | D84: 1450.1 | E84: 5.2 | F84: 886.7 | G84: 5.2 | H84: 1050.8 | I84: 6.2 | J84: 262.6 | K84: 2.5 | L84: 399.3 | M84: 3.8
A85: July 1977 | B85: 1169.8 | C85: 4.2 | D85: 1622.4 | E85: 5.9 | F85: 896 | G85: 5.2 | H85: 1132.7 | I85: 6.6 | J85: 273.8 | K85: 2.6 | L85: 489.6 | M85: 4.6 | N85: 5 week month
A86: August 1977 | B86: 1172.7 | C86: 4.2 | D86: 1635.8 | E86: 5.9 | F86: 898.3 | G86: 5.3 | H86: 1143.5 | I86: 6.7 | J86: 274.4 | K86: 2.6 | L86: 492.3 | M86: 4.7
A87: September 1977 | B87: 1193.6 | C87: 4.3 | D87: 1609.1 | E87: 5.8 | F87: 910.3 | G87: 5.3 | H87: 1124.3 | I87: 6.6 | J87: 283.3 | K87: 2.7 | L87: 484.8 | M87: 4.6
A88: October 1977 | B88: 1188.1 | C88: 4.3 | D88: 1518.3 | E88: 5.5 | F88: 905.1 | G88: 5.3 | H88: 1070.8 | I88: 6.3 | J88: 283 | K88: 2.7 | L88: 447.6 | M88: 4.2 | N88: 5 week month
A89: November 1977 | B89: 1186.1 | C89: 4.3 | D89: 1499.1 | E89: 5.4 | F89: 900.4 | G89: 5.3 | H89: 1063.2 | I89: 6.2 | J89: 285.7 | K89: 2.7 | L89: 435.9 | M89: 4.1
A90: December 1977 | B90: 1181.5 | C90: 4.3 | D90: 1480.8 | E90: 5.4 | F90: 894.9 | G90: 5.2 | H90: 1060.7 | I90: 6.2 | J90: 286.6 | K90: 2.7 | L90: 420.1 | M90: 4
A91: January 1978 | B91: 1167.5 | C91: 4.2 | D91: 1548.5 | E91: 5.6 | F91: 885.3 | G91: 5.2 | H91: 1114.8 | I91: 6.6 | J91: 282.2 | K91: 2.6 | L91: 433.7 | M91: 4 | N91: 5 week month
A92: February 1978 | B92: 1150.9 | C92: 4.1 | D92: 1508.7 | E92: 5.4 | F92: 871.1 | G92: 5.1 | H92: 1089.6 | I92: 6.4 | J92: 279.8 | K92: 2.6 | L92: 419.1 | M92: 3.9
A93: March 1978 | B93: 1148.1 | C93: 4.1 | D93: 1461 | E93: 5.3 | F93: 868 | G93: 5.1 | H93: 1058.4 | I93: 6.2 | J93: 280.1 | K93: 2.6 | L93: 402.6 | M93: 3.7
A94: April 1978 | B94: 1147.3 | C94: 4.1 | D94: 1451.8 | E94: 5.2 | F94: 862.3 | G94: 5.1 | H94: 1045.4 | I94: 6.2 | J94: 285 | K94: 2.6 | L94: 406.4 | M94: 3.8 | N94: 5 week month
A95: May 1978 | B95: 1140.6 | C95: 4.1 | D95: 1386.8 | E95: 5 | F95: 856.5 | G95: 5 | H95: 1001.1 | I95: 5.9 | J95: 284.1 | K95: 2.6 | L95: 385.7 | M95: 3.6
A96: June 1978 | B96: 1140.3 | C96: 4.1 | D96: 1446.1 | E96: 5.2 | F96: 852.5 | G96: 5 | H96: 1022.9 | I96: 6 | J96: 287.8 | K96: 2.7 | L96: 423.1 | M96: 3.9
A97: July 1978 | B97: 1134.6 | C97: 4.1 | D97: 1585.8 | E97: 5.7 | F97: 846.6 | G97: 5 | H97: 1087.3 | I97: 6.4 | J97: 288 | K97: 2.7 | L97: 498.5 | M97: 4.6 | N97: 5 week month
A98: August 1978 | B98: 1144.6 | C98: 4.1 | D98: 1499.6 | E98: 5.4 | F98: 849.2 | G98: 5 | H98: 1059.6 | I98: 6.2 | J98: 295.4 | K98: 2.7 | L98: 440 | M98: 4.1
A99: September 1978 | B99: 1130.2 | C99: 4.1 | D99: 1418.4 | E99: 5.1 | F99: 838.7 | G99: 4.9 | H99: 1007.2 | I99: 5.9 | J99: 291.5 | K99: 2.7 | L99: 411.2 | M99: 3.8 | N99: 5 week month
A100: October 1978 | B100: 1115.4 | C100: 4 | D100: 1335.8 | E100: 4.8 | F100: 825.6 | G100: 4.9 | H100: 958.7 | I100: 5.6 | J100: 289.8 | K100: 2.7 | L100: 377.1 | M100: 3.5
...

Sheet AWE Real_CPI
B1: Total Pay Real AWE (2015 £) | C1: Total Pay Real AWE (%) | D1: Regular Pay Real AWE (2015 £) | E1: Regular Pay Real AWE (%)
A2: Current (3mo avg) | B2: =AVERAGE(OFFSET(INDEX(B$17:B$1048576,COUNTA(B$17:B$1048576)),-2,0,3,1)) -> 528.02564 | D2: =AVERAGE(OFFSET(INDEX(F$17:F$1048576,COUNTA(F$17:F$1048576)),-2,0,3,1)) -> 492.85039
A3: Change on quarter (3mo avg) | B3: =(AVERAGE(OFFSET(INDEX(B$17:B$1048576,COUNTA(B$17:B$1048576)),-2,0,3,1))-AVERAGE(OFFSET(INDEX(B$17:B$1048576,COUNTA(B$17:B$1048576)),-5,0,3,1)))*52 -> 142.57626 | D3: =(AVERAGE(OFFSET(INDEX(F$17:F$1048576,COUNTA(F$17:F$1048576)),-2,0,3,1))-AVERAGE(OFFSET(INDEX(F$17:F$1048576,COUNTA(F$17:F$1048576)),-5,0,3,1)))*52 -> 83.657395
A4: Change year on year (3mo avg) | B4: =(AVERAGE(OFFSET(INDEX(B$17:B$1048576,COUNTA(B$17:B$1048576)),-2,0,3,1))-AVERAGE(OFFSET(INDEX(B$17:B$1048576,COUNTA(B$17:B$1048576)),-14,0,3,1)))*52 -> 263.19994 | C4: {=INDEX(E$31:E$1048576,COUNTA(E$31:E$1048576))} -> 0.96785559 | D4: =(AVERAGE(OFFSET(INDEX(F$17:F$1048576,COUNTA(F$17:F$1048576)),-2,0,3,1))-AVERAGE(OFFSET(INDEX(F$17:F$1048576,COUNTA(F$17:F$1048576)),-14,0,3,1)))*52 -> 218.19933 | E4: {=INDEX(I$31:I$1048576,COUNTA(I$31:I$1048576))} -> 0.85871371
A5: Change since Covid-19 (2019 average) | B5: =(AVERAGE(OFFSET(INDEX($B$17:$B$1048576,COUNTA($B$17:$B$1048576)),-2,0,3,1))-AVERAGE($B$256:$B$258))*52 -> 1529.8116 | C5: =(AVERAGE(OFFSET(INDEX($B$17:$B$1048576,COUNTA($B$17:$B$1048576)),-2,0,3,1))/AVERAGE($B$256:$B$258))-1 -> 0.059003387 | D5: =(AVERAGE(OFFSET(INDEX(F$17:F$1048576,COUNTA(F$17:F$1048576)),-2,0,3,1))-AVERAGE($F$256:$F$258))*52 -> 1118.4456 | E5: =(AVERAGE(OFFSET(INDEX(F$17:F$1048576,COUNTA(F$17:F$1048576)),-2,0,3,1))/AVERAGE($F$256:$F$258))-1 -> 0.045632633
A6: Change since 2010 | B6: =(AVERAGE(OFFSET(INDEX($B$17:$B$1048576,COUNTA($B$17:$B$1048576)),-2,0,3,1))-AVERAGE($B$138:$B$140))*52 -> 1404.219 | C6: =(AVERAGE(OFFSET(INDEX($B$17:$B$1048576,COUNTA($B$17:$B$1048576)),-2,0,3,1))/AVERAGE($B$138:$B$140))-1 -> 0.053898315 | D6: =(AVERAGE(OFFSET(INDEX(F$17:F$1048576,COUNTA(F$17:F$1048576)),-2,0,3,1))-AVERAGE($F$138:$F$140))*52 -> 1127.5591 | E6: =(AVERAGE(OFFSET(INDEX(F$17:F$1048576,COUNTA(F$17:F$1048576)),-2,0,3,1))/AVERAGE($F$138:$F$140))-1 -> 0.046021576
A7: Change since financial crisis | B7: =(AVERAGE(OFFSET(INDEX($B$17:$B$1048576,COUNTA($B$17:$B$1048576)),-2,0,3,1))-AVERAGE($B$110:$B$112))*52 -> 641.89474 | C7: =(AVERAGE(OFFSET(INDEX($B$17:$B$1048576,COUNTA($B$17:$B$1048576)),-2,0,3,1))/AVERAGE($B$110:$B$112))-1 -> 0.023937507 | D7: =(AVERAGE(OFFSET(INDEX(F$17:F$1048576,COUNTA(F$17:F$1048576)),-2,0,3,1))-AVERAGE($F$110:$F$112))*52 -> 643.78509 | E7: =(AVERAGE(OFFSET(INDEX(F$17:F$1048576,COUNTA(F$17:F$1048576)),-2,0,3,1))/AVERAGE($F$110:$F$112))-1 -> 0.025767446
A9: Real Average Weekly Earnings using CPI (seasonally adjusted) | K9: Source: Monthly Wages and Salaries Survey
A10: Date of this publication: 12 August 2025 | G10: Date of next publication: 16 September 2025
A11: Inquiries: Email: | C11: earnings@ons.gov.uk | G11: Tel: 01633 456120
B13: Total pay, seasonally adjusted | F13: Regular Pay, seasonally adjusted
B14: Real AWE (2015 £) | C14: Real AWE (Index numbers 2015=100) | D14: % changes year on year | F14: Real AWE (2015 £) | G14: Real AWE (Index numbers 2015=100) | H14: % changes year on year
D15: Single month | E15: 3 month average | H15: Single month | I15: 3 month average
A17: 36526 | B17: 423.95274 | C17: 87.775943 | F17: 406.33163 | G17: 89.529611
A18: 36557 | B18: 414.27365 | C18: 85.771967 | F18: 405.80864 | G18: 89.414377
A19: 36586 | B19: 429.2198 | C19: 88.866446 | F19: 405.02115 | G19: 89.240865
A20: 36617 | B20: 426.46638 | C20: 88.296372 | F20: 404.98348 | G20: 89.232564
A21: 36647 | B21: 430.20738 | C21: 89.070916 | F21: 407.14371 | G21: 89.708541
A22: 36678 | B22: 428.76137 | C22: 88.771532 | F22: 406.55267 | G22: 89.578315
A23: 36708 | B23: 431.73994 | C23: 89.388221 | F23: 407.75068 | G23: 89.84228
A24: 36739 | B24: 434.52301 | C24: 89.964432 | F24: 410.10059 | G24: 90.360049
A25: 36770 | B25: 435.5864 | C25: 90.184597 | F25: 411.13102 | G25: 90.587091
A26: 36800 | B26: 435.9532 | C26: 90.260541 | F26: 412.51459 | G26: 90.89194
A27: 36831 | B27: 437.14814 | C27: 90.507943 | F27: 413.13673 | G27: 91.02902
A28: 36861 | B28: 443.05599 | C28: 91.731115 | F28: 415.15894 | G28: 91.474587
A29: 36892 | B29: 442.96724 | C29: 91.712741 | D29: 4.4850538 | F29: 416.82958 | G29: 91.842691 | H29: 2.583592
A30: 36923 | B30: 446.10765 | C30: 92.362937 | D30: 7.6842932 | F30: 417.68342 | G30: 92.030822 | H30: 2.9262008
A31: 36951 | B31: 444.84303 | C31: 92.101107 | D31: 3.6399132 | E31: 5.2445413 | F31: 419.02188 | G31: 92.325733 | H31: 3.4567887 | I31: 2.9883836
A32: 36982 | B32: 446.02187 | C32: 92.345176 | D32: 4.585471 | E32: 5.2767592 | F32: 422.16823 | G32: 93.018988 | H32: 4.2433206 | I32: 3.5416827
A33: 37012 | B33: 444.23317 | C33: 91.974842 | D33: 3.2602404 | E33: 3.8264843 | F33: 419.86247 | G33: 92.510947 | H33: 3.1239011 | I33: 3.6071396
A34: 37043 | B34: 445.7564 | C34: 92.290213 | D34: 3.9637498 | E34: 3.9345677 | F34: 419.2915 | G34: 92.38514 | H34: 3.1333758 | I34: 3.4990598
A35: 37073 | B35: 446.12471 | C35: 92.366469 | D35: 3.3318124 | E35: 3.5178804 | F35: 423.22031 | G35: 93.2508 | H35: 3.7938939 | I35: 3.3507157
A36: 37104 | B36: 448.31192 | C36: 92.819314 | D36: 3.1733449 | E36: 3.4878655 | F36: 424.66446 | G36: 93.568999 | H36: 3.5512929 | I36: 3.4933181
A37: 37135 | B37: 448.97588 | C37: 92.956779 | D37: 3.0738974 | E37: 3.1926243 | F37: 425.12795 | G37: 93.671123 | H37: 3.404494 | I37: 3.5826743
A38: 37165 | B38: 451.53684 | C38: 93.487007 | D38: 3.5746136 | E38: 3.2741183 | F38: 427.47003 | G38: 94.187167 | H38: 3.6254337 | I38: 3.5271636
A39: 37196 | B39: 452.8341 | C39: 93.755594 | D39: 3.5882498 | E39: 3.4125091 | F39: 429.46854 | G39: 94.627512 | H39: 3.9531254 | I39: 3.6614516
A40: 37226 | B40: 453.25757 | C40: 93.843269 | D40: 2.3025485 | E40: 3.1509294 | F40: 429.20342 | G40: 94.569096 | H40: 3.3829166 | I40: 3.653398
A41: 37257 | B41: 451.45866 | C41: 93.47082 | D41: 1.916941 | E41: 2.5982248 | F41: 429.13111 | G41: 94.553163 | H41: 2.9512122 | I41: 3.4275925
A42: 37288 | B42: 452.46082 | C42: 93.678308 | D42: 1.4241332 | E42: 1.8801581 | F42: 433.15275 | G42: 95.439276 | H42: 3.7036011 | I42: 3.3461049
... A326: 45931 | B326: 529.53143 | C326: 109.63515 | D326: 0.78208912 | E326: 0.96785559 | F326: 493.70363 | G326: 108.78083 | H326: 0.83390262 | I326: 0.85871371
A327: 1. These estimates of real earnings are calculated by deflating the nominal earnings estimates by the Consumer Prices Index, however our recommended measure of consumer price inflation is the Consumer Prices index including owner occupiers' housing costs (CPIH).
A328: 2. Estimates of Total pay include bonuses but exclude arrears of pay; Regular pay exclude bonuses and arrears of pay.
A329: 3. The seasonal adjustment models for real awe are based on the full data series, from 2000 onwards

Sheet Redundancies >>>

Sheet 1a
B1: North East | C1: North West | D1: Yorkshire and The Humber | E1: East Midlands | F1: West Midlands | G1: East of England | H1: London | I1: South East | J1: South West | K1: Wales | L1: Scotland | M1: GB
A2: Current | B2: =AVERAGE(OFFSET(INDEX(B$13:B$1048576,COUNTA(B$13:B$1048576)),-2,0,3,1)) -> 772.66667 | C2: =AVERAGE(OFFSET(INDEX(C$13:C$1048576,COUNTA(C$13:C$1048576)),-2,0,3,1)) -> 2961 | D2: =AVERAGE(OFFSET(INDEX(D$13:D$1048576,COUNTA(D$13:D$1048576)),-2,0,3,1)) -> 1541.6667 | E2: =AVERAGE(OFFSET(INDEX(E$13:E$1048576,COUNTA(E$13:E$1048576)),-2,0,3,1)) -> 1310.6667 | F2: =AVERAGE(OFFSET(INDEX(F$13:F$1048576,COUNTA(F$13:F$1048576)),-2,0,3,1)) -> 2208.6667 | G2: =AVERAGE(OFFSET(INDEX(G$13:G$1048576,COUNTA(G$13:G$1048576)),-2,0,3,1)) -> 2120.6667 | H2: =AVERAGE(OFFSET(INDEX(H$13:H$1048576,COUNTA(H$13:H$1048576)),-2,0,3,1)) -> 6102.3333 | I2: =AVERAGE(OFFSET(INDEX(I$13:I$1048576,COUNTA(I$13:I$1048576)),-2,0,3,1)) -> 3171.6667 | ... M2: =AVERAGE(OFFSET(INDEX(M$13:M$1048576,COUNTA(M$13:M$1048576)),-2,0,3,1)) -> 25937.667
A3: Average since start of 2023 | B3: =AVERAGE(INDEX(B$13:B$1048576,MATCH(44927,$A$13:$A$1048576,0)): INDEX(B$13:B$1048576,COUNTA(B$13:B$1048576))) -> 663.97143 | C3: =AVERAGE(INDEX(C$13:C$1048576,MATCH(44927,$A$13:$A$1048576,0)): INDEX(C$13:C$1048576,COUNTA(C$13:C$1048576))) -> 1917.9143 | D3: =AVERAGE(INDEX(D$13:D$1048576,MATCH(44927,$A$13:$A$1048576,0)): INDEX(D$13:D$1048576,COUNTA(D$13:D$1048576))) -> 2006.3143 | E3: =AVERAGE(INDEX(E$13:E$1048576,MATCH(44927,$A$13:$A$1048576,0)): INDEX(E$13:E$1048576,COUNTA(E$13:E$1048576))) -> 1658.5882 | F3: =AVERAGE(INDEX(F$13:F$1048576,MATCH(44927,$A$13:$A$1048576,0)): INDEX(F$13:F$1048576,COUNTA(F$13:F$1048576))) -> 1935.3429 | G3: =AVERAGE(INDEX(G$13:G$1048576,MATCH(44927,$A$13:$A$1048576,0)): INDEX(G$13:G$1048576,COUNTA(G$13:G$1048576))) -> 1755.5714 | H3: =AVERAGE(INDEX(H$13:H$1048576,MATCH(44927,$A$13:$A$1048576,0)): INDEX(H$13:H$1048576,COUNTA(H$13:H$1048576))) -> 5313 | I3: =AVERAGE(INDEX(I$13:I$1048576,MATCH(44927,$A$13:$A$1048576,0)): INDEX(I$13:I$1048576,COUNTA(I$13:I$1048576))) -> 2678.7714 | ... M3: =AVERAGE(INDEX(M$13:M$1048576,MATCH(44927,$A$13:$A$1048576,0)): INDEX(M$13:M$1048576,COUNTA(M$13:M$1048576))) -> 22746.514
A4: Average pre-covid (April 2019-February 2020) | B4: =AVERAGE(B$13:B$23) -> 918.1 | C4: =AVERAGE(C$13:C$23) -> 2070.6364 | D4: =AVERAGE(D$13:D$23) -> 2639.6 | E4: =AVERAGE(E$13:E$23) -> 1014.9091 | F4: =AVERAGE(F$13:F$23) -> 1738.2727 | G4: =AVERAGE(G$13:G$23) -> 2198.4 | H4: =AVERAGE(H$13:H$23) -> 3772.4545 | I4: =AVERAGE(I$13:I$23) -> 2414.6364 | ... M4: =AVERAGE(M$13:M$23) -> 27565.273
A5: Change on month | B5: =(AVERAGE(OFFSET(INDEX(B$13:B$1048576,COUNTA(B$13:B$1048576)),-2,0,3,1))/AVERAGE(OFFSET(INDEX(B$13:B$1048576,COUNTA(B$13:B$1048576)),-3,0,3,1)))-1 -> 0.50617284 | C5: =(AVERAGE(OFFSET(INDEX(C$13:C$1048576,COUNTA(C$13:C$1048576)),-2,0,3,1))/AVERAGE(OFFSET(INDEX(C$13:C$1048576,COUNTA(C$13:C$1048576)),-3,0,3,1)))-1 -> 0.14016173 | D5: =(AVERAGE(OFFSET(INDEX(D$13:D$1048576,COUNTA(D$13:D$1048576)),-2,0,3,1))/AVERAGE(OFFSET(INDEX(D$13:D$1048576,COUNTA(D$13:D$1048576)),-3,0,3,1)))-1 -> -0.089028954 | E5: =(AVERAGE(OFFSET(INDEX(E$13:E$1048576,COUNTA(E$13:E$1048576)),-2,0,3,1))/AVERAGE(OFFSET(INDEX(E$13:E$1048576,COUNTA(E$13:E$1048576)),-3,0,3,1)))-1 -> 0.010796915 | F5: =(AVERAGE(OFFSET(INDEX(F$13:F$1048576,COUNTA(F$13:F$1048576)),-2,0,3,1))/AVERAGE(OFFSET(INDEX(F$13:F$1048576,COUNTA(F$13:F$1048576)),-3,0,3,1)))-1 -> -0.076901644 | G5: =(AVERAGE(OFFSET(INDEX(G$13:G$1048576,COUNTA(G$13:G$1048576)),-2,0,3,1))/AVERAGE(OFFSET(INDEX(G$13:G$1048576,COUNTA(G$13:G$1048576)),-3,0,3,1)))-1 -> 0.56084396 | H5: =(AVERAGE(OFFSET(INDEX(H$13:H$1048576,COUNTA(H$13:H$1048576)),-2,0,3,1))/AVERAGE(OFFSET(INDEX(H$13:H$1048576,COUNTA(H$13:H$1048576)),-3,0,3,1)))-1 -> 0.021710012 | I5: =(AVERAGE(OFFSET(INDEX(I$13:I$1048576,COUNTA(I$13:I$1048576)),-2,0,3,1))/AVERAGE(OFFSET(INDEX(I$13:I$1048576,COUNTA(I$13:I$1048576)),-3,0,3,1)))-1 -> 0.52728732 | ... M5: =(AVERAGE(OFFSET(INDEX(M$13:M$1048576,COUNTA(M$13:M$1048576)),-2,0,3,1))/AVERAGE(OFFSET(INDEX(M$13:M$1048576,COUNTA(M$13:M$1048576)),-3,0,3,1)))-1 -> 0.1526315
A6: Change on quarter | B6: =(AVERAGE(OFFSET(INDEX(B$13:B$1048576,COUNTA(B$13:B$1048576)),-2,0,3,1))/AVERAGE(OFFSET(INDEX(B$13:B$1048576,COUNTA(B$13:B$1048576)),-5,0,3,1)))-1 -> 0.25229606 | C6: =(AVERAGE(OFFSET(INDEX(C$13:C$1048576,COUNTA(C$13:C$1048576)),-2,0,3,1))/AVERAGE(OFFSET(INDEX(C$13:C$1048576,COUNTA(C$13:C$1048576)),-5,0,3,1)))-1 -> 0.44368601 | D6: =(AVERAGE(OFFSET(INDEX(D$13:D$1048576,COUNTA(D$13:D$1048576)),-2,0,3,1))/AVERAGE(OFFSET(INDEX(D$13:D$1048576,COUNTA(D$13:D$1048576)),-5,0,3,1)))-1 -> -0.30061999 | E6: =(AVERAGE(OFFSET(INDEX(E$13:E$1048576,COUNTA(E$13:E$1048576)),-2,0,3,1))/AVERAGE(OFFSET(INDEX(E$13:E$1048576,COUNTA(E$13:E$1048576)),-5,0,3,1)))-1 -> -0.14818024 | F6: =(AVERAGE(OFFSET(INDEX(F$13:F$1048576,COUNTA(F$13:F$1048576)),-2,0,3,1))/AVERAGE(OFFSET(INDEX(F$13:F$1048576,COUNTA(F$13:F$1048576)),-5,0,3,1)))-1 -> -0.18247995 | G6: =(AVERAGE(OFFSET(INDEX(G$13:G$1048576,COUNTA(G$13:G$1048576)),-2,0,3,1))/AVERAGE(OFFSET(INDEX(G$13:G$1048576,COUNTA(G$13:G$1048576)),-5,0,3,1)))-1 -> 0.37023476 | H6: =(AVERAGE(OFFSET(INDEX(H$13:H$1048576,COUNTA(H$13:H$1048576)),-2,0,3,1))/AVERAGE(OFFSET(INDEX(H$13:H$1048576,COUNTA(H$13:H$1048576)),-5,0,3,1)))-1 -> 0.4189273 | I6: =(AVERAGE(OFFSET(INDEX(I$13:I$1048576,COUNTA(I$13:I$1048576)),-2,0,3,1))/AVERAGE(OFFSET(INDEX(I$13:I$1048576,COUNTA(I$13:I$1048576)),-5,0,3,1)))-1 -> 0.094810724 | ... M6: =(AVERAGE(OFFSET(INDEX(M$13:M$1048576,COUNTA(M$13:M$1048576)),-2,0,3,1))/AVERAGE(OFFSET(INDEX(M$13:M$1048576,COUNTA(M$13:M$1048576)),-5,0,3,1)))-1 -> 0.12705494
A7: Change on year | B7: =(AVERAGE(OFFSET(INDEX(B$13:B$1048576,COUNTA(B$13:B$1048576)),-2,0,3,1))/AVERAGE(OFFSET(INDEX(B$13:B$1048576,COUNTA(B$13:B$1048576)),-14,0,3,1)))-1 -> 0.32532876 | C7: =(AVERAGE(OFFSET(INDEX(C$13:C$1048576,COUNTA(C$13:C$1048576)),-2,0,3,1))/AVERAGE(OFFSET(INDEX(C$13:C$1048576,COUNTA(C$13:C$1048576)),-14,0,3,1)))-1 -> 0.71288083 | D7: =(AVERAGE(OFFSET(INDEX(D$13:D$1048576,COUNTA(D$13:D$1048576)),-2,0,3,1))/AVERAGE(OFFSET(INDEX(D$13:D$1048576,COUNTA(D$13:D$1048576)),-14,0,3,1)))-1 -> 0.18864045 | E7: =(AVERAGE(OFFSET(INDEX(E$13:E$1048576,COUNTA(E$13:E$1048576)),-2,0,3,1))/AVERAGE(OFFSET(INDEX(E$13:E$1048576,COUNTA(E$13:E$1048576)),-14,0,3,1)))-1 -> 0.19804997 | F7: =(AVERAGE(OFFSET(INDEX(F$13:F$1048576,COUNTA(F$13:F$1048576)),-2,0,3,1))/AVERAGE(OFFSET(INDEX(F$13:F$1048576,COUNTA(F$13:F$1048576)),-14,0,3,1)))-1 -> 0.23527218 | G7: =(AVERAGE(OFFSET(INDEX(G$13:G$1048576,COUNTA(G$13:G$1048576)),-2,0,3,1))/AVERAGE(OFFSET(INDEX(G$13:G$1048576,COUNTA(G$13:G$1048576)),-14,0,3,1)))-1 -> 0.28421478 | H7: =(AVERAGE(OFFSET(INDEX(H$13:H$1048576,COUNTA(H$13:H$1048576)),-2,0,3,1))/AVERAGE(OFFSET(INDEX(H$13:H$1048576,COUNTA(H$13:H$1048576)),-14,0,3,1)))-1 -> 0.33413497 | I7: =(AVERAGE(OFFSET(INDEX(I$13:I$1048576,COUNTA(I$13:I$1048576)),-2,0,3,1))/AVERAGE(OFFSET(INDEX(I$13:I$1048576,COUNTA(I$13:I$1048576)),-14,0,3,1)))-1 -> -0.27244227 | ... M7: =(AVERAGE(OFFSET(INDEX(M$13:M$1048576,COUNTA(M$13:M$1048576)),-2,0,3,1))/AVERAGE(OFFSET(INDEX(M$13:M$1048576,COUNTA(M$13:M$1048576)),-14,0,3,1)))-1 -> 0.26149831
A9: Worksheet 1a: Number of potential redundancies from HR1 forms by region, GB [note 6]
A10: This worksheet contains one table.
A11: Some shorthand is used in this table, [c] = confidential
A12: Month | B12: North East | C12: North West | D12: Yorkshire and The Humber | E12: East Midlands | F12: West Midlands | G12: East of England | H12: London | I12: South East | J12: South West | K12: Wales | L12: Scotland | M12: GB | Q12: Month-on-month | R12: Year-on-year
A13: 43556 | B13: 418 | C13: 1479 | D13: [c] | E13: 553 | F13: 843 | G13: 1551 | H13: 3133 | I13: 2079 | J13: 975 | K13: [c] | L13: 1750 | M13: 82454 | N13: =AVERAGE(M11:M13) -> 82454
A14: 43586 | B14: 1025 | C14: 2416 | D14: 6164 | E14: 982 | F14: 1452 | G14: 1769 | H14: 6616 | I14: 3734 | J14: 1764 | K14: 632 | L14: 1342 | M14: 27896 | N14: =AVERAGE(M12:M14) -> 55175 | Q14: =(M14/M13)-1 -> -0.66167803
A15: 43617 | B15: 1180 | C15: 1302 | D15: 2506 | E15: 1575 | F15: 2716 | G15: 649 | H15: 4664 | I15: 2690 | J15: 749 | K15: 1189 | L15: 1097 | M15: 20317 | N15: =AVERAGE(M13:M15) -> 43555.667 | Q15: =(M15/M14)-1 -> -0.2716877
A16: 43647 | B16: 846 | C16: 1712 | D16: 1598 | E16: 1337 | F16: 1814 | G16: 1101 | H16: 2654 | I16: 2893 | J16: 1174 | K16: 943 | L16: 1424 | M16: 17496 | N16: =AVERAGE(M14:M16) -> 21903 | Q16: =(M16/M15)-1 -> -0.13884924
A17: 43678 | B17: [c] | C17: 1208 | D17: 953 | E17: 437 | F17: 2474 | G17: [c] | H17: 3106 | I17: 1495 | J17: 719 | K17: 1199 | L17: 2374 | M17: 22079 | N17: =AVERAGE(M15:M17) -> 19964 | Q17: =(M17/M16)-1 -> 0.26194559
A18: 43709 | B18: 747 | C18: 5554 | D18: 1303 | E18: 797 | F18: 1153 | G18: 6274 | H18: 4060 | I18: 2501 | J18: 867 | K18: 449 | L18: 1263 | M18: 24968 | N18: =AVERAGE(M16:M18) -> 21514.333 | Q18: =(M18/M17)-1 -> 0.13084832
A19: 43739 | B19: 1240 | C19: 2100 | D19: 2600 | E19: 755 | F19: 2494 | G19: 1026 | H19: 4107 | I19: 1738 | J19: 2497 | K19: 809 | L19: 1578 | M19: 20944 | N19: =AVERAGE(M17:M19) -> 22663.667 | Q19: =(M19/M18)-1 -> -0.16116629
A20: 43770 | B20: 680 | C20: 1817 | D20: 733 | E20: 1125 | F20: 2200 | G20: 3872 | H20: 3246 | I20: 1721 | J20: 1088 | K20: 218 | L20: 1546 | M20: 18246 | N20: =AVERAGE(M18:M20) -> 21386 | Q20: =(M20/M19)-1 -> -0.12881971
A21: 43800 | B21: 919 | C21: 558 | D21: 931 | E21: 665 | F21: 764 | G21: 1069 | H21: 2241 | I21: 1385 | J21: 6382 | K21: 307 | L21: 1398 | M21: 16619 | N21: =AVERAGE(M19:M21) -> 18603 | Q21: =(M21/M20)-1 -> -0.089170229
A22: 43831 | B22: 1569 | C22: 2429 | D22: 4659 | E22: 1541 | F22: 1641 | G22: 1823 | H22: 4439 | I22: 3291 | J22: 2482 | K22: 1453 | L22: 1732 | M22: 27059 | N22: =AVERAGE(M20:M22) -> 20641.333 | Q22: =(M22/M21)-1 -> 0.62819664
A23: 43862 | B23: 557 | C23: 2202 | D23: 4949 | E23: 1397 | F23: 1570 | G23: 2850 | H23: 3231 | I23: 3034 | J23: 1098 | K23: 572 | L23: 3680 | M23: 25140 | N23: =AVERAGE(M21:M23) -> 22939.333 | Q23: =(M23/M22)-1 -> -0.070919103
A24: 43891 | B24: 1246 | C24: 3987 | D24: 2609 | E24: 2131 | F24: 3945 | G24: 3529 | H24: 11919 | I24: 2746 | J24: 2634 | K24: 1034 | L24: 3507 | M24: 39287 | N24: =AVERAGE(M22:M24) -> 30495.333 | Q24: =(M24/M23)-1 -> 0.56272872
A25: 43922 | B25: 782 | C25: 2651 | D25: 1055 | E25: 1620 | F25: 1798 | G25: 1232 | H25: 34983 | I25: 5686 | J25: 1093 | K25: 1343 | L25: 3632 | M25: 55875 | N25: =AVERAGE(M23:M25) -> 40100.667 | Q25: =(M25/M24)-1 -> 0.42222618
A26: 43952 | B26: 1302 | C26: 4451 | D26: 3188 | E26: 5347 | F26: 6575 | G26: 4288 | H26: 15634 | I26: 13852 | J26: 6772 | K26: 3499 | L26: 4382 | M26: 69290 | N26: =AVERAGE(M24:M26) -> 54817.333 | Q26: =(M26/M25)-1 -> 0.24008949 | R26: =(N26/N14)-1 -> -0.0064824045
A27: 43983 | B27: 3419 | C27: 21219 | D27: 8456 | E27: 6484 | F27: 9433 | G27: 6575 | H27: 50855 | I27: 14248 | J27: 11562 | K27: 3053 | L27: 9634 | M27: 144938 | N27: =AVERAGE(M25:M27) -> 90034.333 | Q27: =(M27/M26)-1 -> 1.0917593 | R27: =(N27/N15)-1 -> 1.0671095
A28: 44013 | B28: 2351 | C28: 14472 | D28: 6009 | E28: 4903 | F28: 7608 | G28: 6838 | H28: 36279 | I28: 10619 | J28: 7109 | K28: 4734 | L28: 7953 | M28: 108875 | N28: =AVERAGE(M26:M28) -> 107701 | Q28: =(M28/M27)-1 -> -0.24881674 | R28: =(N28/N16)-1 -> 3.9171803
A29: 44044 | B29: 2195 | C29: 4225 | D29: 2949 | E29: 2258 | F29: 3810 | G29: 3915 | H29: 15370 | I29: 7622 | J29: 3429 | K29: 1338 | L29: 2945 | M29: 50056 | N29: =AVERAGE(M27:M29) -> 101289.67 | Q29: =(M29/M28)-1 -> -0.5402434 | R29: =(N29/N17)-1 -> 4.0736158
A30: 44075 | B30: 2148 | C30: 5446 | D30: 5193 | E30: 3926 | F30: 5908 | G30: 5848 | H30: 15967 | I30: 9494 | J30: 6523 | K30: 3394 | L30: 4343 | M30: 68190 | N30: =AVERAGE(M28:M30) -> 75707 | Q30: =(M30/M29)-1 -> 0.36227425 | R30: =(N30/N18)-1 -> 2.5189099
A31: 44105 | B31: 945 | C31: 5168 | D31: 2527 | E31: 1470 | F31: 4123 | G31: 3167 | H31: 16289 | I31: 4896 | J31: 3341 | K31: 1255 | L31: 2921 | M31: 46102 | N31: =AVERAGE(M29:M31) -> 54782.667 | Q31: =(M31/M30)-1 -> -0.32391846 | R31: =(N31/N19)-1 -> 1.4172023
A32: 44136 | B32: 995 | C32: 2738 | D32: 2454 | E32: 2404 | F32: 2952 | G32: 2325 | H32: 8637 | I32: 5292 | J32: 2212 | K32: 545 | L32: 2374 | M32: 32928 | N32: =AVERAGE(M30:M32) -> 49073.333 | Q32: =(M32/M31)-1 -> -0.28575767 | R32: =(N32/N20)-1 -> 1.2946476
A33: 44166 | B33: 848 | C33: 1466 | D33: 1382 | E33: 1038 | F33: 1532 | G33: 1929 | H33: 6072 | I33: 2015 | J33: 1362 | K33: 783 | L33: 1860 | M33: 20287 | N33: =AVERAGE(M31:M33) -> 33105.667 | Q33: =(M33/M32)-1 -> -0.3838982 | R33: =(N33/N21)-1 -> 0.77958752
A34: 44197 | B34: 789 | C34: 1382 | D34: 880 | E34: 756 | F34: 689 | G34: 1388 | H34: 3792 | I34: 10160 | J34: 4719 | K34: 720 | L34: 1588 | M34: 26863 | N34: =AVERAGE(M32:M34) -> 26692.667 | Q34: =(M34/M33)-1 -> 0.32414847 | R34: =(N34/N22)-1 -> 0.29316582
A35: 44228 | B35: 221 | C35: 2431 | D35: 1211 | E35: 1770 | F35: 4052 | G35: 607 | H35: 6318 | I35: 3108 | J35: 895 | K35: 512 | L35: 1559 | M35: 22684 | N35: =AVERAGE(M33:M35) -> 23278 | Q35: =(M35/M34)-1 -> -0.15556714 | R35: =(N35/N23)-1 -> 0.014763579
A36: 44256 | B36: 611 | C36: 1966 | D36: 1010 | E36: 2163 | F36: 2719 | G36: 1017 | H36: 5804 | I36: 2387 | J36: 1735 | K36: 669 | L36: 1053 | M36: 21134 | N36: =AVERAGE(M34:M36) -> 23560.333 | Q36: =(M36/M35)-1 -> -0.068330101 | R36: =(N36/N24)-1 -> -0.22741184
A37: 44287 | B37: 408 | C37: 2040 | D37: 1111 | E37: 1284 | F37: 1254 | G37: 1084 | H37: 2107 | I37: 1431 | J37: 970 | K37: 594 | L37: 2866 | M37: 15149 | N37: =AVERAGE(M35:M37) -> 19655.667 | Q37: =(M37/M36)-1 -> -0.28319296 | R37: =(N37/N25)-1 -> -0.5098419
... A44: 44501 | B44: 492 | C44: 687 | D44: 1341 | E44: 428 | F44: 1113 | G44: 864 | H44: 3986 | I44: 1319 | J44: 805 | K44: 365 | L44: 724 | M44: 12124 | N44: =AVERAGE(M42:M44) -> 11765.333 | Q44: =(M44/M43)-1 -> -0.0038616383 | R44: =(N44/N32)-1 -> -0.76024997
A45: 44531 | B45: 294 | C45: 655 | D45: 650 | E45: 374 | F45: 630 | G45: [c] | H45: 946 | I45: 166 | J45: [c] | K45: 495 | L45: 1867 | M45: 6209 | N45: =AVERAGE(M43:M45) -> 10168 | Q45: =(M45/M44)-1 -> -0.48787529 | R45: =(N45/N33)-1 -> -0.69286225
A46: 44562 | B46: 325 | C46: 929 | D46: 434 | E46: 279 | F46: 610 | G46: 173 | H46: 2610 | I46: 996 | J46: 570 | K46: 381 | L46: 1562 | M46: 8869 | N46: =AVERAGE(M44:M46) -> 9067.3333 | Q46: =(M46/M45)-1 -> 0.42841037 | R46: =(N46/N34)-1 -> -0.6603062
A47: 44593 | B47: 514 | C47: 1060 | D47: 456 | E47: 1289 | F47: 1323 | G47: 1292 | H47: 6005 | I47: 2094 | J47: 1745 | K47: 746 | L47: 1579 | M47: 18103 | N47: =AVERAGE(M45:M47) -> 11060.333 | Q47: =(M47/M46)-1 -> 1.0411546 | R47: =(N47/N35)-1 -> -0.52485895
A48: 44621 | B48: 852 | C48: 1326 | D48: 1777 | E48: 1128 | F48: 960 | G48: 1444 | H48: 4062 | I48: 3707 | J48: 1101 | K48: 1377 | L48: 5676 | M48: 23410 | N48: =AVERAGE(M46:M48) -> 16794 | Q48: =(M48/M47)-1 -> 0.29315583 | R48: =(N48/N36)-1 -> -0.28719175
A49: 44652 | B49: 592 | C49: 1579 | D49: 1805 | E49: 627 | F49: 1861 | G49: 674 | H49: 3680 | I49: 1186 | J49: 629 | K49: 420 | L49: 1598 | M49: 14651 | N49: =AVERAGE(M47:M49) -> 18721.333 | Q49: =(M49/M48)-1 -> -0.37415634 | R49: =(N49/N37)-1 -> -0.047535062
A50: 44682 | B50: 341 | C50: 2276 | D50: 449 | E50: 1214 | F50: 1324 | G50: 380 | H50: 4562 | I50: 2639 | J50: 793 | K50: 277 | L50: 763 | M50: 15018 | N50: =AVERAGE(M48:M50) -> 17693 | Q50: =(M50/M49)-1 -> 0.025049485 | R50: =(N50/N38)-1 -> -0.011251234
A51: 44713 | B51: 557 | C51: 935 | D51: 745 | E51: 1171 | F51: 424 | G51: 689 | H51: 1579 | I51: 1226 | J51: 276 | K51: 480 | L51: 1918 | M51: 10000 | N51: =AVERAGE(M49:M51) -> 13223 | Q51: =(M51/M50)-1 -> -0.33413237 | R51: =(N51/N39)-1 -> -0.12759781
A52: 44743 | B52: 367 | C52: 1733 | D52: 1182 | E52: 507 | F52: 898 | G52: 718 | H52: 2195 | I52: 2090 | J52: 1050 | K52: 370 | L52: 523 | M52: 11633 | N52: =AVERAGE(M50:M52) -> 12217 | Q52: =(M52/M51)-1 -> 0.1633 | R52: =(N52/N40)-1 -> -0.14334798
A53: 44774 | B53: 828 | C53: 1903 | D53: 1312 | E53: 622 | F53: 1236 | G53: 442 | H53: 3441 | I53: 1912 | J53: 749 | K53: 671 | L53: 1590 | M53: 14706 | N53: =AVERAGE(M51:M53) -> 12113 | Q53: =(M53/M52)-1 -> 0.2641623 | R53: =(N53/N41)-1 -> 0.014205973
A54: 44805 | B54: 445 | C54: 1456 | D54: 1359 | E54: 2103 | F54: 789 | G54: 1269 | H54: 2209 | I54: 1004 | J54: 853 | K54: 681 | L54: 1526 | M54: 13694 | N54: =AVERAGE(M52:M54) -> 13344.333 | Q54: =(M54/M53)-1 -> -0.068815449 | R54: =(N54/N42)-1 -> 0.18060102
A55: 44835 | B55: [c] | C55: 1496 | D55: 1032 | E55: 713 | F55: 1479 | G55: 1280 | H55: 3141 | I55: 2197 | J55: 765 | K55: [c] | L55: 690 | M55: 13570 | N55: =AVERAGE(M53:M55) -> 13990 | Q55: =(M55/M54)-1 -> -0.0090550606 | R55: =(N55/N43)-1 -> 0.24843834
